Workbook

Sheet Read Me
A1: XP ↔ AE rebalance model (Enterprise)
A3: What this is
A4: Revised Enterprise assignments built to cut the number of AEs each XP works with, while holding the account cap, leadership holds, capacity and time-zone fit. Segmentation: every State and every Local ENT account is Enterprise (no special-entity overrides), plus DC. Source: Account Team export 9/21/26 (277 records, 209 countable, former customers excluded); AE mapping from the State map (6/12/26) and Local ENT map (6/30/26).
A6: What to fill in
A7: Column P on the Assignments tab (yellow). Enter Y where an account is Service Cloud Advanced; that marks it complex regardless of capability count. Example: an account with 5 capabilities and Y in column P counts as complex.
A8: Capabilities (column O) are counted from Account Product Categories, excluding Service Cloud, Engagement Cloud, Operations Cloud and anything named Credits. Websites, Portals, & Intranets counts as one. The counted list is in column U.
A9: You can also change any Revised XP (column G). Manager, time-zone fit, cap, AE count and every check recalculate.
A11: Rules applied
A12: Cap: no more than 17 countable accounts per Enterprise XP. Allocated child records do not count and travel with their parent.
A13: Holds: San Antonio with Steffany Amador; District of Columbia with Paige Wendle; Denver with a Savannah Lane report; Columbus with an Ashley Hill report. Preferences (9/21): Steffany takes Texas; Colleen keeps Los Angeles and GLACVCD rather than California state agencies.
A14: Carolina Prieto keeps her current Enterprise book except Connecticut and Maine, which go to Halena Martin. Her book is excluded from the 17-account cap and time-zone rule. Paige Wendle keeps Washington. The open XP2 headcount is Pacific time.
A15: Capacity: no more than one third of an XP's countable book may be complex (more than 7 capabilities, or Service Cloud Advanced).
... A44: Method, sources and full caveats: research/ENT-book-growth-tiering-hypothesis.md

Sheet XP Check
A1: XP | B1: Manager | C1: Level | D1: XP Time Zone | E1: Countable Accounts | F1: Cap | G1: Cap Status | H1: ARR | I1: AEs Worked With (Revised) | J1: AEs Worked With (WIP) | K1: Accounts Outside ±1 hr | L1: Complex Accounts | M1: Max Complex (1/3) | N1: Capacity Status | O1: Accounts Missing Capability Data | Q1: Account cap | R1: 17 | T1: Tier 1 Growth | U1: Tier 2 Expansion | V1: Tier 3 Defend | W1: Tier 4 Maintain | X1: Growth Share | Y1: Growth Load | Z1: Defend ARR
A2: =Lookups!A2 | B2: =Lookups!B2 | C2: =Lookups!C2 | D2: =Lookups!E2 | E2: =COUNTIFS(Assignments!$G$2:$G$278,A2,Assignments!$N$2:$N$278,"Yes") | F2: =$R$1 | G2: =IF(E2<=F2,"OK","OVER BY "&(E2-F2)) | H2: =SUMIFS(Assignments!$M$2:$M$278,Assignments!$G$2:$G$278,A2) | I2: =SUMPRODUCT((Assignments!$G$2:$G$278=A2)/COUNTIFS(Assignments!$G$2:$G$278,Assignments!$G$2:$G$278,Assignments!$E$2:$E$278,Assignments!$E$2:$E$278)) | J2: =SUMPRODUCT((Assignments!$F$2:$F$278=A2)/COUNTIFS(Assignments!$F$2:$F$278,Assignments!$F$2:$F$278,Assignments!$E$2:$E$278,Assignments!$E$2:$E$278)) | K2: =COUNTIFS(Assignments!$G$2:$G$278,A2,Assignments!$N$2:$N$278,"Yes",Assignments!$L$2:$L$278,"No") | L2: =COUNTIFS(Assignments!$G$2:$G$278,A2,Assignments!$Q$2:$Q$278,"Yes") | M2: =ROUNDDOWN(E2*$R$2,0) | N2: =IF(L2>M2,"OVER BY "&(L2-M2),IF(O2>0,"Pending data","OK")) | O2: =COUNTIFS(Assignments!$G$2:$G$278,A2,Assignments!$Q$2:$Q$278,"Pending") | Q2: Complex share limit | R2: 0.33333333 | T2: =COUNTIFS(Assignments!$G$2:$G$278,$A2,Assignments!$N$2:$N$278,"Yes",Assignments!$AB$2:$AB$278,1) | U2: =COUNTIFS(Assignments!$G$2:$G$278,$A2,Assignments!$N$2:$N$278,"Yes",Assignments!$AB$2:$AB$278,2) | V2: =COUNTIFS(Assignments!$G$2:$G$278,$A2,Assignments!$N$2:$N$278,"Yes",Assignments!$AB$2:$AB$278,3) | W2: =COUNTIFS(Assignments!$G$2:$G$278,$A2,Assignments!$N$2:$N$278,"Yes",Assignments!$AB$2:$AB$278,4) | X2: =IFERROR((T2+U2)/COUNTIFS(Assignments!$G$2:$G$278,$A2,Assignments!$N$2:$N$278,"Yes"),"") | Y2: =SUMPRODUCT((Assignments!$G$2:$G$278=$A2)*(Assignments!$N$2:$N$278="Yes")*Assignments!$AD$2:$AD$278) | Z2: =SUMIFS(Assignments!$M$2:$M$278,Assignments!$G$2:$G$278,$A2,Assignments!$N$2:$N$278,"Yes",Assignments!$AB$2:$AB$278,3)
A3: =Lookups!A3 | B3: =Lookups!B3 | C3: =Lookups!C3 | D3: =Lookups!E3 | E3: =COUNTIFS(Assignments!$G$2:$G$278,A3,Assignments!$N$2:$N$278,"Yes") | F3: =$R$1 | G3: =IF(E3<=F3,"OK","OVER BY "&(E3-F3)) | H3: =SUMIFS(Assignments!$M$2:$M$278,Assignments!$G$2:$G$278,A3) | I3: =SUMPRODUCT((Assignments!$G$2:$G$278=A3)/COUNTIFS(Assignments!$G$2:$G$278,Assignments!$G$2:$G$278,Assignments!$E$2:$E$278,Assignments!$E$2:$E$278)) | J3: =SUMPRODUCT((Assignments!$F$2:$F$278=A3)/COUNTIFS(Assignments!$F$2:$F$278,Assignments!$F$2:$F$278,Assignments!$E$2:$E$278,Assignments!$E$2:$E$278)) | K3: =COUNTIFS(Assignments!$G$2:$G$278,A3,Assignments!$N$2:$N$278,"Yes",Assignments!$L$2:$L$278,"No") | L3: =COUNTIFS(Assignments!$G$2:$G$278,A3,Assignments!$Q$2:$Q$278,"Yes") | M3: =ROUNDDOWN(E3*$R$2,0) | N3: =IF(L3>M3,"OVER BY "&(L3-M3),IF(O3>0,"Pending data","OK")) | O3: =COUNTIFS(Assignments!$G$2:$G$278,A3,Assignments!$Q$2:$Q$278,"Pending") | Q3: Complex threshold (capabilities greater than) | R3: =Assignments!$W$1 | T3: =COUNTIFS(Assignments!$G$2:$G$278,$A3,Assignments!$N$2:$N$278,"Yes",Assignments!$AB$2:$AB$278,1) | U3: =COUNTIFS(Assignments!$G$2:$G$278,$A3,Assignments!$N$2:$N$278,"Yes",Assignments!$AB$2:$AB$278,2) | V3: =COUNTIFS(Assignments!$G$2:$G$278,$A3,Assignments!$N$2:$N$278,"Yes",Assignments!$AB$2:$AB$278,3) | W3: =COUNTIFS(Assignments!$G$2:$G$278,$A3,Assignments!$N$2:$N$278,"Yes",Assignments!$AB$2:$AB$278,4) | X3: =IFERROR((T3+U3)/COUNTIFS(Assignments!$G$2:$G$278,$A3,Assignments!$N$2:$N$278,"Yes"),"") | Y3: =SUMPRODUCT((Assignments!$G$2:$G$278=$A3)*(Assignments!$N$2:$N$278="Yes")*Assignments!$AD$2:$AD$278) | Z3: =SUMIFS(Assignments!$M$2:$M$278,Assignments!$G$2:$G$278,$A3,Assignments!$N$2:$N$278,"Yes",Assignments!$AB$2:$AB$278,3)
A4: =Lookups!A4 | B4: =Lookups!B4 | C4: =Lookups!C4 | D4: =Lookups!E4 | E4: =COUNTIFS(Assignments!$G$2:$G$278,A4,Assignments!$N$2:$N$278,"Yes") | F4: =$R$1 | G4: =IF(E4<=F4,"OK","OVER BY "&(E4-F4)) | H4: =SUMIFS(Assignments!$M$2:$M$278,Assignments!$G$2:$G$278,A4) | I4: =SUMPRODUCT((Assignments!$G$2:$G$278=A4)/COUNTIFS(Assignments!$G$2:$G$278,Assignments!$G$2:$G$278,Assignments!$E$2:$E$278,Assignments!$E$2:$E$278)) | J4: =SUMPRODUCT((Assignments!$F$2:$F$278=A4)/COUNTIFS(Assignments!$F$2:$F$278,Assignments!$F$2:$F$278,Assignments!$E$2:$E$278,Assignments!$E$2:$E$278)) | K4: =COUNTIFS(Assignments!$G$2:$G$278,A4,Assignments!$N$2:$N$278,"Yes",Assignments!$L$2:$L$278,"No") | L4: =COUNTIFS(Assignments!$G$2:$G$278,A4,Assignments!$Q$2:$Q$278,"Yes") | M4: =ROUNDDOWN(E4*$R$2,0) | N4: =IF(L4>M4,"OVER BY "&(L4-M4),IF(O4>0,"Pending data","OK")) | O4: =COUNTIFS(Assignments!$G$2:$G$278,A4,Assignments!$Q$2:$Q$278,"Pending") | Q4: Cap, share limit and threshold are user-provided (9/21 instruction). Edit the threshold on Assignments cell W1. | T4: =COUNTIFS(Assignments!$G$2:$G$278,$A4,Assignments!$N$2:$N$278,"Yes",Assignments!$AB$2:$AB$278,1) | U4: =COUNTIFS(Assignments!$G$2:$G$278,$A4,Assignments!$N$2:$N$278,"Yes",Assignments!$AB$2:$AB$278,2) | V4: =COUNTIFS(Assignments!$G$2:$G$278,$A4,Assignments!$N$2:$N$278,"Yes",Assignments!$AB$2:$AB$278,3) | W4: =COUNTIFS(Assignments!$G$2:$G$278,$A4,Assignments!$N$2:$N$278,"Yes",Assignments!$AB$2:$AB$278,4) | X4: =IFERROR((T4+U4)/COUNTIFS(Assignments!$G$2:$G$278,$A4,Assignments!$N$2:$N$278,"Yes"),"") | Y4: =SUMPRODUCT((Assignments!$G$2:$G$278=$A4)*(Assignments!$N$2:$N$278="Yes")*Assignments!$AD$2:$AD$278) | Z4: =SUMIFS(Assignments!$M$2:$M$278,Assignments!$G$2:$G$278,$A4,Assignments!$N$2:$N$278,"Yes",Assignments!$AB$2:$AB$278,3)
A5: =Lookups!A5 | B5: =Lookups!B5 | C5: =Lookups!C5 | D5: =Lookups!E5 | E5: =COUNTIFS(Assignments!$G$2:$G$278,A5,Assignments!$N$2:$N$278,"Yes") | F5: =$R$1 | G5: =IF(E5<=F5,"OK","OVER BY "&(E5-F5)) | H5: =SUMIFS(Assignments!$M$2:$M$278,Assignments!$G$2:$G$278,A5) | I5: =SUMPRODUCT((Assignments!$G$2:$G$278=A5)/COUNTIFS(Assignments!$G$2:$G$278,Assignments!$G$2:$G$278,Assignments!$E$2:$E$278,Assignments!$E$2:$E$278)) | J5: =SUMPRODUCT((Assignments!$F$2:$F$278=A5)/COUNTIFS(Assignments!$F$2:$F$278,Assignments!$F$2:$F$278,Assignments!$E$2:$E$278,Assignments!$E$2:$E$278)) | K5: =COUNTIFS(Assignments!$G$2:$G$278,A5,Assignments!$N$2:$N$278,"Yes",Assignments!$L$2:$L$278,"No") | L5: =COUNTIFS(Assignments!$G$2:$G$278,A5,Assignments!$Q$2:$Q$278,"Yes") | M5: =ROUNDDOWN(E5*$R$2,0) | N5: =IF(L5>M5,"OVER BY "&(L5-M5),IF(O5>0,"Pending data","OK")) | O5: =COUNTIFS(Assignments!$G$2:$G$278,A5,Assignments!$Q$2:$Q$278,"Pending") | T5: =COUNTIFS(Assignments!$G$2:$G$278,$A5,Assignments!$N$2:$N$278,"Yes",Assignments!$AB$2:$AB$278,1) | U5: =COUNTIFS(Assignments!$G$2:$G$278,$A5,Assignments!$N$2:$N$278,"Yes",Assignments!$AB$2:$AB$278,2) | V5: =COUNTIFS(Assignments!$G$2:$G$278,$A5,Assignments!$N$2:$N$278,"Yes",Assignments!$AB$2:$AB$278,3) | W5: =COUNTIFS(Assignments!$G$2:$G$278,$A5,Assignments!$N$2:$N$278,"Yes",Assignments!$AB$2:$AB$278,4) | X5: =IFERROR((T5+U5)/COUNTIFS(Assignments!$G$2:$G$278,$A5,Assignments!$N$2:$N$278,"Yes"),"") | Y5: =SUMPRODUCT((Assignments!$G$2:$G$278=$A5)*(Assignments!$N$2:$N$278="Yes")*Assignments!$AD$2:$AD$278) | Z5: =SUMIFS(Assignments!$M$2:$M$278,Assignments!$G$2:$G$278,$A5,Assignments!$N$2:$N$278,"Yes",Assignments!$AB$2:$AB$278,3)
A6: =Lookups!A6 | B6: =Lookups!B6 | C6: =Lookups!C6 | D6: =Lookups!E6 | E6: =COUNTIFS(Assignments!$G$2:$G$278,A6,Assignments!$N$2:$N$278,"Yes") | F6: =$R$1 | G6: =IF(E6<=F6,"OK","OVER BY "&(E6-F6)) | H6: =SUMIFS(Assignments!$M$2:$M$278,Assignments!$G$2:$G$278,A6) | I6: =SUMPRODUCT((Assignments!$G$2:$G$278=A6)/COUNTIFS(Assignments!$G$2:$G$278,Assignments!$G$2:$G$278,Assignments!$E$2:$E$278,Assignments!$E$2:$E$278)) | J6: =SUMPRODUCT((Assignments!$F$2:$F$278=A6)/COUNTIFS(Assignments!$F$2:$F$278,Assignments!$F$2:$F$278,Assignments!$E$2:$E$278,Assignments!$E$2:$E$278)) | K6: =COUNTIFS(Assignments!$G$2:$G$278,A6,Assignments!$N$2:$N$278,"Yes",Assignments!$L$2:$L$278,"No") | L6: =COUNTIFS(Assignments!$G$2:$G$278,A6,Assignments!$Q$2:$Q$278,"Yes") | M6: =ROUNDDOWN(E6*$R$2,0) | N6: =IF(L6>M6,"OVER BY "&(L6-M6),IF(O6>0,"Pending data","OK")) | O6: =COUNTIFS(Assignments!$G$2:$G$278,A6,Assignments!$Q$2:$Q$278,"Pending") | T6: =COUNTIFS(Assignments!$G$2:$G$278,$A6,Assignments!$N$2:$N$278,"Yes",Assignments!$AB$2:$AB$278,1) | U6: =COUNTIFS(Assignments!$G$2:$G$278,$A6,Assignments!$N$2:$N$278,"Yes",Assignments!$AB$2:$AB$278,2) | V6: =COUNTIFS(Assignments!$G$2:$G$278,$A6,Assignments!$N$2:$N$278,"Yes",Assignments!$AB$2:$AB$278,3) | W6: =COUNTIFS(Assignments!$G$2:$G$278,$A6,Assignments!$N$2:$N$278,"Yes",Assignments!$AB$2:$AB$278,4) | X6: =IFERROR((T6+U6)/COUNTIFS(Assignments!$G$2:$G$278,$A6,Assignments!$N$2:$N$278,"Yes"),"") | Y6: =SUMPRODUCT((Assignments!$G$2:$G$278=$A6)*(Assignments!$N$2:$N$278="Yes")*Assignments!$AD$2:$AD$278) | Z6: =SUMIFS(Assignments!$M$2:$M$278,Assignments!$G$2:$G$278,$A6,Assignments!$N$2:$N$278,"Yes",Assignments!$AB$2:$AB$278,3)
A7: =Lookups!A7 | B7: =Lookups!B7 | C7: =Lookups!C7 | D7: =Lookups!E7 | E7: =COUNTIFS(Assignments!$G$2:$G$278,A7,Assignments!$N$2:$N$278,"Yes") | F7: =$R$1 | G7: =IF(E7<=F7,"OK","OVER BY "&(E7-F7)) | H7: =SUMIFS(Assignments!$M$2:$M$278,Assignments!$G$2:$G$278,A7) | I7: =SUMPRODUCT((Assignments!$G$2:$G$278=A7)/COUNTIFS(Assignments!$G$2:$G$278,Assignments!$G$2:$G$278,Assignments!$E$2:$E$278,Assignments!$E$2:$E$278)) | J7: =SUMPRODUCT((Assignments!$F$2:$F$278=A7)/COUNTIFS(Assignments!$F$2:$F$278,Assignments!$F$2:$F$278,Assignments!$E$2:$E$278,Assignments!$E$2:$E$278)) | K7: =COUNTIFS(Assignments!$G$2:$G$278,A7,Assignments!$N$2:$N$278,"Yes",Assignments!$L$2:$L$278,"No") | L7: =COUNTIFS(Assignments!$G$2:$G$278,A7,Assignments!$Q$2:$Q$278,"Yes") | M7: =ROUNDDOWN(E7*$R$2,0) | N7: =IF(L7>M7,"OVER BY "&(L7-M7),IF(O7>0,"Pending data","OK")) | O7: =COUNTIFS(Assignments!$G$2:$G$278,A7,Assignments!$Q$2:$Q$278,"Pending") | T7: =COUNTIFS(Assignments!$G$2:$G$278,$A7,Assignments!$N$2:$N$278,"Yes",Assignments!$AB$2:$AB$278,1) | U7: =COUNTIFS(Assignments!$G$2:$G$278,$A7,Assignments!$N$2:$N$278,"Yes",Assignments!$AB$2:$AB$278,2) | V7: =COUNTIFS(Assignments!$G$2:$G$278,$A7,Assignments!$N$2:$N$278,"Yes",Assignments!$AB$2:$AB$278,3) | W7: =COUNTIFS(Assignments!$G$2:$G$278,$A7,Assignments!$N$2:$N$278,"Yes",Assignments!$AB$2:$AB$278,4) | X7: =IFERROR((T7+U7)/COUNTIFS(Assignments!$G$2:$G$278,$A7,Assignments!$N$2:$N$278,"Yes"),"") | Y7: =SUMPRODUCT((Assignments!$G$2:$G$278=$A7)*(Assignments!$N$2:$N$278="Yes")*Assignments!$AD$2:$AD$278) | Z7: =SUMIFS(Assignments!$M$2:$M$278,Assignments!$G$2:$G$278,$A7,Assignments!$N$2:$N$278,"Yes",Assignments!$AB$2:$AB$278,3)
A8: =Lookups!A8 | B8: =Lookups!B8 | C8: =Lookups!C8 | D8: =Lookups!E8 | E8: =COUNTIFS(Assignments!$G$2:$G$278,A8,Assignments!$N$2:$N$278,"Yes") | F8: =$R$1 | G8: =IF(E8<=F8,"OK","OVER BY "&(E8-F8)) | H8: =SUMIFS(Assignments!$M$2:$M$278,Assignments!$G$2:$G$278,A8) | I8: =SUMPRODUCT((Assignments!$G$2:$G$278=A8)/COUNTIFS(Assignments!$G$2:$G$278,Assignments!$G$2:$G$278,Assignments!$E$2:$E$278,Assignments!$E$2:$E$278)) | J8: =SUMPRODUCT((Assignments!$F$2:$F$278=A8)/COUNTIFS(Assignments!$F$2:$F$278,Assignments!$F$2:$F$278,Assignments!$E$2:$E$278,Assignments!$E$2:$E$278)) | K8: =COUNTIFS(Assignments!$G$2:$G$278,A8,Assignments!$N$2:$N$278,"Yes",Assignments!$L$2:$L$278,"No") | L8: =COUNTIFS(Assignments!$G$2:$G$278,A8,Assignments!$Q$2:$Q$278,"Yes") | M8: =ROUNDDOWN(E8*$R$2,0) | N8: =IF(L8>M8,"OVER BY "&(L8-M8),IF(O8>0,"Pending data","OK")) | O8: =COUNTIFS(Assignments!$G$2:$G$278,A8,Assignments!$Q$2:$Q$278,"Pending") | T8: =COUNTIFS(Assignments!$G$2:$G$278,$A8,Assignments!$N$2:$N$278,"Yes",Assignments!$AB$2:$AB$278,1) | U8: =COUNTIFS(Assignments!$G$2:$G$278,$A8,Assignments!$N$2:$N$278,"Yes",Assignments!$AB$2:$AB$278,2) | V8: =COUNTIFS(Assignments!$G$2:$G$278,$A8,Assignments!$N$2:$N$278,"Yes",Assignments!$AB$2:$AB$278,3) | W8: =COUNTIFS(Assignments!$G$2:$G$278,$A8,Assignments!$N$2:$N$278,"Yes",Assignments!$AB$2:$AB$278,4) | X8: =IFERROR((T8+U8)/COUNTIFS(Assignments!$G$2:$G$278,$A8,Assignments!$N$2:$N$278,"Yes"),"") | Y8: =SUMPRODUCT((Assignments!$G$2:$G$278=$A8)*(Assignments!$N$2:$N$278="Yes")*Assignments!$AD$2:$AD$278) | Z8: =SUMIFS(Assignments!$M$2:$M$278,Assignments!$G$2:$G$278,$A8,Assignments!$N$2:$N$278,"Yes",Assignments!$AB$2:$AB$278,3)
A9: =Lookups!A9 | B9: =Lookups!B9 | C9: =Lookups!C9 | D9: =Lookups!E9 | E9: =COUNTIFS(Assignments!$G$2:$G$278,A9,Assignments!$N$2:$N$278,"Yes") | F9: =$R$1 | G9: =IF(E9<=F9,"OK","OVER BY "&(E9-F9)) | H9: =SUMIFS(Assignments!$M$2:$M$278,Assignments!$G$2:$G$278,A9) | I9: =SUMPRODUCT((Assignments!$G$2:$G$278=A9)/COUNTIFS(Assignments!$G$2:$G$278,Assignments!$G$2:$G$278,Assignments!$E$2:$E$278,Assignments!$E$2:$E$278)) | J9: =SUMPRODUCT((Assignments!$F$2:$F$278=A9)/COUNTIFS(Assignments!$F$2:$F$278,Assignments!$F$2:$F$278,Assignments!$E$2:$E$278,Assignments!$E$2:$E$278)) | K9: =COUNTIFS(Assignments!$G$2:$G$278,A9,Assignments!$N$2:$N$278,"Yes",Assignments!$L$2:$L$278,"No") | L9: =COUNTIFS(Assignments!$G$2:$G$278,A9,Assignments!$Q$2:$Q$278,"Yes") | M9: =ROUNDDOWN(E9*$R$2,0) | N9: =IF(L9>M9,"OVER BY "&(L9-M9),IF(O9>0,"Pending data","OK")) | O9: =COUNTIFS(Assignments!$G$2:$G$278,A9,Assignments!$Q$2:$Q$278,"Pending") | T9: =COUNTIFS(Assignments!$G$2:$G$278,$A9,Assignments!$N$2:$N$278,"Yes",Assignments!$AB$2:$AB$278,1) | U9: =COUNTIFS(Assignments!$G$2:$G$278,$A9,Assignments!$N$2:$N$278,"Yes",Assignments!$AB$2:$AB$278,2) | V9: =COUNTIFS(Assignments!$G$2:$G$278,$A9,Assignments!$N$2:$N$278,"Yes",Assignments!$AB$2:$AB$278,3) | W9: =COUNTIFS(Assignments!$G$2:$G$278,$A9,Assignments!$N$2:$N$278,"Yes",Assignments!$AB$2:$AB$278,4) | X9: =IFERROR((T9+U9)/COUNTIFS(Assignments!$G$2:$G$278,$A9,Assignments!$N$2:$N$278,"Yes"),"") | Y9: =SUMPRODUCT((Assignments!$G$2:$G$278=$A9)*(Assignments!$N$2:$N$278="Yes")*Assignments!$AD$2:$AD$278) | Z9: =SUMIFS(Assignments!$M$2:$M$278,Assignments!$G$2:$G$278,$A9,Assignments!$N$2:$N$278,"Yes",Assignments!$AB$2:$AB$278,3)
A10: =Lookups!A10 | B10: =Lookups!B10 | C10: =Lookups!C10 | D10: =Lookups!E10 | E10: =COUNTIFS(Assignments!$G$2:$G$278,A10,Assignments!$N$2:$N$278,"Yes") | F10: =$R$1 | G10: =IF(E10<=F10,"OK","OVER BY "&(E10-F10)) | H10: =SUMIFS(Assignments!$M$2:$M$278,Assignments!$G$2:$G$278,A10) | I10: =SUMPRODUCT((Assignments!$G$2:$G$278=A10)/COUNTIFS(Assignments!$G$2:$G$278,Assignments!$G$2:$G$278,Assignments!$E$2:$E$278,Assignments!$E$2:$E$278)) | J10: =SUMPRODUCT((Assignments!$F$2:$F$278=A10)/COUNTIFS(Assignments!$F$2:$F$278,Assignments!$F$2:$F$278,Assignments!$E$2:$E$278,Assignments!$E$2:$E$278)) | K10: =COUNTIFS(Assignments!$G$2:$G$278,A10,Assignments!$N$2:$N$278,"Yes",Assignments!$L$2:$L$278,"No") | L10: =COUNTIFS(Assignments!$G$2:$G$278,A10,Assignments!$Q$2:$Q$278,"Yes") | M10: =ROUNDDOWN(E10*$R$2,0) | N10: =IF(L10>M10,"OVER BY "&(L10-M10),IF(O10>0,"Pending data","OK")) | O10: =COUNTIFS(Assignments!$G$2:$G$278,A10,Assignments!$Q$2:$Q$278,"Pending") | T10: =COUNTIFS(Assignments!$G$2:$G$278,$A10,Assignments!$N$2:$N$278,"Yes",Assignments!$AB$2:$AB$278,1) | U10: =COUNTIFS(Assignments!$G$2:$G$278,$A10,Assignments!$N$2:$N$278,"Yes",Assignments!$AB$2:$AB$278,2) | V10: =COUNTIFS(Assignments!$G$2:$G$278,$A10,Assignments!$N$2:$N$278,"Yes",Assignments!$AB$2:$AB$278,3) | W10: =COUNTIFS(Assignments!$G$2:$G$278,$A10,Assignments!$N$2:$N$278,"Yes",Assignments!$AB$2:$AB$278,4) | X10: =IFERROR((T10+U10)/COUNTIFS(Assignments!$G$2:$G$278,$A10,Assignments!$N$2:$N$278,"Yes"),"") | Y10: =SUMPRODUCT((Assignments!$G$2:$G$278=$A10)*(Assignments!$N$2:$N$278="Yes")*Assignments!$AD$2:$AD$278) | Z10: =SUMIFS(Assignments!$M$2:$M$278,Assignments!$G$2:$G$278,$A10,Assignments!$N$2:$N$278,"Yes",Assignments!$AB$2:$AB$278,3)
A11: =Lookups!A11 | B11: =Lookups!B11 | C11: =Lookups!C11 | D11: =Lookups!E11 | E11: =COUNTIFS(Assignments!$G$2:$G$278,A11,Assignments!$N$2:$N$278,"Yes") | F11: =$R$1 | G11: =IF(E11<=F11,"OK","OVER BY "&(E11-F11)) | H11: =SUMIFS(Assignments!$M$2:$M$278,Assignments!$G$2:$G$278,A11) | I11: =SUMPRODUCT((Assignments!$G$2:$G$278=A11)/COUNTIFS(Assignments!$G$2:$G$278,Assignments!$G$2:$G$278,Assignments!$E$2:$E$278,Assignments!$E$2:$E$278)) | J11: =SUMPRODUCT((Assignments!$F$2:$F$278=A11)/COUNTIFS(Assignments!$F$2:$F$278,Assignments!$F$2:$F$278,Assignments!$E$2:$E$278,Assignments!$E$2:$E$278)) | K11: =COUNTIFS(Assignments!$G$2:$G$278,A11,Assignments!$N$2:$N$278,"Yes",Assignments!$L$2:$L$278,"No") | L11: =COUNTIFS(Assignments!$G$2:$G$278,A11,Assignments!$Q$2:$Q$278,"Yes") | M11: =ROUNDDOWN(E11*$R$2,0) | N11: =IF(L11>M11,"OVER BY "&(L11-M11),IF(O11>0,"Pending data","OK")) | O11: =COUNTIFS(Assignments!$G$2:$G$278,A11,Assignments!$Q$2:$Q$278,"Pending") | T11: =COUNTIFS(Assignments!$G$2:$G$278,$A11,Assignments!$N$2:$N$278,"Yes",Assignments!$AB$2:$AB$278,1) | U11: =COUNTIFS(Assignments!$G$2:$G$278,$A11,Assignments!$N$2:$N$278,"Yes",Assignments!$AB$2:$AB$278,2) | V11: =COUNTIFS(Assignments!$G$2:$G$278,$A11,Assignments!$N$2:$N$278,"Yes",Assignments!$AB$2:$AB$278,3) | W11: =COUNTIFS(Assignments!$G$2:$G$278,$A11,Assignments!$N$2:$N$278,"Yes",Assignments!$AB$2:$AB$278,4) | X11: =IFERROR((T11+U11)/COUNTIFS(Assignments!$G$2:$G$278,$A11,Assignments!$N$2:$N$278,"Yes"),"") | Y11: =SUMPRODUCT((Assignments!$G$2:$G$278=$A11)*(Assignments!$N$2:$N$278="Yes")*Assignments!$AD$2:$AD$278) | Z11: =SUMIFS(Assignments!$M$2:$M$278,Assignments!$G$2:$G$278,$A11,Assignments!$N$2:$N$278,"Yes",Assignments!$AB$2:$AB$278,3)
A12: =Lookups!A12 | B12: =Lookups!B12 | C12: =Lookups!C12 | D12: =Lookups!E12 | E12: =COUNTIFS(Assignments!$G$2:$G$278,A12,Assignments!$N$2:$N$278,"Yes") | F12: =$R$1 | G12: =IF(E12<=F12,"OK","OVER BY "&(E12-F12)) | H12: =SUMIFS(Assignments!$M$2:$M$278,Assignments!$G$2:$G$278,A12) | I12: =SUMPRODUCT((Assignments!$G$2:$G$278=A12)/COUNTIFS(Assignments!$G$2:$G$278,Assignments!$G$2:$G$278,Assignments!$E$2:$E$278,Assignments!$E$2:$E$278)) | J12: =SUMPRODUCT((Assignments!$F$2:$F$278=A12)/COUNTIFS(Assignments!$F$2:$F$278,Assignments!$F$2:$F$278,Assignments!$E$2:$E$278,Assignments!$E$2:$E$278)) | K12: =COUNTIFS(Assignments!$G$2:$G$278,A12,Assignments!$N$2:$N$278,"Yes",Assignments!$L$2:$L$278,"No") | L12: =COUNTIFS(Assignments!$G$2:$G$278,A12,Assignments!$Q$2:$Q$278,"Yes") | M12: =ROUNDDOWN(E12*$R$2,0) | N12: =IF(L12>M12,"OVER BY "&(L12-M12),IF(O12>0,"Pending data","OK")) | O12: =COUNTIFS(Assignments!$G$2:$G$278,A12,Assignments!$Q$2:$Q$278,"Pending") | T12: =COUNTIFS(Assignments!$G$2:$G$278,$A12,Assignments!$N$2:$N$278,"Yes",Assignments!$AB$2:$AB$278,1) | U12: =COUNTIFS(Assignments!$G$2:$G$278,$A12,Assignments!$N$2:$N$278,"Yes",Assignments!$AB$2:$AB$278,2) | V12: =COUNTIFS(Assignments!$G$2:$G$278,$A12,Assignments!$N$2:$N$278,"Yes",Assignments!$AB$2:$AB$278,3) | W12: =COUNTIFS(Assignments!$G$2:$G$278,$A12,Assignments!$N$2:$N$278,"Yes",Assignments!$AB$2:$AB$278,4) | X12: =IFERROR((T12+U12)/COUNTIFS(Assignments!$G$2:$G$278,$A12,Assignments!$N$2:$N$278,"Yes"),"") | Y12: =SUMPRODUCT((Assignments!$G$2:$G$278=$A12)*(Assignments!$N$2:$N$278="Yes")*Assignments!$AD$2:$AD$278) | Z12: =SUMIFS(Assignments!$M$2:$M$278,Assignments!$G$2:$G$278,$A12,Assignments!$N$2:$N$278,"Yes",Assignments!$AB$2:$AB$278,3)
A13: =Lookups!A13 | B13: =Lookups!B13 | C13: =Lookups!C13 | D13: =Lookups!E13 | E13: =COUNTIFS(Assignments!$G$2:$G$278,A13,Assignments!$N$2:$N$278,"Yes") | F13: =$R$1 | G13: =IF(E13<=F13,"OK","OVER BY "&(E13-F13)) | H13: =SUMIFS(Assignments!$M$2:$M$278,Assignments!$G$2:$G$278,A13) | I13: =SUMPRODUCT((Assignments!$G$2:$G$278=A13)/COUNTIFS(Assignments!$G$2:$G$278,Assignments!$G$2:$G$278,Assignments!$E$2:$E$278,Assignments!$E$2:$E$278)) | J13: =SUMPRODUCT((Assignments!$F$2:$F$278=A13)/COUNTIFS(Assignments!$F$2:$F$278,Assignments!$F$2:$F$278,Assignments!$E$2:$E$278,Assignments!$E$2:$E$278)) | K13: =COUNTIFS(Assignments!$G$2:$G$278,A13,Assignments!$N$2:$N$278,"Yes",Assignments!$L$2:$L$278,"No") | L13: =COUNTIFS(Assignments!$G$2:$G$278,A13,Assignments!$Q$2:$Q$278,"Yes") | M13: =ROUNDDOWN(E13*$R$2,0) | N13: =IF(L13>M13,"OVER BY "&(L13-M13),IF(O13>0,"Pending data","OK")) | O13: =COUNTIFS(Assignments!$G$2:$G$278,A13,Assignments!$Q$2:$Q$278,"Pending") | T13: =COUNTIFS(Assignments!$G$2:$G$278,$A13,Assignments!$N$2:$N$278,"Yes",Assignments!$AB$2:$AB$278,1) | U13: =COUNTIFS(Assignments!$G$2:$G$278,$A13,Assignments!$N$2:$N$278,"Yes",Assignments!$AB$2:$AB$278,2) | V13: =COUNTIFS(Assignments!$G$2:$G$278,$A13,Assignments!$N$2:$N$278,"Yes",Assignments!$AB$2:$AB$278,3) | W13: =COUNTIFS(Assignments!$G$2:$G$278,$A13,Assignments!$N$2:$N$278,"Yes",Assignments!$AB$2:$AB$278,4) | X13: =IFERROR((T13+U13)/COUNTIFS(Assignments!$G$2:$G$278,$A13,Assignments!$N$2:$N$278,"Yes"),"") | Y13: =SUMPRODUCT((Assignments!$G$2:$G$278=$A13)*(Assignments!$N$2:$N$278="Yes")*Assignments!$AD$2:$AD$278) | Z13: =SUMIFS(Assignments!$M$2:$M$278,Assignments!$G$2:$G$278,$A13,Assignments!$N$2:$N$278,"Yes",Assignments!$AB$2:$AB$278,3)
A14: =Lookups!A14 | B14: =Lookups!B14 | C14: =Lookups!C14 | D14: =Lookups!E14 | E14: =COUNTIFS(Assignments!$G$2:$G$278,A14,Assignments!$N$2:$N$278,"Yes") | F14: n/a | G14: Manager book | H14: =SUMIFS(Assignments!$M$2:$M$278,Assignments!$G$2:$G$278,A14) | I14: =SUMPRODUCT((Assignments!$G$2:$G$278=A14)/COUNTIFS(Assignments!$G$2:$G$278,Assignments!$G$2:$G$278,Assignments!$E$2:$E$278,Assignments!$E$2:$E$278)) | J14: =SUMPRODUCT((Assignments!$F$2:$F$278=A14)/COUNTIFS(Assignments!$F$2:$F$278,Assignments!$F$2:$F$278,Assignments!$E$2:$E$278,Assignments!$E$2:$E$278)) | K14: =COUNTIFS(Assignments!$G$2:$G$278,A14,Assignments!$N$2:$N$278,"Yes",Assignments!$L$2:$L$278,"No") | L14: =COUNTIFS(Assignments!$G$2:$G$278,A14,Assignments!$Q$2:$Q$278,"Yes") | M14: =ROUNDDOWN(E14*$R$2,0) | N14: =IF(L14>M14,"OVER BY "&(L14-M14),IF(O14>0,"Pending data","OK")) | O14: =COUNTIFS(Assignments!$G$2:$G$278,A14,Assignments!$Q$2:$Q$278,"Pending") | T14: =COUNTIFS(Assignments!$G$2:$G$278,$A14,Assignments!$N$2:$N$278,"Yes",Assignments!$AB$2:$AB$278,1) | U14: =COUNTIFS(Assignments!$G$2:$G$278,$A14,Assignments!$N$2:$N$278,"Yes",Assignments!$AB$2:$AB$278,2) | V14: =COUNTIFS(Assignments!$G$2:$G$278,$A14,Assignments!$N$2:$N$278,"Yes",Assignments!$AB$2:$AB$278,3) | W14: =COUNTIFS(Assignments!$G$2:$G$278,$A14,Assignments!$N$2:$N$278,"Yes",Assignments!$AB$2:$AB$278,4) | X14: =IFERROR((T14+U14)/COUNTIFS(Assignments!$G$2:$G$278,$A14,Assignments!$N$2:$N$278,"Yes"),"") | Y14: =SUMPRODUCT((Assignments!$G$2:$G$278=$A14)*(Assignments!$N$2:$N$278="Yes")*Assignments!$AD$2:$AD$278) | Z14: =SUMIFS(Assignments!$M$2:$M$278,Assignments!$G$2:$G$278,$A14,Assignments!$N$2:$N$278,"Yes",Assignments!$AB$2:$AB$278,3)
A15: Enterprise total | E15: =SUM(E2:E14) | H15: =SUM(H2:H14) | I15: =AVERAGE(I2:I13) | J15: =AVERAGEIF(J2:J13,">0") | K15: =SUM(K2:K14)
A16: AE counts include map gaps (open seats, no State AE shown, DC not on either map) as one counterpart each. Revised average covers the 12 XP seats including the open XP2; WIP average covers the 11 XPs with a WIP book. Both exclude Carolina Prieto's manager book.

Sheet Holds
A1: Hold | B1: Account | C1: Required | D1: Assigned XP | E1: Assigned Manager | F1: Result
A2: San Antonio stays with Steffany | B2: San Antonio, TX | C2: Steffany Amador | D2: =INDEX(Assignments!$G$2:$G$278,MATCH(B2,Assignments!$A$2:$A$278,0)) | E2: =INDEX(Assignments!$I$2:$I$278,MATCH(B2,Assignments!$A$2:$A$278,0)) | F2: =IF(D2=C2,"Met","BROKEN")
A3: DC stays with Paige | B3: District of Columbia | C3: Paige Wendle | D3: =INDEX(Assignments!$G$2:$G$278,MATCH(B3,Assignments!$A$2:$A$278,0)) | E3: =INDEX(Assignments!$I$2:$I$278,MATCH(B3,Assignments!$A$2:$A$278,0)) | F3: =IF(D3=C3,"Met","BROKEN")
A4: Denver held by a Savannah report | B4: Denver City and County, CO | C4: Savannah Lane | D4: =INDEX(Assignments!$G$2:$G$278,MATCH(B4,Assignments!$A$2:$A$278,0)) | E4: =INDEX(Assignments!$I$2:$I$278,MATCH(B4,Assignments!$A$2:$A$278,0)) | F4: =IF(E4=C4,"Met","BROKEN")
A5: Columbus held by an Ashley report | B5: Columbus OH | C5: Ashley Hill | D5: =INDEX(Assignments!$G$2:$G$278,MATCH(B5,Assignments!$A$2:$A$278,0)) | E5: =INDEX(Assignments!$I$2:$I$278,MATCH(B5,Assignments!$A$2:$A$278,0)) | F5: =IF(E5=C5,"Met","BROKEN")
A6: Colleen keeps Los Angeles | B6: Los Angeles, CA | C6: Colleen Moran | D6: =INDEX(Assignments!$G$2:$G$278,MATCH(B6,Assignments!$A$2:$A$278,0)) | E6: =INDEX(Assignments!$I$2:$I$278,MATCH(B6,Assignments!$A$2:$A$278,0)) | F6: =IF(D6=C6,"Met","BROKEN")
A7: Colleen keeps GLACVCD | B7: Greater Los Angeles County Vector Control District CA | C7: Colleen Moran | D7: =INDEX(Assignments!$G$2:$G$278,MATCH(B7,Assignments!$A$2:$A$278,0)) | E7: =INDEX(Assignments!$I$2:$I$278,MATCH(B7,Assignments!$A$2:$A$278,0)) | F7: =IF(D7=C7,"Met","BROKEN")
A8: Steffany takes Texas state | B8: Texas Department of Transportation (TXDOT) | C8: Steffany Amador | D8: =INDEX(Assignments!$G$2:$G$278,MATCH(B8,Assignments!$A$2:$A$278,0)) | E8: =INDEX(Assignments!$I$2:$I$278,MATCH(B8,Assignments!$A$2:$A$278,0)) | F8: =IF(D8=C8,"Met","BROKEN")
A9: Miami stays with Taylor | B9: Miami FL | C9: Taylor Roman | D9: =INDEX(Assignments!$G$2:$G$278,MATCH(B9,Assignments!$A$2:$A$278,0)) | E9: =INDEX(Assignments!$I$2:$I$278,MATCH(B9,Assignments!$A$2:$A$278,0)) | F9: =IF(D9=C9,"Met","BROKEN")
A10: Paige keeps Washington | B10: Washington Department of Transportation | C10: Paige Wendle | D10: =INDEX(Assignments!$G$2:$G$278,MATCH(B10,Assignments!$A$2:$A$278,0)) | E10: =INDEX(Assignments!$I$2:$I$278,MATCH(B10,Assignments!$A$2:$A$278,0)) | F10: =IF(D10=C10,"Met","BROKEN")
A11: Halena keeps Connecticut | B11: Connecticut Department of Administrative Services | C11: Halena Martin | D11: =INDEX(Assignments!$G$2:$G$278,MATCH(B11,Assignments!$A$2:$A$278,0)) | E11: =INDEX(Assignments!$I$2:$I$278,MATCH(B11,Assignments!$A$2:$A$278,0)) | F11: =IF(D11=C11,"Met","BROKEN")
A12: Halena keeps Maine | B12: Maine | C12: Halena Martin | D12: =INDEX(Assignments!$G$2:$G$278,MATCH(B12,Assignments!$A$2:$A$278,0)) | E12: =INDEX(Assignments!$I$2:$I$278,MATCH(B12,Assignments!$A$2:$A$278,0)) | F12: =IF(D12=C12,"Met","BROKEN")

Sheet AE Fan-out
A1: AE / SAM | B1: Map | C1: XPs Worked With (Revised) | D1: XPs Worked With (WIP) | E1: Countable Accounts | F1: ARR
A2: Andrew Wyzkoski | B2: Local ENT | C2: =SUMPRODUCT((Assignments!$E$2:$E$278=A2)/COUNTIFS(Assignments!$E$2:$E$278,Assignments!$E$2:$E$278,Assignments!$G$2:$G$278,Assignments!$G$2:$G$278)) | D2: =SUMPRODUCT((Assignments!$E$2:$E$278=A2)/COUNTIFS(Assignments!$E$2:$E$278,Assignments!$E$2:$E$278,Assignments!$F$2:$F$278,Assignments!$F$2:$F$278)) | E2: =COUNTIFS(Assignments!$E$2:$E$278,A2,Assignments!$N$2:$N$278,"Yes") | F2: =SUMIFS(Assignments!$M$2:$M$278,Assignments!$E$2:$E$278,A2)
A3: Austin Goodman | B3: Local ENT | C3: =SUMPRODUCT((Assignments!$E$2:$E$278=A3)/COUNTIFS(Assignments!$E$2:$E$278,Assignments!$E$2:$E$278,Assignments!$G$2:$G$278,Assignments!$G$2:$G$278)) | D3: =SUMPRODUCT((Assignments!$E$2:$E$278=A3)/COUNTIFS(Assignments!$E$2:$E$278,Assignments!$E$2:$E$278,Assignments!$F$2:$F$278,Assignments!$F$2:$F$278)) | E3: =COUNTIFS(Assignments!$E$2:$E$278,A3,Assignments!$N$2:$N$278,"Yes") | F3: =SUMIFS(Assignments!$M$2:$M$278,Assignments!$E$2:$E$278,A3)
A4: Bill Marshall | B4: Local ENT | C4: =SUMPRODUCT((Assignments!$E$2:$E$278=A4)/COUNTIFS(Assignments!$E$2:$E$278,Assignments!$E$2:$E$278,Assignments!$G$2:$G$278,Assignments!$G$2:$G$278)) | D4: =SUMPRODUCT((Assignments!$E$2:$E$278=A4)/COUNTIFS(Assignments!$E$2:$E$278,Assignments!$E$2:$E$278,Assignments!$F$2:$F$278,Assignments!$F$2:$F$278)) | E4: =COUNTIFS(Assignments!$E$2:$E$278,A4,Assignments!$N$2:$N$278,"Yes") | F4: =SUMIFS(Assignments!$M$2:$M$278,Assignments!$E$2:$E$278,A4)
A5: Carrie Breedlove | B5: Local ENT | C5: =SUMPRODUCT((Assignments!$E$2:$E$278=A5)/COUNTIFS(Assignments!$E$2:$E$278,Assignments!$E$2:$E$278,Assignments!$G$2:$G$278,Assignments!$G$2:$G$278)) | D5: =SUMPRODUCT((Assignments!$E$2:$E$278=A5)/COUNTIFS(Assignments!$E$2:$E$278,Assignments!$E$2:$E$278,Assignments!$F$2:$F$278,Assignments!$F$2:$F$278)) | E5: =COUNTIFS(Assignments!$E$2:$E$278,A5,Assignments!$N$2:$N$278,"Yes") | F5: =SUMIFS(Assignments!$M$2:$M$278,Assignments!$E$2:$E$278,A5)
A6: Carter Bradford | B6: Local ENT | C6: =SUMPRODUCT((Assignments!$E$2:$E$278=A6)/COUNTIFS(Assignments!$E$2:$E$278,Assignments!$E$2:$E$278,Assignments!$G$2:$G$278,Assignments!$G$2:$G$278)) | D6: =SUMPRODUCT((Assignments!$E$2:$E$278=A6)/COUNTIFS(Assignments!$E$2:$E$278,Assignments!$E$2:$E$278,Assignments!$F$2:$F$278,Assignments!$F$2:$F$278)) | E6: =COUNTIFS(Assignments!$E$2:$E$278,A6,Assignments!$N$2:$N$278,"Yes") | F6: =SUMIFS(Assignments!$M$2:$M$278,Assignments!$E$2:$E$278,A6)
A7: Cedric Simpkins | B7: Local ENT | C7: =SUMPRODUCT((Assignments!$E$2:$E$278=A7)/COUNTIFS(Assignments!$E$2:$E$278,Assignments!$E$2:$E$278,Assignments!$G$2:$G$278,Assignments!$G$2:$G$278)) | D7: =SUMPRODUCT((Assignments!$E$2:$E$278=A7)/COUNTIFS(Assignments!$E$2:$E$278,Assignments!$E$2:$E$278,Assignments!$F$2:$F$278,Assignments!$F$2:$F$278)) | E7: =COUNTIFS(Assignments!$E$2:$E$278,A7,Assignments!$N$2:$N$278,"Yes") | F7: =SUMIFS(Assignments!$M$2:$M$278,Assignments!$E$2:$E$278,A7)
A8: Conrad Taylor | B8: Local ENT | C8: =SUMPRODUCT((Assignments!$E$2:$E$278=A8)/COUNTIFS(Assignments!$E$2:$E$278,Assignments!$E$2:$E$278,Assignments!$G$2:$G$278,Assignments!$G$2:$G$278)) | D8: =SUMPRODUCT((Assignments!$E$2:$E$278=A8)/COUNTIFS(Assignments!$E$2:$E$278,Assignments!$E$2:$E$278,Assignments!$F$2:$F$278,Assignments!$F$2:$F$278)) | E8: =COUNTIFS(Assignments!$E$2:$E$278,A8,Assignments!$N$2:$N$278,"Yes") | F8: =SUMIFS(Assignments!$M$2:$M$278,Assignments!$E$2:$E$278,A8)
A9: Dallas SAM (open) | B9: Local ENT | C9: =SUMPRODUCT((Assignments!$E$2:$E$278=A9)/COUNTIFS(Assignments!$E$2:$E$278,Assignments!$E$2:$E$278,Assignments!$G$2:$G$278,Assignments!$G$2:$G$278)) | D9: =SUMPRODUCT((Assignments!$E$2:$E$278=A9)/COUNTIFS(Assignments!$E$2:$E$278,Assignments!$E$2:$E$278,Assignments!$F$2:$F$278,Assignments!$F$2:$F$278)) | E9: =COUNTIFS(Assignments!$E$2:$E$278,A9,Assignments!$N$2:$N$278,"Yes") | F9: =SUMIFS(Assignments!$M$2:$M$278,Assignments!$E$2:$E$278,A9)
A10: David Cliff | B10: Local ENT | C10: =SUMPRODUCT((Assignments!$E$2:$E$278=A10)/COUNTIFS(Assignments!$E$2:$E$278,Assignments!$E$2:$E$278,Assignments!$G$2:$G$278,Assignments!$G$2:$G$278)) | D10: =SUMPRODUCT((Assignments!$E$2:$E$278=A10)/COUNTIFS(Assignments!$E$2:$E$278,Assignments!$E$2:$E$278,Assignments!$F$2:$F$278,Assignments!$F$2:$F$278)) | E10: =COUNTIFS(Assignments!$E$2:$E$278,A10,Assignments!$N$2:$N$278,"Yes") | F10: =SUMIFS(Assignments!$M$2:$M$278,Assignments!$E$2:$E$278,A10)
A11: Desmond Davis | B11: Local ENT | C11: =SUMPRODUCT((Assignments!$E$2:$E$278=A11)/COUNTIFS(Assignments!$E$2:$E$278,Assignments!$E$2:$E$278,Assignments!$G$2:$G$278,Assignments!$G$2:$G$278)) | D11: =SUMPRODUCT((Assignments!$E$2:$E$278=A11)/COUNTIFS(Assignments!$E$2:$E$278,Assignments!$E$2:$E$278,Assignments!$F$2:$F$278,Assignments!$F$2:$F$278)) | E11: =COUNTIFS(Assignments!$E$2:$E$278,A11,Assignments!$N$2:$N$278,"Yes") | F11: =SUMIFS(Assignments!$M$2:$M$278,Assignments!$E$2:$E$278,A11)
A12: Jason Spanier | B12: Local ENT | C12: =SUMPRODUCT((Assignments!$E$2:$E$278=A12)/COUNTIFS(Assignments!$E$2:$E$278,Assignments!$E$2:$E$278,Assignments!$G$2:$G$278,Assignments!$G$2:$G$278)) | D12: =SUMPRODUCT((Assignments!$E$2:$E$278=A12)/COUNTIFS(Assignments!$E$2:$E$278,Assignments!$E$2:$E$278,Assignments!$F$2:$F$278,Assignments!$F$2:$F$278)) | E12: =COUNTIFS(Assignments!$E$2:$E$278,A12,Assignments!$N$2:$N$278,"Yes") | F12: =SUMIFS(Assignments!$M$2:$M$278,Assignments!$E$2:$E$278,A12)
A13: Jeff Gaisford | B13: Local ENT | C13: =SUMPRODUCT((Assignments!$E$2:$E$278=A13)/COUNTIFS(Assignments!$E$2:$E$278,Assignments!$E$2:$E$278,Assignments!$G$2:$G$278,Assignments!$G$2:$G$278)) | D13: =SUMPRODUCT((Assignments!$E$2:$E$278=A13)/COUNTIFS(Assignments!$E$2:$E$278,Assignments!$E$2:$E$278,Assignments!$F$2:$F$278,Assignments!$F$2:$F$278)) | E13: =COUNTIFS(Assignments!$E$2:$E$278,A13,Assignments!$N$2:$N$278,"Yes") | F13: =SUMIFS(Assignments!$M$2:$M$278,Assignments!$E$2:$E$278,A13)
... A39: Todd Bowers | B39: State | C39: =SUMPRODUCT((Assignments!$E$2:$E$278=A39)/COUNTIFS(Assignments!$E$2:$E$278,Assignments!$E$2:$E$278,Assignments!$G$2:$G$278,Assignments!$G$2:$G$278)) | D39: =SUMPRODUCT((Assignments!$E$2:$E$278=A39)/COUNTIFS(Assignments!$E$2:$E$278,Assignments!$E$2:$E$278,Assignments!$F$2:$F$278,Assignments!$F$2:$F$278)) | E39: =COUNTIFS(Assignments!$E$2:$E$278,A39,Assignments!$N$2:$N$278,"Yes") | F39: =SUMIFS(Assignments!$M$2:$M$278,Assignments!$E$2:$E$278,A39)

Sheet Growth Tiers
A1: State | B1: State-agency tier | C1: State-agency score | D1: State accts in book | E1: Local ENT tier | F1: Local ENT score | G1: Local accts in book | H1: Tiers disagree | I1: Jurisdictions 100k+ | J1: Held in this book | K1: Fiscal posture | L1: Rainy day % of spend | M1: Budget cycle | N1: IT modernization signal | O1: Grant environment | P1: ARPA cliff exposure | Q1: Purchasing access | R1: League channel taken | S1: Local capacity | T1: Property tax cap | U1: Population | V1: Pop % chg | W1: Domestic mig / 1k | X1: Research confidence | Y1: State ARR | Z1: Local ARR
A2: Texas | B2: A | C2: 82.4 | D2: 13 | E2: A | F2: 63.1 | G2: 10 | I2: 87 | J2: 10 | K2: Stable | L2: 23.3 | M2: Biennial | N2: funded | O2: thin | P2: med | Q2: strong | S2: typical | T2: yes | U2: 31709821 | V2: 1.25 | W2: 2.12 | X2: med | Y2: 2013624 | Z2: 2823033
A3: Virginia | B3: A | C3: 78.8 | D3: 1 | E3: A | F3: 63.9 | G3: 2 | I3: 18 | J3: 2 | K3: Stable | L3: 12.4 | M3: Biennial | N3: funded | O3: rich | P3: med | Q3: strong | S3: typical | U3: 8880107 | V3: 0.69 | W3: 0.71 | X3: high | Y3: 82354 | Z3: 831127
A4: Georgia | B4: A | C4: 77.5 | D4: 5 | E4: A | F4: 61.3 | G4: 2 | I4: 36 | J4: 2 | K4: Stable | L4: 15.4 | M4: Annual | N4: funded | O4: moderate | P4: med | Q4: present | R4: yes | S4: typical | U4: 11302748 | V4: 0.88 | W4: 2.42 | X4: low | Y4: 328232 | Z4: 406859
A5: Ohio | B5: A | C5: 74.7 | D5: 2 | E5: B | F5: 47 | G5: 3 | H5: yes | I5: 32 | J5: 3 | K5: Stable | L5: 12.6 | M5: Biennial | N5: funded | O5: moderate | P5: med | Q5: present | S5: constrained | U5: 11900510 | V5: 0.34 | W5: 1 | X5: med | Y5: 205769 | Z5: 1782145
A6: Pennsylvania | B6: A | C6: 72.6 | D6: 0 | E6: B | F6: 57.9 | G6: 3 | H6: yes | I6: 34 | J6: 3 | K6: Distressed | L6: 15.5 | M6: Annual | N6: funded | O6: moderate | P6: med | Q6: strong | S6: constrained | U6: 13059432 | V6: 0.1 | W6: -0.22 | X6: med | Y6: 0 | Z6: 286025
A7: Washington | B7: D | C7: 33.6 | D7: 5 | E7: A | F7: 70.1 | G7: 0 | H7: yes | I7: 23 | J7: 0 | K7: Distressed | L7: 2.8 | M7: Biennial | N7: none | O7: rich | P7: med | Q7: present | S7: typical | U7: 8001020 | V7: 0.92 | W7: 1.15 | X7: med | Y7: 994013 | Z7: 0
A8: Minnesota | B8: A | C8: 67.4 | D8: 4 | E8: A | F8: 58.5 | G8: 2 | I8: 15 | J8: 2 | K8: Constrained | L8: 10.6 | M8: Biennial | N8: funded | O8: rich | P8: med | Q8: strong | S8: constrained | U8: 5830405 | V8: 0.57 | W8: 1.42 | X8: med | Y8: 136946 | Z8: 403270
A9: New Mexico | B9: A | C9: 67 | D9: 7 | E9: B | F9: 53.4 | G9: 1 | H9: yes | I9: 8 | J9: 1 | K9: Expanding | L9: 24.1 | M9: Annual | N9: funded | O9: moderate | P9: med | Q9: present | S9: typical | U9: 2125498 | V9: -0.06 | W9: -1.07 | X9: low | Y9: 383693 | Z9: 90042
A10: Utah | B10: B | C10: 57.5 | D10: 1 | E10: A | F10: 66.6 | G10: 0 | H10: yes | I10: 11 | J10: 0 | K10: Stable | L10: 10.9 | M10: Annual | N10: none | O10: moderate | P10: low–med | Q10: present | S10: typical | U10: 3538904 | V10: 1.03 | W10: 0.94 | X10: med | Y10: 95340 | Z10: 0
A11: Montana | B11: A | C11: 65.8 | D11: 0 | E11: B | F11: 48.3 | G11: 0 | H11: yes | I11: 5 | J11: 0 | K11: Stable | L11: 15.3 | M11: Biennial | N11: funded | O11: thin | P11: high | Q11: present | S11: constrained | T11: yes | U11: 1144694 | V11: 0.63 | W11: 5.55 | X11: low | Y11: 0 | Z11: 0
A12: Massachusetts | B12: A | C12: 61.8 | D12: 1 | E12: A | F12: 65.3 | G12: 0 | I12: 20 | J12: 0 | K12: Stable | L12: 15.8 | M12: Annual | N12: none | O12: rich | P12: low | Q12: present | S12: typical | U12: 7154084 | V12: 0.22 | W12: -4.66 | X12: med | Y12: 214644 | Z12: 0
A13: Arkansas | B13: A | C13: 65.2 | D13: 0 | E13: B | F13: 55.3 | G13: 0 | H13: yes | I13: 9 | J13: 0 | K13: Expanding | L13: 27.9 | M13: Annual | N13: none | O13: thin | P13: med | Q13: coop_only | S13: typical | U13: 3114791 | V13: 0.6 | W13: 4.65 | X13: low | Y13: 0 | Z13: 0
A14: New York | B14: B | C14: 57 | D14: 2 | E14: A | F14: 64.9 | G14: 3 | H14: yes | I14: 34 | J14: 3 | K14: Constrained | L14: 7.7 | M14: Annual | N14: none | O14: rich | P14: low (state) / med (nyc & locals) | Q14: strong | S14: constrained | U14: 20002427 | V14: 0.01 | W14: -6.88 | X14: med | Y14: 1632532 | Z14: 226709
A15: North Carolina | B15: A | C15: 62.1 | D15: 0 | E15: A | F15: 64.9 | G15: 2 | I15: 39 | J15: 2 | K15: Stable | L15: 11.1 | M15: Biennial | N15: none | O15: moderate | P15: med | Q15: present | R15: yes | S15: constrained | U15: 11197968 | V15: 1.32 | W15: 7.51 | X15: low | Y15: 0 | Z15: 202481
A16: Indiana | B16: B | C16: 51.8 | D16: 0 | E16: A | F16: 63.7 | G16: 1 | H16: yes | I16: 24 | J16: 1 | K16: Constrained | L16: 9.5 | M16: Biennial | N16: none | O16: moderate | P16: med | Q16: present | S16: typical | U16: 6973333 | V16: 0.56 | W16: 1.75 | X16: low | Y16: 0 | Z16: 70972
A17: Michigan | B17: A | C17: 62.7 | D17: 0 | E17: B | F17: 49.5 | G17: 1 | H17: yes | I17: 27 | J17: 1 | K17: Constrained | L17: 13.1 | M17: Annual | N17: none | O17: moderate | P17: high | Q17: strong | S17: constrained | U17: 10127884 | V17: 0.28 | W17: 0.18 | X17: med | Y17: 0 | Z17: 489446
A18: California | B18: B | C18: 54.4 | D18: 16 | E18: A | F18: 62.3 | G18: 10 | H18: yes | I18: 112 | J18: 10 | K18: Distressed | L18: 17.4 | M18: Annual | N18: neutral | O18: rich | P18: low–med | Q18: present | R18: yes | S18: typical | U18: 39355309 | V18: -0.02 | W18: -5.82 | X18: med | Y18: 3303459 | Z18: 3907669
A19: Florida | B19: A | C19: 62 | D19: 4 | E19: B | F19: 57.8 | G19: 13 | H19: yes | I19: 63 | J19: 13 | K19: Constrained | L19: 8.6 | M19: Annual | N19: governance | O19: rich | P19: med | Q19: present | S19: typical | T19: yes | U19: 23462518 | V19: 0.85 | W19: 0.96 | X19: med | Y19: 505348 | Z19: 2567452
A20: Idaho | B20: C | C20: 42.3 | D20: 1 | E20: A | F20: 59.7 | G20: 0 | H20: yes | I20: 7 | J20: 0 | K20: Constrained | L20: 21.3 | M20: Annual | N20: headwind | O20: thin | P20: med | Q20: coop_only | S20: typical | U20: 2029733 | V20: 1.44 | W20: 9.81 | X20: low | Y20: 88765 | Z20: 0
A21: Alabama | B21: A | C21: 58.4 | D21: 1 | E21: B | F21: 55.1 | G21: 1 | H21: yes | I21: 19 | J21: 1 | K21: Stable | L21: 19.5 | M21: Annual | N21: none | O21: moderate | P21: med | Q21: coop_only | R21: yes | S21: typical | U21: 5193088 | V21: 0.58 | W21: 4.5 | X21: low | Y21: 75086 | Z21: 57780
A22: Wisconsin | B22: B | C22: 57.8 | D22: 2 | E22: C | F22: 44.7 | G22: 3 | H22: yes | I22: 19 | J22: 3 | K22: Stable | L22: 9.3 | M22: Biennial | N22: none | O22: moderate | P22: high | Q22: present | R22: yes | S22: constrained | U22: 5972787 | V22: 0.26 | W22: 1.17 | X22: med | Y22: 53544 | Z22: 429986
A23: Oklahoma | B23: B | C23: 57.6 | D23: 2 | E23: B | F23: 52 | G23: 1 | I23: 11 | J23: 1 | K23: Constrained | L23: 17.1 | M23: Annual | N23: none | O23: thin | P23: high | Q23: strong | S23: typical | U23: 4123288 | V23: 0.62 | W23: 3.51 | X23: med | Y23: 79354 | Z23: 300031
A24: Arizona | B24: C | C24: 46.6 | D24: 7 | E24: B | F24: 57.3 | G24: 3 | H24: yes | I24: 23 | J24: 3 | K24: Constrained | L24: 9.1 | M24: Annual | N24: headwind | O24: moderate | P24: med | Q24: present | S24: typical | U24: 7623818 | V24: 0.89 | W24: 4.08 | X24: low | Y24: 598447 | Z24: 366230
A25: Maryland | B25: B | C25: 52 | D25: 0 | E25: B | F25: 56.3 | G25: 2 | I25: 15 | J25: 2 | K25: Distressed | L25: 7.8 | M25: Annual | N25: headwind | O25: rich | P25: med | Q25: strong | R25: yes | S25: typical | U25: 6265347 | V25: 0.32 | W25: -1.94 | X25: high | Y25: 0 | Z25: 256954
A26: Mississippi | B26: B | C26: 54.8 | D26: 0 | E26: C | F26: 46.9 | G26: 0 | H26: yes | I26: 7 | J26: 0 | K26: Stable | L26: 9.9 | M26: Annual | N26: none | O26: thin | P26: high | Q26: coop_only | S26: typical | U26: 2954160 | V26: 0.14 | W26: -0.31 | X26: med | Y26: 0 | Z26: 0
A27: Delaware | B27: C | C27: 41 | D27: 0 | E27: B | F27: 54.2 | G27: 0 | H27: yes | I27: 3 | J27: 0 | K27: Constrained | L27: 5.1 | M27: Annual | N27: none | O27: moderate | P27: high | Q27: coop_only | S27: typical | U27: 1059952 | V27: 0.94 | W27: 6.47 | X27: low | Y27: 0 | Z27: 0
A28: New Jersey | B28: C | C28: 42.5 | D28: 2 | E28: B | F28: 54 | G28: 1 | H28: yes | I28: 23 | J28: 1 | K28: Distressed | L28: 0 | M28: Annual | N28: none | O28: rich | P28: high | Q28: coop_only | S28: typical | U28: 9548215 | V28: 0.44 | W28: -3.92 | X28: high | Y28: 227906 | Z28: 23334
A29: Nevada | B29: B | C29: 49.1 | D29: 3 | E29: B | F29: 53.3 | G29: 0 | I29: 7 | J29: 0 | K29: Stable | L29: 18.5 | M29: Biennial | N29: none | O29: moderate | P29: high | Q29: coop_only | S29: typical | U29: 3282188 | V29: 0.88 | W29: 4.54 | X29: med | Y29: 163668 | Z29: 0
A30: Maine | B30: D | C30: 26.9 | D30: 2 | E30: B | F30: 52.9 | G30: 0 | H30: yes | I30: 5 | J30: 0 | K30: Constrained | L30: 13.2 | M30: Biennial | N30: none | O30: moderate | P30: high | Q30: coop_only | S30: constrained | U30: 1414874 | V30: 0.46 | W30: 5.23 | X30: med | Y30: 356387 | Z30: 0
A31: Illinois | B31: B | C31: 52.2 | D31: 1 | E31: C | F31: 40 | G31: 4 | H31: yes | I31: 27 | J31: 4 | K31: Constrained | L31: 4.5 | M31: Annual | N31: none | O31: moderate | P31: med | Q31: coop_only | S31: constrained | U31: 12719141 | V31: 0.13 | W31: -3.15 | X31: med | Y31: 76184 | Z31: 1666026
A32: District of Columbia | B32: D | C32: 34.3 | D32: 0 | E32: B | F32: 51.7 | G32: 1 | H32: yes | I32: 1 | J32: 0 | K32: Distressed | L32: 8.2 | M32: Annual | N32: none | O32: moderate | P32: low | Q32: coop_only | S32: typical | U32: 693645 | V32: 0.34 | W32: -5.95 | X32: med | Y32: 0 | Z32: 0
A33: Connecticut | B33: C | C33: 40.5 | D33: 4 | E33: B | F33: 51.4 | G33: 0 | H33: yes | I33: 13 | J33: 0 | K33: Stable | L33: 18.8 | M33: Biennial | N33: none | O33: moderate | P33: med | Q33: coop_only | R33: yes | S33: typical | U33: 3688496 | V33: 0.38 | W33: -1.61 | X33: med | Y33: 745164 | Z33: 0
A34: South Carolina | B34: B | C34: 51 | D34: 0 | E34: B | F34: 51.3 | G34: 1 | I34: 19 | J34: 1 | K34: Constrained | L34: 13.8 | M34: Annual | N34: none | O34: thin | P34: high | Q34: coop_only | R34: yes | S34: typical | U34: 5570274 | V34: 1.46 | W34: 11.96 | X34: med | Y34: 0 | Z34: 237874
A35: Iowa | B35: C | C35: 42.3 | D35: 1 | E35: B | F35: 50.3 | G35: 1 | H35: yes | I35: 11 | J35: 1 | K35: Constrained | L35: 9 | M35: Annual | N35: none | O35: moderate | P35: med | Q35: strong | R35: yes | S35: constrained | U35: 3238387 | V35: 0.25 | W35: -0.3 | X35: low | Y35: 511995 | Z35: 89731
A36: Colorado | B36: C | C36: 42.5 | D36: 4 | E36: B | F36: 50.1 | G36: 2 | H36: yes | I36: 24 | J36: 2 | K36: Distressed | L36: 9 | M36: Annual | N36: headwind | O36: rich | P36: med | Q36: present | S36: typical | T36: yes | U36: 6012561 | V36: 0.4 | W36: -2.01 | X36: high | Y36: 307639 | Z36: 702396
A37: South Dakota | B37: B | C37: 49.9 | D37: 0 | E37: B | F37: 48.8 | G37: 0 | I37: 3 | J37: 0 | K37: Stable | L37: 12.4 | M37: Annual | N37: none | O37: thin | P37: high | Q37: coop_only | S37: constrained | U37: 935094 | V37: 0.86 | W37: 2.32 | X37: low | Y37: 0 | Z37: 0
A38: Kentucky | B38: D | C38: 34.7 | D38: 12 | E38: B | F38: 49.1 | G38: 1 | H38: yes | I38: 11 | J38: 1 | K38: Constrained | L38: 22.5 | M38: Biennial | N38: none | O38: moderate | P38: med | Q38: coop_only | S38: typical | U38: 4606864 | V38: 0.5 | W38: 1.58 | X38: low | Y38: 936944 | Z38: 72050
A39: Rhode Island | B39: C | C39: 41.3 | D39: 0 | E39: B | F39: 48.8 | G39: 0 | H39: yes | I39: 4 | J39: 0 | K39: Constrained | L39: 5.2 | M39: Annual | N39: none | O39: moderate | P39: high | Q39: coop_only | S39: typical | U39: 1114521 | V39: 0.37 | W39: -1.39 | X39: low | Y39: 0 | Z39: 0
A40: Tennessee | B40: B | C40: 47.9 | D40: 1 | E40: B | F40: 48.7 | G40: 2 | I40: 23 | J40: 2 | K40: Constrained | L40: 8.5 | M40: Annual | N40: none | O40: moderate | P40: high | Q40: coop_only | R40: yes | S40: typical | U40: 7315076 | V40: 0.88 | W40: 5.79 | X40: med | Y40: 244500 | Z40: 667398
A41: Kansas | B41: C | C41: 44.1 | D41: 4 | E41: B | F41: 48.1 | G41: 0 | H41: yes | I41: 10 | J41: 0 | K41: Stable | L41: 18.1 | M41: Annual | N41: none | O41: thin | P41: high | Q41: coop_only | S41: constrained | U41: 2977220 | V41: 0.4 | W41: -0.17 | X41: low | Y41: 402855 | Z41: 0
A42: New Hampshire | B42: C | C42: 40.4 | D42: 0 | E42: B | F42: 48 | G42: 0 | H42: yes | I42: 5 | J42: 0 | K42: Constrained | L42: 11.5 | M42: Biennial | N42: none | O42: thin | P42: high | Q42: coop_only | S42: constrained | U42: 1415342 | V42: 0.48 | W42: 4.63 | X42: med | Y42: 0 | Z42: 0
A43: West Virginia | B43: B | C43: 47.9 | D43: 0 | E43: C | F43: 43.2 | G43: 0 | H43: yes | I43: 3 | J43: 0 | K43: Constrained | L43: 23.5 | M43: Annual | N43: none | O43: thin | P43: high | Q43: coop_only | S43: constrained | U43: 1766147 | V43: -0.07 | W43: 3.63 | X43: med | Y43: 0 | Z43: 0
A44: Wyoming | B44: B | C44: 47.3 | D44: 0 | E44: C | F44: 43.1 | G44: 0 | H44: yes | I44: 1 | J44: 0 | K44: Stable | L44: 70.3 | M44: Biennial | N44: none | O44: thin | P44: high | Q44: coop_only | S44: constrained | U44: 588753 | V44: 0.35 | W44: 2.5 | X44: low | Y44: 0 | Z44: 0
A45: Oregon | B45: C | C45: 42 | D45: 4 | E45: C | F45: 46 | G45: 2 | I45: 16 | J45: 2 | K45: Constrained | L45: 17.1 | M45: Biennial | N45: none | O45: moderate | P45: med | Q45: coop_only | S45: typical | U45: 4273586 | V45: 0.19 | W45: 0.52 | X45: low | Y45: 231897 | Z45: 410694
A46: Louisiana | B46: C | C46: 45.9 | D46: 3 | E46: C | F46: 40.6 | G46: 3 | I46: 18 | J46: 3 | K46: Constrained | L46: 9.8 | M46: Annual | N46: none | O46: moderate | P46: high | Q46: coop_only | S46: typical | U46: 4618189 | V46: 0.07 | W46: -3.12 | X46: low | Y46: 158911 | Z46: 569777
A47: Hawai'i | B47: C | C47: 41.2 | D47: 0 | E47: C | F47: 43.3 | G47: 0 | I47: 4 | J47: 0 | K47: Constrained | L47: 14.5 | M47: Biennial | N47: none | O47: moderate | P47: high | Q47: coop_only | S47: typical | U47: 1432820 | V47: -0.15 | W47: -6.19 | X47: low | Y47: 0 | Z47: 0
A48: Nebraska | B48: C | C48: 37.5 | D48: 0 | E48: C | F48: 42.8 | G48: 1 | I48: 5 | J48: 1 | K48: Distressed | L48: 15.2 | M48: Biennial | N48: none | O48: thin | P48: med | Q48: coop_only | S48: constrained | T48: yes | U48: 2018006 | V48: 0.62 | W48: -0.18 | X48: low | Y48: 0 | Z48: 28683
A49: North Dakota | B49: D | C49: 34.7 | D49: 7 | E49: C | F49: 42.5 | G49: 0 | H49: yes | I49: 3 | J49: 0 | K49: Stable | L49: 30 | M49: Biennial | N49: none | O49: moderate | P49: high | Q49: coop_only | S49: constrained | T49: yes | U49: 799358 | V49: 0.75 | W49: 0.64 | X49: med | Y49: 398584 | Z49: 0
A50: Missouri | B50: C | C50: 42.3 | D50: 3 | E50: C | F50: 41.9 | G50: 2 | I50: 18 | J50: 2 | K50: Distressed | L50: 5.8 | M50: Annual | N50: none | O50: thin | P50: med | Q50: coop_only | S50: constrained | U50: 6270541 | V50: 0.43 | W50: 2.24 | X50: low | Y50: 126709 | Z50: 660757
A51: Alaska | B51: C | C51: 38.6 | D51: 0 | E51: C | F51: 41.9 | G51: 0 | I51: 3 | J51: 0 | K51: Distressed | L51: 51.7 | M51: Annual | N51: none | O51: moderate | P51: high | Q51: coop_only | S51: typical | U51: 737270 | V51: 0.1 | W51: -6.14 | X51: low | Y51: 0 | Z51: 0
A52: Vermont | B52: C | C52: 41.8 | D52: 0 | E52: C | F52: 40.7 | G52: 0 | I52: 1 | J52: 0 | K52: Constrained | L52: 18.2 | M52: Annual | N52: none | O52: moderate | P52: high | Q52: coop_only | S52: constrained | U52: 644663 | V52: -0.29 | W52: -1.13 | X52: low | Y52: 0 | Z52: 0

Sheet Lookups
A1: XP | B1: Manager (Scenario A) | C1: Level | D1: Location | E1: XP Time Zone | G1: Time Zone | H1: Offset
A2: Paige Wendle | B2: Savannah Lane | C2: XP3 | D2: Idaho | E2: MT | G2: PT | H2: 0
A3: Colleen Moran | B3: Ashley Hill | C3: XP3 | D3: Nevada | E3: PT | G3: MT | H3: 1
A4: Open XP2 (PT) | B4: TBD | C4: XP2 | D4: Open headcount, Pacific | E4: PT | G4: CT | H4: 2
A5: Cody Nichols | B5: Ashley Hill | C5: XP1 | D5: Costa Rica | E5: CT | G5: ET | H5: 3
A6: Alejandro Solano | B6: Ashley Hill | C6: XP1 | D6: Costa Rica | E6: CT
A7: Taylor Roman | B7: Savannah Lane | C7: XP3 | D7: Miami, FL | E7: ET
A8: Marcy Castro | B8: Ashley Hill | C8: XP1 | D8: Costa Rica | E8: CT | G8: Offsets are hours relative to Pacific. Source: standard US time zones; Costa Rica treated as Central.
A9: Brooke Minichino | B9: Savannah Lane | C9: XP2 | D9: Washington, DC | E9: ET
A10: Steffany Amador | B10: Ashley Hill | C10: XP3 | D10: North Carolina | E10: ET
A11: Halena Martin | B11: Savannah Lane | C11: XP3 | D11: Pennsylvania | E11: ET
A12: Andy O'Brien | B12: Savannah Lane | C12: XP3 | D12: Virginia | E12: ET
A13: Carolina Cambronero | B13: Savannah Lane | C13: XP3 | D13: Costa Rica | E13: CT
A14: Carolina Prieto | B14: Carolina Prieto (manager book) | C14: Manager | D14: Not specified | E14: n/a

Sheet Assignments
A1: Account Name | B1: Ultimate Parent | C1: State | D1: Map | E1: AE / SAM | F1: WIP Proposed XP | G1: Revised XP | H1: Moved vs WIP | I1: Revised Manager | J1: XP Time Zone | K1: Account Time Zone | L1: Time Zone Fit | M1: ARR | N1: Counts vs Cap | O1: Capabilities (#) | P1: Service Cloud Advanced (Y/N) | Q1: Complex Account | R1: Mapping Note | S1: Current XP (9/21 export) | T1: Market Segment (export) | U1: Capabilities Counted | V1: Complex threshold | W1: 7 | X1: Territory Tier | Y1: Territory Score | Z1: Capability Whitespace | AA1: Growth Potential | AB1: Growth Tier | AC1: Growth Tier Label | AD1: Growth Load | AE1: Capability Data
A2: Denver City and County, CO | B2: Denver City and County, CO | C2: CO | D2: Local ENT | E2: David Cliff | F2: Steffany Amador | G2: Paige Wendle | H2: =IF(F2="(not in WIP)","New to Enterprise",IF(F2=G2,"No","Yes")) | I2: =IFERROR(INDEX(Lookups!$B$2:$B$14,MATCH(G2,Lookups!$A$2:$A$14,0)),"Not found") | J2: =IFERROR(INDEX(Lookups!$E$2:$E$14,MATCH(G2,Lookups!$A$2:$A$14,0)),"") | K2: MT | L2: =IF(J2="n/a","n/a",IFERROR(IF(ABS(INDEX(Lookups!$H$2:$H$5,MATCH(J2,Lookups!$G$2:$G$5,0))-INDEX(Lookups!$H$2:$H$5,MATCH(K2,Lookups!$G$2:$G$5,0)))<=1,"Yes","No"),"Check")) | M2: 370850.21 | N2: Yes | O2: 4 | Q2: =IF(N2<>"Yes","n/a",IF(OR(AND(O2<>"",O2>$W$1),P2="Y"),"Yes",IF(O2<>"","No","Pending"))) | S2: Steffany Amador | T2: Local ENT | U2: Agenda & Video, Forms & Workflows, Websites, Portals, & Intranets, govXCloud | X2: B | Y2: 50.1 | Z2: 0.5 | AA2: 0.5006 | AB2: 3 | AC2: Defend | AD2: 0.5 | AE2: reported
A3: Arapahoe County CO | B3: Arapahoe County CO | C3: CO | D3: Local ENT | E3: David Cliff | F3: Steffany Amador | G3: Paige Wendle | H3: =IF(F3="(not in WIP)","New to Enterprise",IF(F3=G3,"No","Yes")) | I3: =IFERROR(INDEX(Lookups!$B$2:$B$14,MATCH(G3,Lookups!$A$2:$A$14,0)),"Not found") | J3: =IFERROR(INDEX(Lookups!$E$2:$E$14,MATCH(G3,Lookups!$A$2:$A$14,0)),"") | K3: MT | L3: =IF(J3="n/a","n/a",IFERROR(IF(ABS(INDEX(Lookups!$H$2:$H$5,MATCH(J3,Lookups!$G$2:$G$5,0))-INDEX(Lookups!$H$2:$H$5,MATCH(K3,Lookups!$G$2:$G$5,0)))<=1,"Yes","No"),"Check")) | M3: 331546.29 | N3: Yes | O3: 7 | Q3: =IF(N3<>"Yes","n/a",IF(OR(AND(O3<>"",O3>$W$1),P3="Y"),"Yes",IF(O3<>"","No","Pending"))) | S3: Steffany Amador | T3: Local ENT | U3: Agenda & Video, Email & SMS, Engagement & Sentiment, Forms & Workflows, Recurring Services, Short-term Rentals, Websites, Portals, & Intranets | X3: B | Y3: 50.1 | Z3: 0.125 | AA3: 0.3506 | AB3: 3 | AC3: Defend | AD3: 0.5 | AE3: reported
A4: District of Columbia | B4: District of Columbia | C4: DC | D4: Neither map | E4: Not on either map | F4: Paige Wendle | G4: Paige Wendle | H4: =IF(F4="(not in WIP)","New to Enterprise",IF(F4=G4,"No","Yes")) | I4: =IFERROR(INDEX(Lookups!$B$2:$B$14,MATCH(G4,Lookups!$A$2:$A$14,0)),"Not found") | J4: =IFERROR(INDEX(Lookups!$E$2:$E$14,MATCH(G4,Lookups!$A$2:$A$14,0)),"") | K4: ET | L4: =IF(J4="n/a","n/a",IFERROR(IF(ABS(INDEX(Lookups!$H$2:$H$5,MATCH(J4,Lookups!$G$2:$G$5,0))-INDEX(Lookups!$H$2:$H$5,MATCH(K4,Lookups!$G$2:$G$5,0)))<=1,"Yes","No"),"Check")) | M4: 725132.5 | N4: Yes | O4: 4 | Q4: =IF(N4<>"Yes","n/a",IF(OR(AND(O4<>"",O4>$W$1),P4="Y"),"Yes",IF(O4<>"","No","Pending"))) | S4: Paige Wendle | T4: Federal | U4: Email & SMS, Engagement & Sentiment, Public Records Request, Recurring Services | X4: B | Y4: 51.7 | Z4: 0.5 | AA4: 0.5102 | AB4: 3 | AC4: Defend | AD4: 0.5 | AE4: reported
A5: Idaho Labor Department | B5: Idaho | C5: ID | D5: State | E5: Scott Mark | F5: Paige Wendle | G5: Paige Wendle | H5: =IF(F5="(not in WIP)","New to Enterprise",IF(F5=G5,"No","Yes")) | I5: =IFERROR(INDEX(Lookups!$B$2:$B$14,MATCH(G5,Lookups!$A$2:$A$14,0)),"Not found") | J5: =IFERROR(INDEX(Lookups!$E$2:$E$14,MATCH(G5,Lookups!$A$2:$A$14,0)),"") | K5: MT | L5: =IF(J5="n/a","n/a",IFERROR(IF(ABS(INDEX(Lookups!$H$2:$H$5,MATCH(J5,Lookups!$G$2:$G$5,0))-INDEX(Lookups!$H$2:$H$5,MATCH(K5,Lookups!$G$2:$G$5,0)))<=1,"Yes","No"),"Check")) | M5: 88765.39 | N5: Yes | O5: 3 | Q5: =IF(N5<>"Yes","n/a",IF(OR(AND(O5<>"",O5>$W$1),P5="Y"),"Yes",IF(O5<>"","No","Pending"))) | S5: Paige Wendle | T5: State | U5: Email & SMS, Engagement & Sentiment, Recurring Services | X5: C | Y5: 42.3 | Z5: 0.625 | AA5: 0.5038 | AB5: 4 | AC5: Maintain | AD5: 0.3 | AE5: reported
A6: Washington County OR | B6: Washington County OR | C6: OR | D6: Local ENT | E6: Carrie Breedlove | F6: Paige Wendle | G6: Paige Wendle | H6: =IF(F6="(not in WIP)","New to Enterprise",IF(F6=G6,"No","Yes")) | I6: =IFERROR(INDEX(Lookups!$B$2:$B$14,MATCH(G6,Lookups!$A$2:$A$14,0)),"Not found") | J6: =IFERROR(INDEX(Lookups!$E$2:$E$14,MATCH(G6,Lookups!$A$2:$A$14,0)),"") | K6: PT | L6: =IF(J6="n/a","n/a",IFERROR(IF(ABS(INDEX(Lookups!$H$2:$H$5,MATCH(J6,Lookups!$G$2:$G$5,0))-INDEX(Lookups!$H$2:$H$5,MATCH(K6,Lookups!$G$2:$G$5,0)))<=1,"Yes","No"),"Check")) | M6: 229991.53 | N6: Yes | O6: 6 | Q6: =IF(N6<>"Yes","n/a",IF(OR(AND(O6<>"",O6>$W$1),P6="Y"),"Yes",IF(O6<>"","No","Pending"))) | S6: Brooke Minichino | T6: Local ENT | U6: Agenda & Video, Channel Shift, Email & SMS, Engagement & Sentiment, Public Records Request, Recurring Services | X6: C | Y6: 46 | Z6: 0.25 | AA6: 0.376 | AB6: 3 | AC6: Defend | AD6: 0.5 | AE6: reported
A7: Tri-County Metropolitan Transportation District of Oregon (TriMet) | B7: Multnomah County OR | C7: OR | D7: Local ENT | E7: Carrie Breedlove | F7: (not in WIP) | G7: Paige Wendle | H7: =IF(F7="(not in WIP)","New to Enterprise",IF(F7=G7,"No","Yes")) | I7: =IFERROR(INDEX(Lookups!$B$2:$B$14,MATCH(G7,Lookups!$A$2:$A$14,0)),"Not found") | J7: =IFERROR(INDEX(Lookups!$E$2:$E$14,MATCH(G7,Lookups!$A$2:$A$14,0)),"") | K7: PT | L7: =IF(J7="n/a","n/a",IFERROR(IF(ABS(INDEX(Lookups!$H$2:$H$5,MATCH(J7,Lookups!$G$2:$G$5,0))-INDEX(Lookups!$H$2:$H$5,MATCH(K7,Lookups!$G$2:$G$5,0)))<=1,"Yes","No"),"Check")) | M7: 180702.45 | N7: Yes | O7: 2 | Q7: =IF(N7<>"Yes","n/a",IF(OR(AND(O7<>"",O7>$W$1),P7="Y"),"Yes",IF(O7<>"","No","Pending"))) | S7: Natalia Sanchez | T7: Local ENT | U7: Email & SMS, Public Records Request | X7: C | Y7: 46 | Z7: 0.75 | AA7: 0.576 | AB7: 3 | AC7: Defend | AD7: 0.5 | AE7: reported
A8: Oregon Department of Corrections | B8: Oregon | C8: OR | D8: State | E8: Todd Bowers | F8: Paige Wendle | G8: Paige Wendle | H8: =IF(F8="(not in WIP)","New to Enterprise",IF(F8=G8,"No","Yes")) | I8: =IFERROR(INDEX(Lookups!$B$2:$B$14,MATCH(G8,Lookups!$A$2:$A$14,0)),"Not found") | J8: =IFERROR(INDEX(Lookups!$E$2:$E$14,MATCH(G8,Lookups!$A$2:$A$14,0)),"") | K8: PT | L8: =IF(J8="n/a","n/a",IFERROR(IF(ABS(INDEX(Lookups!$H$2:$H$5,MATCH(J8,Lookups!$G$2:$G$5,0))-INDEX(Lookups!$H$2:$H$5,MATCH(K8,Lookups!$G$2:$G$5,0)))<=1,"Yes","No"),"Check")) | M8: 72622 | N8: Yes | O8: 4 | Q8: =IF(N8<>"Yes","n/a",IF(OR(AND(O8<>"",O8>$W$1),P8="Y"),"Yes",IF(O8<>"","No","Pending"))) | S8: Paige Wendle | T8: State | U8: Email & SMS, Engagement & Sentiment, Public Records Request, Recurring Services | X8: C | Y8: 42 | Z8: 0.5 | AA8: 0.452 | AB8: 4 | AC8: Maintain | AD8: 0.3 | AE8: reported
A9: Oregon Housing and Community Services | B9: Oregon | C9: OR | D9: State | E9: Todd Bowers | F9: Paige Wendle | G9: Paige Wendle | H9: =IF(F9="(not in WIP)","New to Enterprise",IF(F9=G9,"No","Yes")) | I9: =IFERROR(INDEX(Lookups!$B$2:$B$14,MATCH(G9,Lookups!$A$2:$A$14,0)),"Not found") | J9: =IFERROR(INDEX(Lookups!$E$2:$E$14,MATCH(G9,Lookups!$A$2:$A$14,0)),"") | K9: PT | L9: =IF(J9="n/a","n/a",IFERROR(IF(ABS(INDEX(Lookups!$H$2:$H$5,MATCH(J9,Lookups!$G$2:$G$5,0))-INDEX(Lookups!$H$2:$H$5,MATCH(K9,Lookups!$G$2:$G$5,0)))<=1,"Yes","No"),"Check")) | M9: 64326.23 | N9: Yes | O9: 2 | Q9: =IF(N9<>"Yes","n/a",IF(OR(AND(O9<>"",O9>$W$1),P9="Y"),"Yes",IF(O9<>"","No","Pending"))) | S9: Kerrian Dailey | T9: State | U9: Other, Public Records Request | X9: C | Y9: 42 | Z9: 0.75 | AA9: 0.552 | AB9: 4 | AC9: Maintain | AD9: 0.3 | AE9: reported
A10: Oregon Public Utility Commission | B10: Oregon | C10: OR | D10: State | E10: Todd Bowers | F10: Paige Wendle | G10: Paige Wendle | H10: =IF(F10="(not in WIP)","New to Enterprise",IF(F10=G10,"No","Yes")) | I10: =IFERROR(INDEX(Lookups!$B$2:$B$14,MATCH(G10,Lookups!$A$2:$A$14,0)),"Not found") | J10: =IFERROR(INDEX(Lookups!$E$2:$E$14,MATCH(G10,Lookups!$A$2:$A$14,0)),"") | K10: PT | L10: =IF(J10="n/a","n/a",IFERROR(IF(ABS(INDEX(Lookups!$H$2:$H$5,MATCH(J10,Lookups!$G$2:$G$5,0))-INDEX(Lookups!$H$2:$H$5,MATCH(K10,Lookups!$G$2:$G$5,0)))<=1,"Yes","No"),"Check")) | M10: 52502.57 | N10: Yes | O10: 2 | Q10: =IF(N10<>"Yes","n/a",IF(OR(AND(O10<>"",O10>$W$1),P10="Y"),"Yes",IF(O10<>"","No","Pending"))) | S10: Cody Nichols | T10: State | U10: Agenda & Video, Public Records Request | X10: C | Y10: 42 | Z10: 0.75 | AA10: 0.552 | AB10: 4 | AC10: Maintain | AD10: 0.3 | AE10: reported
A11: Oregon Teacher Standards and Practices Commission | B11: Oregon | C11: OR | D11: State | E11: Todd Bowers | F11: Paige Wendle | G11: Paige Wendle | H11: =IF(F11="(not in WIP)","New to Enterprise",IF(F11=G11,"No","Yes")) | I11: =IFERROR(INDEX(Lookups!$B$2:$B$14,MATCH(G11,Lookups!$A$2:$A$14,0)),"Not found") | J11: =IFERROR(INDEX(Lookups!$E$2:$E$14,MATCH(G11,Lookups!$A$2:$A$14,0)),"") | K11: PT | L11: =IF(J11="n/a","n/a",IFERROR(IF(ABS(INDEX(Lookups!$H$2:$H$5,MATCH(J11,Lookups!$G$2:$G$5,0))-INDEX(Lookups!$H$2:$H$5,MATCH(K11,Lookups!$G$2:$G$5,0)))<=1,"Yes","No"),"Check")) | M11: 42446.25 | N11: Yes | O11: 4 | Q11: =IF(N11<>"Yes","n/a",IF(OR(AND(O11<>"",O11>$W$1),P11="Y"),"Yes",IF(O11<>"","No","Pending"))) | S11: Kristen Murphy | T11: State | U11: Email & SMS, Engagement & Sentiment, Recurring Services, govXCloud | X11: C | Y11: 42 | Z11: 0.5 | AA11: 0.452 | AB11: 4 | AC11: Maintain | AD11: 0.3 | AE11: reported
A12: Washington Department of Transportation | B12: Washington Department of Enterprise Services | C12: WA | D12: State | E12: Todd Bowers | F12: Paige Wendle | G12: Paige Wendle | H12: =IF(F12="(not in WIP)","New to Enterprise",IF(F12=G12,"No","Yes")) | I12: =IFERROR(INDEX(Lookups!$B$2:$B$14,MATCH(G12,Lookups!$A$2:$A$14,0)),"Not found") | J12: =IFERROR(INDEX(Lookups!$E$2:$E$14,MATCH(G12,Lookups!$A$2:$A$14,0)),"") | K12: PT | L12: =IF(J12="n/a","n/a",IFERROR(IF(ABS(INDEX(Lookups!$H$2:$H$5,MATCH(J12,Lookups!$G$2:$G$5,0))-INDEX(Lookups!$H$2:$H$5,MATCH(K12,Lookups!$G$2:$G$5,0)))<=1,"Yes","No"),"Check")) | M12: 301828.73 | N12: Yes | O12: 4 | Q12: =IF(N12<>"Yes","n/a",IF(OR(AND(O12<>"",O12>$W$1),P12="Y"),"Yes",IF(O12<>"","No","Pending"))) | S12: Paige Wendle | T12: State | U12: Email & SMS, Engagement & Sentiment, Public Records Request, Recurring Services | X12: D | Y12: 33.6 | Z12: 0.5 | AA12: 0.4016 | AB12: 3 | AC12: Defend | AD12: 0.5 | AE12: reported
A13: Washington State Department of Health | B13: Washington Department of Enterprise Services | C13: WA | D13: State | E13: Todd Bowers | F13: Paige Wendle | G13: Paige Wendle | H13: =IF(F13="(not in WIP)","New to Enterprise",IF(F13=G13,"No","Yes")) | I13: =IFERROR(INDEX(Lookups!$B$2:$B$14,MATCH(G13,Lookups!$A$2:$A$14,0)),"Not found") | J13: =IFERROR(INDEX(Lookups!$E$2:$E$14,MATCH(G13,Lookups!$A$2:$A$14,0)),"") | K13: PT | L13: =IF(J13="n/a","n/a",IFERROR(IF(ABS(INDEX(Lookups!$H$2:$H$5,MATCH(J13,Lookups!$G$2:$G$5,0))-INDEX(Lookups!$H$2:$H$5,MATCH(K13,Lookups!$G$2:$G$5,0)))<=1,"Yes","No"),"Check")) | M13: 296031.42 | N13: Yes | O13: 2 | Q13: =IF(N13<>"Yes","n/a",IF(OR(AND(O13<>"",O13>$W$1),P13="Y"),"Yes",IF(O13<>"","No","Pending"))) | S13: Paige Wendle | T13: State | U13: Email & SMS, Public Records Request | X13: D | Y13: 33.6 | Z13: 0.75 | AA13: 0.5016 | AB13: 3 | AC13: Defend | AD13: 0.5 | AE13: reported
... A52: Arizona Corporation Commission | B52: Arizona (HOLD FOR PARENT ACCOUNT) | C52: AZ | D52: State | E52: Cameron Chadsey | F52: Cody Nichols | G52: Cody Nichols | H52: =IF(F52="(not in WIP)","New to Enterprise",IF(F52=G52,"No","Yes")) | I52: =IFERROR(INDEX(Lookups!$B$2:$B$14,MATCH(G52,Lookups!$A$2:$A$14,0)),"Not found") | J52: =IFERROR(INDEX(Lookups!$E$2:$E$14,MATCH(G52,Lookups!$A$2:$A$14,0)),"") | K52: MT | L52: =IF(J52="n/a","n/a",IFERROR(IF(ABS(INDEX(Lookups!$H$2:$H$5,MATCH(J52,Lookups!$G$2:$G$5,0))-INDEX(Lookups!$H$2:$H$5,MATCH(K52,Lookups!$G$2:$G$5,0)))<=1,"Yes","No"),"Check")) | M52: 49215 | N52: Yes | O52: 1 | Q52: =IF(N52<>"Yes","n/a",IF(OR(AND(O52<>"",O52>$W$1),P52="Y"),"Yes",IF(O52<>"","No","Pending"))) | S52: Kristen Murphy | T52: State | U52: Agenda & Video | X52: C | Y52: 46.6 | Z52: 0.875 | AA52: 0.6296 | AB52: 2 | AC52: Expansion | AD52: 0.8 | AE52: reported
A53: Arizona State Schools for the Deaf & the Blind | B53: Arizona (HOLD FOR PARENT ACCOUNT) | C53: AZ | D53: State | E53: Cameron Chadsey | F53: Cody Nichols | G53: Cody Nichols | H53: =IF(F53="(not in WIP)","New to Enterprise",IF(F53=G53,"No","Yes")) | I53: =IFERROR(INDEX(Lookups!$B$2:$B$14,MATCH(G53,Lookups!$A$2:$A$14,0)),"Not found") | J53: =IFERROR(INDEX(Lookups!$E$2:$E$14,MATCH(G53,Lookups!$A$2:$A$14,0)),"") | K53: MT | L53: =IF(J53="n/a","n/a",IFERROR(IF(ABS(INDEX(Lookups!$H$2:$H$5,MATCH(J53,Lookups!$G$2:$G$5,0))-INDEX(Lookups!$H$2:$H$5,MATCH(K53,Lookups!$G$2:$G$5,0)))<=1,"Yes","No"),"Check")) | M53: 22991.98 | N53: Yes | O53: 0 | Q53: =IF(N53<>"Yes","n/a",IF(OR(AND(O53<>"",O53>$W$1),P53="Y"),"Yes",IF(O53<>"","No","Pending"))) | S53: Andrés Pérez | T53: State | X53: C | Y53: 46.6 | Z53: 0.75 | AA53: 0.5796 | AB53: 2 | AC53: Expansion | AD53: 0.8 | AE53: imputed
A54: Albuquerque, NM | B54: Albuquerque, NM | C54: NM | D54: Local ENT | E54: Stephen Allen | F54: Cody Nichols | G54: Cody Nichols | H54: =IF(F54="(not in WIP)","New to Enterprise",IF(F54=G54,"No","Yes")) | I54: =IFERROR(INDEX(Lookups!$B$2:$B$14,MATCH(G54,Lookups!$A$2:$A$14,0)),"Not found") | J54: =IFERROR(INDEX(Lookups!$E$2:$E$14,MATCH(G54,Lookups!$A$2:$A$14,0)),"") | K54: MT | L54: =IF(J54="n/a","n/a",IFERROR(IF(ABS(INDEX(Lookups!$H$2:$H$5,MATCH(J54,Lookups!$G$2:$G$5,0))-INDEX(Lookups!$H$2:$H$5,MATCH(K54,Lookups!$G$2:$G$5,0)))<=1,"Yes","No"),"Check")) | M54: 90042.24 | N54: Yes | O54: 1 | Q54: =IF(N54<>"Yes","n/a",IF(OR(AND(O54<>"",O54>$W$1),P54="Y"),"Yes",IF(O54<>"","No","Pending"))) | S54: Kristen Murphy | T54: Local ENT | U54: Agenda & Video | X54: B | Y54: 53.4 | Z54: 0.875 | AA54: 0.6704 | AB54: 2 | AC54: Expansion | AD54: 0.8 | AE54: reported
A55: New Mexico Department of Public Safety | B55: New Mexico (HOLD FOR PARENT ACCOUNT) | C55: NM | D55: State | E55: Cameron Chadsey | F55: Cody Nichols | G55: Cody Nichols | H55: =IF(F55="(not in WIP)","New to Enterprise",IF(F55=G55,"No","Yes")) | I55: =IFERROR(INDEX(Lookups!$B$2:$B$14,MATCH(G55,Lookups!$A$2:$A$14,0)),"Not found") | J55: =IFERROR(INDEX(Lookups!$E$2:$E$14,MATCH(G55,Lookups!$A$2:$A$14,0)),"") | K55: MT | L55: =IF(J55="n/a","n/a",IFERROR(IF(ABS(INDEX(Lookups!$H$2:$H$5,MATCH(J55,Lookups!$G$2:$G$5,0))-INDEX(Lookups!$H$2:$H$5,MATCH(K55,Lookups!$G$2:$G$5,0)))<=1,"Yes","No"),"Check")) | M55: 119725.38 | N55: Yes | O55: 1 | Q55: =IF(N55<>"Yes","n/a",IF(OR(AND(O55<>"",O55>$W$1),P55="Y"),"Yes",IF(O55<>"","No","Pending"))) | S55: Colleen Moran | T55: State | U55: Public Records Request | X55: A | Y55: 67 | Z55: 0.875 | AA55: 0.752 | AB55: 1 | AC55: Growth engine | AD55: 1 | AE55: reported
A56: New Mexico Energy, Minerals & Natural Resources Department | B56: New Mexico (HOLD FOR PARENT ACCOUNT) | C56: NM | D56: State | E56: Cameron Chadsey | F56: Cody Nichols | G56: Cody Nichols | H56: =IF(F56="(not in WIP)","New to Enterprise",IF(F56=G56,"No","Yes")) | I56: =IFERROR(INDEX(Lookups!$B$2:$B$14,MATCH(G56,Lookups!$A$2:$A$14,0)),"Not found") | J56: =IFERROR(INDEX(Lookups!$E$2:$E$14,MATCH(G56,Lookups!$A$2:$A$14,0)),"") | K56: MT | L56: =IF(J56="n/a","n/a",IFERROR(IF(ABS(INDEX(Lookups!$H$2:$H$5,MATCH(J56,Lookups!$G$2:$G$5,0))-INDEX(Lookups!$H$2:$H$5,MATCH(K56,Lookups!$G$2:$G$5,0)))<=1,"Yes","No"),"Check")) | M56: 68159.85 | N56: Yes | O56: 2 | Q56: =IF(N56<>"Yes","n/a",IF(OR(AND(O56<>"",O56>$W$1),P56="Y"),"Yes",IF(O56<>"","No","Pending"))) | S56: Kerrian Dailey | T56: State | U56: Other, Public Records Request | X56: A | Y56: 67 | Z56: 0.75 | AA56: 0.702 | AB56: 2 | AC56: Expansion | AD56: 0.8 | AE56: reported
A57: New Mexico Regulation & Licensing Department | B57: New Mexico (HOLD FOR PARENT ACCOUNT) | C57: NM | D57: State | E57: Cameron Chadsey | F57: Cody Nichols | G57: Cody Nichols | H57: =IF(F57="(not in WIP)","New to Enterprise",IF(F57=G57,"No","Yes")) | I57: =IFERROR(INDEX(Lookups!$B$2:$B$14,MATCH(G57,Lookups!$A$2:$A$14,0)),"Not found") | J57: =IFERROR(INDEX(Lookups!$E$2:$E$14,MATCH(G57,Lookups!$A$2:$A$14,0)),"") | K57: MT | L57: =IF(J57="n/a","n/a",IFERROR(IF(ABS(INDEX(Lookups!$H$2:$H$5,MATCH(J57,Lookups!$G$2:$G$5,0))-INDEX(Lookups!$H$2:$H$5,MATCH(K57,Lookups!$G$2:$G$5,0)))<=1,"Yes","No"),"Check")) | M57: 47966.91 | N57: Yes | O57: 3 | Q57: =IF(N57<>"Yes","n/a",IF(OR(AND(O57<>"",O57>$W$1),P57="Y"),"Yes",IF(O57<>"","No","Pending"))) | S57: Colleen Moran | T57: State | U57: Email & SMS, Engagement & Sentiment, Recurring Services | X57: A | Y57: 67 | Z57: 0.625 | AA57: 0.652 | AB57: 2 | AC57: Expansion | AD57: 0.8 | AE57: reported
A58: New Mexico Environment Department | B58: New Mexico (HOLD FOR PARENT ACCOUNT) | C58: NM | D58: State | E58: Cameron Chadsey | F58: Cody Nichols | G58: Cody Nichols | H58: =IF(F58="(not in WIP)","New to Enterprise",IF(F58=G58,"No","Yes")) | I58: =IFERROR(INDEX(Lookups!$B$2:$B$14,MATCH(G58,Lookups!$A$2:$A$14,0)),"Not found") | J58: =IFERROR(INDEX(Lookups!$E$2:$E$14,MATCH(G58,Lookups!$A$2:$A$14,0)),"") | K58: MT | L58: =IF(J58="n/a","n/a",IFERROR(IF(ABS(INDEX(Lookups!$H$2:$H$5,MATCH(J58,Lookups!$G$2:$G$5,0))-INDEX(Lookups!$H$2:$H$5,MATCH(K58,Lookups!$G$2:$G$5,0)))<=1,"Yes","No"),"Check")) | M58: 45471.89 | N58: Yes | O58: 3 | Q58: =IF(N58<>"Yes","n/a",IF(OR(AND(O58<>"",O58>$W$1),P58="Y"),"Yes",IF(O58<>"","No","Pending"))) | S58: Carlos Torres | T58: State | U58: Email & SMS, Engagement & Sentiment, Recurring Services | X58: A | Y58: 67 | Z58: 0.625 | AA58: 0.652 | AB58: 2 | AC58: Expansion | AD58: 0.8 | AE58: reported
A59: New Mexico Early Childhood Education & Care Department | B59: New Mexico Early Childhood Education & Care Department | C59: NM | D59: State | E59: Cameron Chadsey | F59: Cody Nichols | G59: Cody Nichols | H59: =IF(F59="(not in WIP)","New to Enterprise",IF(F59=G59,"No","Yes")) | I59: =IFERROR(INDEX(Lookups!$B$2:$B$14,MATCH(G59,Lookups!$A$2:$A$14,0)),"Not found") | J59: =IFERROR(INDEX(Lookups!$E$2:$E$14,MATCH(G59,Lookups!$A$2:$A$14,0)),"") | K59: MT | L59: =IF(J59="n/a","n/a",IFERROR(IF(ABS(INDEX(Lookups!$H$2:$H$5,MATCH(J59,Lookups!$G$2:$G$5,0))-INDEX(Lookups!$H$2:$H$5,MATCH(K59,Lookups!$G$2:$G$5,0)))<=1,"Yes","No"),"Check")) | M59: 42743.1 | N59: Yes | O59: 1 | Q59: =IF(N59<>"Yes","n/a",IF(OR(AND(O59<>"",O59>$W$1),P59="Y"),"Yes",IF(O59<>"","No","Pending"))) | S59: Kerrian Dailey | T59: State | U59: Public Records Request | X59: A | Y59: 67 | Z59: 0.875 | AA59: 0.752 | AB59: 2 | AC59: Expansion | AD59: 0.8 | AE59: reported
A60: New Mexico Health Care Authority | B60: New Mexico (HOLD FOR PARENT ACCOUNT) | C60: NM | D60: State | E60: Cameron Chadsey | F60: Cody Nichols | G60: Cody Nichols | H60: =IF(F60="(not in WIP)","New to Enterprise",IF(F60=G60,"No","Yes")) | I60: =IFERROR(INDEX(Lookups!$B$2:$B$14,MATCH(G60,Lookups!$A$2:$A$14,0)),"Not found") | J60: =IFERROR(INDEX(Lookups!$E$2:$E$14,MATCH(G60,Lookups!$A$2:$A$14,0)),"") | K60: MT | L60: =IF(J60="n/a","n/a",IFERROR(IF(ABS(INDEX(Lookups!$H$2:$H$5,MATCH(J60,Lookups!$G$2:$G$5,0))-INDEX(Lookups!$H$2:$H$5,MATCH(K60,Lookups!$G$2:$G$5,0)))<=1,"Yes","No"),"Check")) | M60: 36674.93 | N60: Yes | O60: 1 | Q60: =IF(N60<>"Yes","n/a",IF(OR(AND(O60<>"",O60>$W$1),P60="Y"),"Yes",IF(O60<>"","No","Pending"))) | S60: Steffany Amador | T60: State | U60: Public Records Request | X60: A | Y60: 67 | Z60: 0.875 | AA60: 0.752 | AB60: 2 | AC60: Expansion | AD60: 0.8 | AE60: reported
A61: New Mexico Department of Justice | B61: New Mexico (HOLD FOR PARENT ACCOUNT) | C61: NM | D61: State | E61: Cameron Chadsey | F61: Cody Nichols | G61: Cody Nichols | H61: =IF(F61="(not in WIP)","New to Enterprise",IF(F61=G61,"No","Yes")) | I61: =IFERROR(INDEX(Lookups!$B$2:$B$14,MATCH(G61,Lookups!$A$2:$A$14,0)),"Not found") | J61: =IFERROR(INDEX(Lookups!$E$2:$E$14,MATCH(G61,Lookups!$A$2:$A$14,0)),"") | K61: MT | L61: =IF(J61="n/a","n/a",IFERROR(IF(ABS(INDEX(Lookups!$H$2:$H$5,MATCH(J61,Lookups!$G$2:$G$5,0))-INDEX(Lookups!$H$2:$H$5,MATCH(K61,Lookups!$G$2:$G$5,0)))<=1,"Yes","No"),"Check")) | M61: 22951.04 | N61: Yes | O61: 3 | Q61: =IF(N61<>"Yes","n/a",IF(OR(AND(O61<>"",O61>$W$1),P61="Y"),"Yes",IF(O61<>"","No","Pending"))) | S61: Paige Wendle | T61: State | U61: Email & SMS, Engagement & Sentiment, Recurring Services | X61: A | Y61: 67 | Z61: 0.625 | AA61: 0.652 | AB61: 2 | AC61: Expansion | AD61: 0.8 | AE61: reported
A62: Colorado Department of Regulatory Agencies | B62: Colorado | C62: CO | D62: State | E62: Che Bustos | F62: Alejandro Solano | G62: Alejandro Solano | H62: =IF(F62="(not in WIP)","New to Enterprise",IF(F62=G62,"No","Yes")) | I62: =IFERROR(INDEX(Lookups!$B$2:$B$14,MATCH(G62,Lookups!$A$2:$A$14,0)),"Not found") | J62: =IFERROR(INDEX(Lookups!$E$2:$E$14,MATCH(G62,Lookups!$A$2:$A$14,0)),"") | K62: MT | L62: =IF(J62="n/a","n/a",IFERROR(IF(ABS(INDEX(Lookups!$H$2:$H$5,MATCH(J62,Lookups!$G$2:$G$5,0))-INDEX(Lookups!$H$2:$H$5,MATCH(K62,Lookups!$G$2:$G$5,0)))<=1,"Yes","No"),"Check")) | M62: 114064.65 | N62: Yes | O62: 3 | Q62: =IF(N62<>"Yes","n/a",IF(OR(AND(O62<>"",O62>$W$1),P62="Y"),"Yes",IF(O62<>"","No","Pending"))) | S62: Kerrian Dailey | T62: State | U62: Email & SMS, Engagement & Sentiment, Recurring Services | X62: C | Y62: 42.5 | Z62: 0.625 | AA62: 0.505 | AB62: 3 | AC62: Defend | AD62: 0.5 | AE62: reported
A63: Colorado Department of Natural Resources | B63: Colorado | C63: CO | D63: State | E63: Che Bustos | F63: Alejandro Solano | G63: Alejandro Solano | H63: =IF(F63="(not in WIP)","New to Enterprise",IF(F63=G63,"No","Yes")) | I63: =IFERROR(INDEX(Lookups!$B$2:$B$14,MATCH(G63,Lookups!$A$2:$A$14,0)),"Not found") | J63: =IFERROR(INDEX(Lookups!$E$2:$E$14,MATCH(G63,Lookups!$A$2:$A$14,0)),"") | K63: MT | L63: =IF(J63="n/a","n/a",IFERROR(IF(ABS(INDEX(Lookups!$H$2:$H$5,MATCH(J63,Lookups!$G$2:$G$5,0))-INDEX(Lookups!$H$2:$H$5,MATCH(K63,Lookups!$G$2:$G$5,0)))<=1,"Yes","No"),"Check")) | M63: 86432.01 | N63: Yes | O63: 2 | Q63: =IF(N63<>"Yes","n/a",IF(OR(AND(O63<>"",O63>$W$1),P63="Y"),"Yes",IF(O63<>"","No","Pending"))) | S63: Savannah Lane | T63: State | U63: Email & SMS, Engagement & Sentiment | X63: C | Y63: 42.5 | Z63: 0.75 | AA63: 0.555 | AB63: 4 | AC63: Maintain | AD63: 0.3 | AE63: reported
A64: Colorado Department of Labor and Employment | B64: Colorado | C64: CO | D64: State | E64: Che Bustos | F64: Alejandro Solano | G64: Alejandro Solano | H64: =IF(F64="(not in WIP)","New to Enterprise",IF(F64=G64,"No","Yes")) | I64: =IFERROR(INDEX(Lookups!$B$2:$B$14,MATCH(G64,Lookups!$A$2:$A$14,0)),"Not found") | J64: =IFERROR(INDEX(Lookups!$E$2:$E$14,MATCH(G64,Lookups!$A$2:$A$14,0)),"") | K64: MT | L64: =IF(J64="n/a","n/a",IFERROR(IF(ABS(INDEX(Lookups!$H$2:$H$5,MATCH(J64,Lookups!$G$2:$G$5,0))-INDEX(Lookups!$H$2:$H$5,MATCH(K64,Lookups!$G$2:$G$5,0)))<=1,"Yes","No"),"Check")) | M64: 56832.3 | N64: Yes | O64: 3 | Q64: =IF(N64<>"Yes","n/a",IF(OR(AND(O64<>"",O64>$W$1),P64="Y"),"Yes",IF(O64<>"","No","Pending"))) | S64: Colleen Moran | T64: State | U64: Email & SMS, Engagement & Sentiment, Recurring Services | X64: C | Y64: 42.5 | Z64: 0.625 | AA64: 0.505 | AB64: 4 | AC64: Maintain | AD64: 0.3 | AE64: reported
A65: Colorado Department of Corrections | B65: Colorado | C65: CO | D65: State | E65: Che Bustos | F65: Alejandro Solano | G65: Alejandro Solano | H65: =IF(F65="(not in WIP)","New to Enterprise",IF(F65=G65,"No","Yes")) | I65: =IFERROR(INDEX(Lookups!$B$2:$B$14,MATCH(G65,Lookups!$A$2:$A$14,0)),"Not found") | J65: =IFERROR(INDEX(Lookups!$E$2:$E$14,MATCH(G65,Lookups!$A$2:$A$14,0)),"") | K65: MT | L65: =IF(J65="n/a","n/a",IFERROR(IF(ABS(INDEX(Lookups!$H$2:$H$5,MATCH(J65,Lookups!$G$2:$G$5,0))-INDEX(Lookups!$H$2:$H$5,MATCH(K65,Lookups!$G$2:$G$5,0)))<=1,"Yes","No"),"Check")) | M65: 50310.23 | N65: Yes | O65: 3 | Q65: =IF(N65<>"Yes","n/a",IF(OR(AND(O65<>"",O65>$W$1),P65="Y"),"Yes",IF(O65<>"","No","Pending"))) | S65: Colleen Moran | T65: State | U65: Email & SMS, Engagement & Sentiment, Recurring Services | X65: C | Y65: 42.5 | Z65: 0.625 | AA65: 0.505 | AB65: 4 | AC65: Maintain | AD65: 0.3 | AE65: reported
... A95: Georgia Environmental Protection Division | B95: Georgia | C95: GA | D95: State | E95: Sarah Duncan | F95: Andy O'Brien | G95: Taylor Roman | H95: =IF(F95="(not in WIP)","New to Enterprise",IF(F95=G95,"No","Yes")) | I95: =IFERROR(INDEX(Lookups!$B$2:$B$14,MATCH(G95,Lookups!$A$2:$A$14,0)),"Not found") | J95: =IFERROR(INDEX(Lookups!$E$2:$E$14,MATCH(G95,Lookups!$A$2:$A$14,0)),"") | K95: ET | L95: =IF(J95="n/a","n/a",IFERROR(IF(ABS(INDEX(Lookups!$H$2:$H$5,MATCH(J95,Lookups!$G$2:$G$5,0))-INDEX(Lookups!$H$2:$H$5,MATCH(K95,Lookups!$G$2:$G$5,0)))<=1,"Yes","No"),"Check")) | M95: 24946.5 | N95: Yes | O95: 3 | Q95: =IF(N95<>"Yes","n/a",IF(OR(AND(O95<>"",O95>$W$1),P95="Y"),"Yes",IF(O95<>"","No","Pending"))) | S95: Marcy Castro | T95: State | U95: Email & SMS, Engagement & Sentiment, Recurring Services | X95: A | Y95: 77.5 | Z95: 0.625 | AA95: 0.715 | AB95: 2 | AC95: Expansion | AD95: 0.8 | AE95: reported
A96: Cook County, IL | B96: Cook County, IL | C96: IL | D96: Local ENT | E96: Kent Hartsfield | F96: Steffany Amador | G96: Marcy Castro | H96: =IF(F96="(not in WIP)","New to Enterprise",IF(F96=G96,"No","Yes")) | I96: =IFERROR(INDEX(Lookups!$B$2:$B$14,MATCH(G96,Lookups!$A$2:$A$14,0)),"Not found") | J96: =IFERROR(INDEX(Lookups!$E$2:$E$14,MATCH(G96,Lookups!$A$2:$A$14,0)),"") | K96: CT | L96: =IF(J96="n/a","n/a",IFERROR(IF(ABS(INDEX(Lookups!$H$2:$H$5,MATCH(J96,Lookups!$G$2:$G$5,0))-INDEX(Lookups!$H$2:$H$5,MATCH(K96,Lookups!$G$2:$G$5,0)))<=1,"Yes","No"),"Check")) | M96: 1110948.2 | N96: Yes | O96: 3 | Q96: =IF(N96<>"Yes","n/a",IF(OR(AND(O96<>"",O96>$W$1),P96="Y"),"Yes",IF(O96<>"","No","Pending"))) | R96: Cook County: modeled as Chicago SAM; either way it lands with Kent Hartsfield | S96: Steffany Amador | T96: Local ENT | U96: Agenda & Video, Email & SMS, Public Records Request | X96: C | Y96: 40 | Z96: 0.625 | AA96: 0.49 | AB96: 3 | AC96: Defend | AD96: 0.5 | AE96: reported
A97: Lake County IL | B97: Lake County IL | C97: IL | D97: Local ENT | E97: Kent Hartsfield | F97: Steffany Amador | G97: Marcy Castro | H97: =IF(F97="(not in WIP)","New to Enterprise",IF(F97=G97,"No","Yes")) | I97: =IFERROR(INDEX(Lookups!$B$2:$B$14,MATCH(G97,Lookups!$A$2:$A$14,0)),"Not found") | J97: =IFERROR(INDEX(Lookups!$E$2:$E$14,MATCH(G97,Lookups!$A$2:$A$14,0)),"") | K97: CT | L97: =IF(J97="n/a","n/a",IFERROR(IF(ABS(INDEX(Lookups!$H$2:$H$5,MATCH(J97,Lookups!$G$2:$G$5,0))-INDEX(Lookups!$H$2:$H$5,MATCH(K97,Lookups!$G$2:$G$5,0)))<=1,"Yes","No"),"Check")) | M97: 185771.15 | N97: Yes | O97: 5 | Q97: =IF(N97<>"Yes","n/a",IF(OR(AND(O97<>"",O97>$W$1),P97="Y"),"Yes",IF(O97<>"","No","Pending"))) | S97: Natalia Sanchez | T97: Local ENT | U97: Agenda & Video, Email & SMS, Engagement & Sentiment, Public Records Request, Recurring Services | X97: C | Y97: 40 | Z97: 0.375 | AA97: 0.39 | AB97: 3 | AC97: Defend | AD97: 0.5 | AE97: reported
A98: Chicago Metropolitan Agency for Planning | B98: Chicago Metropolitan Agency for Planning | C98: IL | D98: Local ENT | E98: Kent Hartsfield | F98: Steffany Amador | G98: Marcy Castro | H98: =IF(F98="(not in WIP)","New to Enterprise",IF(F98=G98,"No","Yes")) | I98: =IFERROR(INDEX(Lookups!$B$2:$B$14,MATCH(G98,Lookups!$A$2:$A$14,0)),"Not found") | J98: =IFERROR(INDEX(Lookups!$E$2:$E$14,MATCH(G98,Lookups!$A$2:$A$14,0)),"") | K98: CT | L98: =IF(J98="n/a","n/a",IFERROR(IF(ABS(INDEX(Lookups!$H$2:$H$5,MATCH(J98,Lookups!$G$2:$G$5,0))-INDEX(Lookups!$H$2:$H$5,MATCH(K98,Lookups!$G$2:$G$5,0)))<=1,"Yes","No"),"Check")) | M98: 91016.97 | N98: Yes | O98: 4 | Q98: =IF(N98<>"Yes","n/a",IF(OR(AND(O98<>"",O98>$W$1),P98="Y"),"Yes",IF(O98<>"","No","Pending"))) | S98: Carolina Cambronero | T98: Local ENT | U98: Agenda & Video, Email & SMS, Engagement & Sentiment, Recurring Services | X98: C | Y98: 40 | Z98: 0.5 | AA98: 0.44 | AB98: 4 | AC98: Maintain | AD98: 0.3 | AE98: reported
A99: Illinois Department of Financial and Professional Regulation | B99: Illinois | C99: IL | D99: State | E99: Bill Pintsak | F99: Steffany Amador | G99: Marcy Castro | H99: =IF(F99="(not in WIP)","New to Enterprise",IF(F99=G99,"No","Yes")) | I99: =IFERROR(INDEX(Lookups!$B$2:$B$14,MATCH(G99,Lookups!$A$2:$A$14,0)),"Not found") | J99: =IFERROR(INDEX(Lookups!$E$2:$E$14,MATCH(G99,Lookups!$A$2:$A$14,0)),"") | K99: CT | L99: =IF(J99="n/a","n/a",IFERROR(IF(ABS(INDEX(Lookups!$H$2:$H$5,MATCH(J99,Lookups!$G$2:$G$5,0))-INDEX(Lookups!$H$2:$H$5,MATCH(K99,Lookups!$G$2:$G$5,0)))<=1,"Yes","No"),"Check")) | M99: 76183.63 | N99: Yes | O99: 3 | Q99: =IF(N99<>"Yes","n/a",IF(OR(AND(O99<>"",O99>$W$1),P99="Y"),"Yes",IF(O99<>"","No","Pending"))) | S99: Kristen Murphy | T99: State | U99: Email & SMS, Engagement & Sentiment, Recurring Services | X99: B | Y99: 52.2 | Z99: 0.625 | AA99: 0.5632 | AB99: 4 | AC99: Maintain | AD99: 0.3 | AE99: reported
A100: Lake County IN | B100: Lake County IN | C100: IN | D100: Local ENT | E100: Kent Hartsfield | F100: Brooke Minichino | G100: Marcy Castro | H100: =IF(F100="(not in WIP)","New to Enterprise",IF(F100=G100,"No","Yes")) | I100: =IFERROR(INDEX(Lookups!$B$2:$B$14,MATCH(G100,Lookups!$A$2:$A$14,0)),"Not found") | J100: =IFERROR(INDEX(Lookups!$E$2:$E$14,MATCH(G100,Lookups!$A$2:$A$14,0)),"") | K100: ET | L100: =IF(J100="n/a","n/a",IFERROR(IF(ABS(INDEX(Lookups!$H$2:$H$5,MATCH(J100,Lookups!$G$2:$G$5,0))-INDEX(Lookups!$H$2:$H$5,MATCH(K100,Lookups!$G$2:$G$5,0)))<=1,"Yes","No"),"Check")) | M100: 70971.57 | N100: Yes | O100: 2 | Q100: =IF(N100<>"Yes","n/a",IF(OR(AND(O100<>"",O100>$W$1),P100="Y"),"Yes",IF(O100<>"","No","Pending"))) | S100: Alejandro Solano | T100: Local ENT | U100: Agenda & Video, Email & SMS | X100: A | Y100: 63.7 | Z100: 0.75 | AA100: 0.6822 | AB100: 2 | AC100: Expansion | AD100: 0.8 | AE100: reported
A101: Jackson County MO | B101: Jackson County MO | C101: MO | D101: Local ENT | E101: David Cliff | F101: Marcy Castro | G101: Marcy Castro | H101: =IF(F101="(not in WIP)","New to Enterprise",IF(F101=G101,"No","Yes")) | I101: =IFERROR(INDEX(Lookups!$B$2:$B$14,MATCH(G101,Lookups!$A$2:$A$14,0)),"Not found") | J101: =IFERROR(INDEX(Lookups!$E$2:$E$14,MATCH(G101,Lookups!$A$2:$A$14,0)),"") | K101: CT | L101: =IF(J101="n/a","n/a",IFERROR(IF(ABS(INDEX(Lookups!$H$2:$H$5,MATCH(J101,Lookups!$G$2:$G$5,0))-INDEX(Lookups!$H$2:$H$5,MATCH(K101,Lookups!$G$2:$G$5,0)))<=1,"Yes","No"),"Check")) | M101: 521351.74 | N101: Yes | O101: 9 | Q101: =IF(N101<>"Yes","n/a",IF(OR(AND(O101<>"",O101>$W$1),P101="Y"),"Yes",IF(O101<>"","No","Pending"))) | S101: Carolina Cambronero | T101: Local ENT | U101: Agenda & Video, Channel Shift, Email & SMS, Engagement & Sentiment, Experience Agents, Forms & Workflows, Public Records Request, Recurring Services, Websites, Portals, & Intranets | X101: C | Y101: 41.9 | Z101: 0 | AA101: 0.2514 | AB101: 3 | AC101: Defend | AD101: 0.5 | AE101: reported
A102: Kansas City, MO, Police Department | B102: Kansas City, MO | C102: MO | D102: Local ENT | E102: David Cliff | F102: Marcy Castro | G102: Marcy Castro | H102: =IF(F102="(not in WIP)","New to Enterprise",IF(F102=G102,"No","Yes")) | I102: =IFERROR(INDEX(Lookups!$B$2:$B$14,MATCH(G102,Lookups!$A$2:$A$14,0)),"Not found") | J102: =IFERROR(INDEX(Lookups!$E$2:$E$14,MATCH(G102,Lookups!$A$2:$A$14,0)),"") | K102: CT | L102: =IF(J102="n/a","n/a",IFERROR(IF(ABS(INDEX(Lookups!$H$2:$H$5,MATCH(J102,Lookups!$G$2:$G$5,0))-INDEX(Lookups!$H$2:$H$5,MATCH(K102,Lookups!$G$2:$G$5,0)))<=1,"Yes","No"),"Check")) | M102: 139405.59 | N102: Yes | O102: 1 | Q102: =IF(N102<>"Yes","n/a",IF(OR(AND(O102<>"",O102>$W$1),P102="Y"),"Yes",IF(O102<>"","No","Pending"))) | S102: Carolina Cambronero | T102: Local ENT | U102: Public Records Request | X102: C | Y102: 41.9 | Z102: 0.875 | AA102: 0.6014 | AB102: 1 | AC102: Growth engine | AD102: 1 | AE102: reported
A103: Missouri Department of Elementary and Secondary Education | B103: Missouri | C103: MO | D103: State | E103: Bill Pintsak | F103: Marcy Castro | G103: Marcy Castro | H103: =IF(F103="(not in WIP)","New to Enterprise",IF(F103=G103,"No","Yes")) | I103: =IFERROR(INDEX(Lookups!$B$2:$B$14,MATCH(G103,Lookups!$A$2:$A$14,0)),"Not found") | J103: =IFERROR(INDEX(Lookups!$E$2:$E$14,MATCH(G103,Lookups!$A$2:$A$14,0)),"") | K103: CT | L103: =IF(J103="n/a","n/a",IFERROR(IF(ABS(INDEX(Lookups!$H$2:$H$5,MATCH(J103,Lookups!$G$2:$G$5,0))-INDEX(Lookups!$H$2:$H$5,MATCH(K103,Lookups!$G$2:$G$5,0)))<=1,"Yes","No"),"Check")) | M103: 71337.62 | N103: Yes | O103: 3 | Q103: =IF(N103<>"Yes","n/a",IF(OR(AND(O103<>"",O103>$W$1),P103="Y"),"Yes",IF(O103<>"","No","Pending"))) | S103: Natalia Sanchez | T103: State | U103: Email & SMS, Engagement & Sentiment, Recurring Services | X103: C | Y103: 42.3 | Z103: 0.625 | AA103: 0.5038 | AB103: 4 | AC103: Maintain | AD103: 0.3 | AE103: reported
A104: Missouri State Treasurer | B104: Missouri | C104: MO | D104: State | E104: Bill Pintsak | F104: Marcy Castro | G104: Marcy Castro | H104: =IF(F104="(not in WIP)","New to Enterprise",IF(F104=G104,"No","Yes")) | I104: =IFERROR(INDEX(Lookups!$B$2:$B$14,MATCH(G104,Lookups!$A$2:$A$14,0)),"Not found") | J104: =IFERROR(INDEX(Lookups!$E$2:$E$14,MATCH(G104,Lookups!$A$2:$A$14,0)),"") | K104: CT | L104: =IF(J104="n/a","n/a",IFERROR(IF(ABS(INDEX(Lookups!$H$2:$H$5,MATCH(J104,Lookups!$G$2:$G$5,0))-INDEX(Lookups!$H$2:$H$5,MATCH(K104,Lookups!$G$2:$G$5,0)))<=1,"Yes","No"),"Check")) | M104: 28547.35 | N104: Yes | O104: 3 | Q104: =IF(N104<>"Yes","n/a",IF(OR(AND(O104<>"",O104>$W$1),P104="Y"),"Yes",IF(O104<>"","No","Pending"))) | S104: Kerrian Dailey | T104: State | U104: Email & SMS, Engagement & Sentiment, Recurring Services | X104: C | Y104: 42.3 | Z104: 0.625 | AA104: 0.5038 | AB104: 4 | AC104: Maintain | AD104: 0.3 | AE104: reported
A105: Missouri Public Service Commission | B105: Missouri | C105: MO | D105: State | E105: Bill Pintsak | F105: Marcy Castro | G105: Marcy Castro | H105: =IF(F105="(not in WIP)","New to Enterprise",IF(F105=G105,"No","Yes")) | I105: =IFERROR(INDEX(Lookups!$B$2:$B$14,MATCH(G105,Lookups!$A$2:$A$14,0)),"Not found") | J105: =IFERROR(INDEX(Lookups!$E$2:$E$14,MATCH(G105,Lookups!$A$2:$A$14,0)),"") | K105: CT | L105: =IF(J105="n/a","n/a",IFERROR(IF(ABS(INDEX(Lookups!$H$2:$H$5,MATCH(J105,Lookups!$G$2:$G$5,0))-INDEX(Lookups!$H$2:$H$5,MATCH(K105,Lookups!$G$2:$G$5,0)))<=1,"Yes","No"),"Check")) | M105: 26823.83 | N105: Yes | O105: 3 | Q105: =IF(N105<>"Yes","n/a",IF(OR(AND(O105<>"",O105>$W$1),P105="Y"),"Yes",IF(O105<>"","No","Pending"))) | S105: Kristen Murphy | T105: State | U105: Email & SMS, Engagement & Sentiment, Recurring Services | X105: C | Y105: 42.3 | Z105: 0.625 | AA105: 0.5038 | AB105: 4 | AC105: Maintain | AD105: 0.3 | AE105: reported
A106: DOTComm (Douglas Omaha Technology Commission) | B106: Douglas County, NE | C106: NE | D106: Local ENT | E106: David Cliff | F106: (not in WIP) | G106: Marcy Castro | H106: =IF(F106="(not in WIP)","New to Enterprise",IF(F106=G106,"No","Yes")) | I106: =IFERROR(INDEX(Lookups!$B$2:$B$14,MATCH(G106,Lookups!$A$2:$A$14,0)),"Not found") | J106: =IFERROR(INDEX(Lookups!$E$2:$E$14,MATCH(G106,Lookups!$A$2:$A$14,0)),"") | K106: CT | L106: =IF(J106="n/a","n/a",IFERROR(IF(ABS(INDEX(Lookups!$H$2:$H$5,MATCH(J106,Lookups!$G$2:$G$5,0))-INDEX(Lookups!$H$2:$H$5,MATCH(K106,Lookups!$G$2:$G$5,0)))<=1,"Yes","No"),"Check")) | M106: 28683.16 | N106: Yes | O106: 1 | Q106: =IF(N106<>"Yes","n/a",IF(OR(AND(O106<>"",O106>$W$1),P106="Y"),"Yes",IF(O106<>"","No","Pending"))) | S106: Carolina Cambronero | T106: Local ENT | U106: Public Records Request | X106: C | Y106: 42.8 | Z106: 0.875 | AA106: 0.6068 | AB106: 2 | AC106: Expansion | AD106: 0.8 | AE106: reported
A107: Columbus OH | B107: Columbus OH | C107: OH | D107: Local ENT | E107: Kent Hartsfield | F107: Steffany Amador | G107: Marcy Castro | H107: =IF(F107="(not in WIP)","New to Enterprise",IF(F107=G107,"No","Yes")) | I107: =IFERROR(INDEX(Lookups!$B$2:$B$14,MATCH(G107,Lookups!$A$2:$A$14,0)),"Not found") | J107: =IFERROR(INDEX(Lookups!$E$2:$E$14,MATCH(G107,Lookups!$A$2:$A$14,0)),"") | K107: ET | L107: =IF(J107="n/a","n/a",IFERROR(IF(ABS(INDEX(Lookups!$H$2:$H$5,MATCH(J107,Lookups!$G$2:$G$5,0))-INDEX(Lookups!$H$2:$H$5,MATCH(K107,Lookups!$G$2:$G$5,0)))<=1,"Yes","No"),"Check")) | M107: 870256.4 | N107: Yes | O107: 9 | Q107: =IF(N107<>"Yes","n/a",IF(OR(AND(O107<>"",O107>$W$1),P107="Y"),"Yes",IF(O107<>"","No","Pending"))) | S107: Ashley Hill | T107: Local ENT | U107: Agenda & Video, Channel Shift, Email & SMS, Engagement & Sentiment, Forms & Workflows, Recurring Services, Service Request Management, Websites, Portals, & Intranets, govXCloud | X107: B | Y107: 47 | Z107: 0 | AA107: 0.282 | AB107: 3 | AC107: Defend | AD107: 0.5 | AE107: reported
A108: Franklin County OH | B108: Franklin County OH | C108: OH | D108: Local ENT | E108: Kent Hartsfield | F108: Steffany Amador | G108: Marcy Castro | H108: =IF(F108="(not in WIP)","New to Enterprise",IF(F108=G108,"No","Yes")) | I108: =IFERROR(INDEX(Lookups!$B$2:$B$14,MATCH(G108,Lookups!$A$2:$A$14,0)),"Not found") | J108: =IFERROR(INDEX(Lookups!$E$2:$E$14,MATCH(G108,Lookups!$A$2:$A$14,0)),"") | K108: ET | L108: =IF(J108="n/a","n/a",IFERROR(IF(ABS(INDEX(Lookups!$H$2:$H$5,MATCH(J108,Lookups!$G$2:$G$5,0))-INDEX(Lookups!$H$2:$H$5,MATCH(K108,Lookups!$G$2:$G$5,0)))<=1,"Yes","No"),"Check")) | M108: 619425.92 | N108: Yes | O108: 8 | Q108: =IF(N108<>"Yes","n/a",IF(OR(AND(O108<>"",O108>$W$1),P108="Y"),"Yes",IF(O108<>"","No","Pending"))) | R108: Franklin County OH: modeled as Columbus SAM (same person either way) | S108: Andy O'Brien | T108: Local ENT | U108: Agenda & Video, Email & SMS, Engagement & Sentiment, Forms & Workflows, Permitting & Licensing, Recurring Services, Websites, Portals, & Intranets, govXCloud | X108: B | Y108: 47 | Z108: 0 | AA108: 0.282 | AB108: 3 | AC108: Defend | AD108: 0.5 | AE108: reported
A109: Cleveland, OH | B109: Cleveland, OH | C109: OH | D109: Local ENT | E109: Kent Hartsfield | F109: Steffany Amador | G109: Marcy Castro | H109: =IF(F109="(not in WIP)","New to Enterprise",IF(F109=G109,"No","Yes")) | I109: =IFERROR(INDEX(Lookups!$B$2:$B$14,MATCH(G109,Lookups!$A$2:$A$14,0)),"Not found") | J109: =IFERROR(INDEX(Lookups!$E$2:$E$14,MATCH(G109,Lookups!$A$2:$A$14,0)),"") | K109: ET | L109: =IF(J109="n/a","n/a",IFERROR(IF(ABS(INDEX(Lookups!$H$2:$H$5,MATCH(J109,Lookups!$G$2:$G$5,0))-INDEX(Lookups!$H$2:$H$5,MATCH(K109,Lookups!$G$2:$G$5,0)))<=1,"Yes","No"),"Check")) | M109: 292462.82 | N109: Yes | O109: 3 | Q109: =IF(N109<>"Yes","n/a",IF(OR(AND(O109<>"",O109>$W$1),P109="Y"),"Yes",IF(O109<>"","No","Pending"))) | S109: Steffany Amador | T109: Local ENT | U109: Agenda & Video, Channel Shift, Public Records Request | X109: B | Y109: 47 | Z109: 0.625 | AA109: 0.532 | AB109: 3 | AC109: Defend | AD109: 0.5 | AE109: reported
A110: Ohio Workers' Compensation Bureau | B110: Ohio | C110: OH | D110: State | E110: Bettsy Desjarlais | F110: Steffany Amador | G110: Marcy Castro | H110: =IF(F110="(not in WIP)","New to Enterprise",IF(F110=G110,"No","Yes")) | I110: =IFERROR(INDEX(Lookups!$B$2:$B$14,MATCH(G110,Lookups!$A$2:$A$14,0)),"Not found") | J110: =IFERROR(INDEX(Lookups!$E$2:$E$14,MATCH(G110,Lookups!$A$2:$A$14,0)),"") | K110: ET | L110: =IF(J110="n/a","n/a",IFERROR(IF(ABS(INDEX(Lookups!$H$2:$H$5,MATCH(J110,Lookups!$G$2:$G$5,0))-INDEX(Lookups!$H$2:$H$5,MATCH(K110,Lookups!$G$2:$G$5,0)))<=1,"Yes","No"),"Check")) | M110: 155215 | N110: Yes | O110: 3 | Q110: =IF(N110<>"Yes","n/a",IF(OR(AND(O110<>"",O110>$W$1),P110="Y"),"Yes",IF(O110<>"","No","Pending"))) | S110: Steffany Amador | T110: State | U110: Email & SMS, Engagement & Sentiment, Recurring Services | X110: A | Y110: 74.7 | Z110: 0.625 | AA110: 0.6982 | AB110: 1 | AC110: Growth engine | AD110: 1 | AE110: reported
A111: Ohio Department of Natural Resources | B111: Ohio | C111: OH | D111: State | E111: Bettsy Desjarlais | F111: Steffany Amador | G111: Marcy Castro | H111: =IF(F111="(not in WIP)","New to Enterprise",IF(F111=G111,"No","Yes")) | I111: =IFERROR(INDEX(Lookups!$B$2:$B$14,MATCH(G111,Lookups!$A$2:$A$14,0)),"Not found") | J111: =IFERROR(INDEX(Lookups!$E$2:$E$14,MATCH(G111,Lookups!$A$2:$A$14,0)),"") | K111: ET | L111: =IF(J111="n/a","n/a",IFERROR(IF(ABS(INDEX(Lookups!$H$2:$H$5,MATCH(J111,Lookups!$G$2:$G$5,0))-INDEX(Lookups!$H$2:$H$5,MATCH(K111,Lookups!$G$2:$G$5,0)))<=1,"Yes","No"),"Check")) | M111: 50554.39 | N111: Yes | O111: 2 | Q111: =IF(N111<>"Yes","n/a",IF(OR(AND(O111<>"",O111>$W$1),P111="Y"),"Yes",IF(O111<>"","No","Pending"))) | S111: Kristen Murphy | T111: State | U111: Other, Public Records Request | X111: A | Y111: 74.7 | Z111: 0.75 | AA111: 0.7482 | AB111: 2 | AC111: Expansion | AD111: 0.8 | AE111: reported
A112: Des Moines IA | B112: Des Moines IA | C112: IA | D112: Local ENT | E112: Tyler Carlson | F112: Steffany Amador | G112: Brooke Minichino | H112: =IF(F112="(not in WIP)","New to Enterprise",IF(F112=G112,"No","Yes")) | I112: =IFERROR(INDEX(Lookups!$B$2:$B$14,MATCH(G112,Lookups!$A$2:$A$14,0)),"Not found") | J112: =IFERROR(INDEX(Lookups!$E$2:$E$14,MATCH(G112,Lookups!$A$2:$A$14,0)),"") | K112: CT | L112: =IF(J112="n/a","n/a",IFERROR(IF(ABS(INDEX(Lookups!$H$2:$H$5,MATCH(J112,Lookups!$G$2:$G$5,0))-INDEX(Lookups!$H$2:$H$5,MATCH(K112,Lookups!$G$2:$G$5,0)))<=1,"Yes","No"),"Check")) | M112: 89731.12 | N112: Yes | O112: 5 | Q112: =IF(N112<>"Yes","n/a",IF(OR(AND(O112<>"",O112>$W$1),P112="Y"),"Yes",IF(O112<>"","No","Pending"))) | S112: David Treminio | T112: Local ENT | U112: Agenda & Video, Email & SMS, Engagement & Sentiment, Recurring Services, Service Request Management | X112: B | Y112: 50.3 | Z112: 0.375 | AA112: 0.4518 | AB112: 4 | AC112: Maintain | AD112: 0.3 | AE112: reported
A113: Iowa Division of Information Technology | B113: Iowa | C113: IA | D113: State | E113: No State AE shown (IA) | F113: Steffany Amador | G113: Brooke Minichino | H113: =IF(F113="(not in WIP)","New to Enterprise",IF(F113=G113,"No","Yes")) | I113: =IFERROR(INDEX(Lookups!$B$2:$B$14,MATCH(G113,Lookups!$A$2:$A$14,0)),"Not found") | J113: =IFERROR(INDEX(Lookups!$E$2:$E$14,MATCH(G113,Lookups!$A$2:$A$14,0)),"") | K113: CT | L113: =IF(J113="n/a","n/a",IFERROR(IF(ABS(INDEX(Lookups!$H$2:$H$5,MATCH(J113,Lookups!$G$2:$G$5,0))-INDEX(Lookups!$H$2:$H$5,MATCH(K113,Lookups!$G$2:$G$5,0)))<=1,"Yes","No"),"Check")) | M113: 511994.99 | N113: Yes | O113: 3 | Q113: =IF(N113<>"Yes","n/a",IF(OR(AND(O113<>"",O113>$W$1),P113="Y"),"Yes",IF(O113<>"","No","Pending"))) | S113: Steffany Amador | T113: State | U113: Email & SMS, Engagement & Sentiment, Recurring Services | X113: C | Y113: 42.3 | Z113: 0.625 | AA113: 0.5038 | AB113: 3 | AC113: Defend | AD113: 0.5 | AE113: reported
A114: Wayne County MI | B114: Wayne County MI | C114: MI | D114: Local ENT | E114: Tyler Carlson | F114: Brooke Minichino | G114: Brooke Minichino | H114: =IF(F114="(not in WIP)","New to Enterprise",IF(F114=G114,"No","Yes")) | I114: =IFERROR(INDEX(Lookups!$B$2:$B$14,MATCH(G114,Lookups!$A$2:$A$14,0)),"Not found") | J114: =IFERROR(INDEX(Lookups!$E$2:$E$14,MATCH(G114,Lookups!$A$2:$A$14,0)),"") | K114: ET | L114: =IF(J114="n/a","n/a",IFERROR(IF(ABS(INDEX(Lookups!$H$2:$H$5,MATCH(J114,Lookups!$G$2:$G$5,0))-INDEX(Lookups!$H$2:$H$5,MATCH(K114,Lookups!$G$2:$G$5,0)))<=1,"Yes","No"),"Check")) | M114: 489446.2 | N114: Yes | O114: 8 | Q114: =IF(N114<>"Yes","n/a",IF(OR(AND(O114<>"",O114>$W$1),P114="Y"),"Yes",IF(O114<>"","No","Pending"))) | S114: Brooke Minichino | T114: Local ENT | U114: Channel Shift, Email & SMS, Engagement & Sentiment, Forms & Workflows, Land & Vitals, Recurring Services, Service Request Management, Websites, Portals, & Intranets | X114: B | Y114: 49.5 | Z114: 0 | AA114: 0.297 | AB114: 3 | AC114: Defend | AD114: 0.5 | AE114: reported
A115: St. Paul MN | B115: St. Paul MN | C115: MN | D115: Local ENT | E115: Tyler Carlson | F115: Brooke Minichino | G115: Brooke Minichino | H115: =IF(F115="(not in WIP)","New to Enterprise",IF(F115=G115,"No","Yes")) | I115: =IFERROR(INDEX(Lookups!$B$2:$B$14,MATCH(G115,Lookups!$A$2:$A$14,0)),"Not found") | J115: =IFERROR(INDEX(Lookups!$E$2:$E$14,MATCH(G115,Lookups!$A$2:$A$14,0)),"") | K115: CT | L115: =IF(J115="n/a","n/a",IFERROR(IF(ABS(INDEX(Lookups!$H$2:$H$5,MATCH(J115,Lookups!$G$2:$G$5,0))-INDEX(Lookups!$H$2:$H$5,MATCH(K115,Lookups!$G$2:$G$5,0)))<=1,"Yes","No"),"Check")) | M115: 225711.22 | N115: Yes | O115: 4 | Q115: =IF(N115<>"Yes","n/a",IF(OR(AND(O115<>"",O115>$W$1),P115="Y"),"Yes",IF(O115<>"","No","Pending"))) | S115: Brooke Minichino | T115: Local ENT | U115: Agenda & Video, Email & SMS, Engagement & Sentiment, Public Records Request | X115: A | Y115: 58.5 | Z115: 0.5 | AA115: 0.551 | AB115: 3 | AC115: Defend | AD115: 0.5 | AE115: reported
A116: Ramsey County MN | B116: Ramsey County MN | C116: MN | D116: Local ENT | E116: Tyler Carlson | F116: Brooke Minichino | G116: Brooke Minichino | H116: =IF(F116="(not in WIP)","New to Enterprise",IF(F116=G116,"No","Yes")) | I116: =IFERROR(INDEX(Lookups!$B$2:$B$14,MATCH(G116,Lookups!$A$2:$A$14,0)),"Not found") | J116: =IFERROR(INDEX(Lookups!$E$2:$E$14,MATCH(G116,Lookups!$A$2:$A$14,0)),"") | K116: CT | L116: =IF(J116="n/a","n/a",IFERROR(IF(ABS(INDEX(Lookups!$H$2:$H$5,MATCH(J116,Lookups!$G$2:$G$5,0))-INDEX(Lookups!$H$2:$H$5,MATCH(K116,Lookups!$G$2:$G$5,0)))<=1,"Yes","No"),"Check")) | M116: 177558.91 | N116: Yes | O116: 3 | Q116: =IF(N116<>"Yes","n/a",IF(OR(AND(O116<>"",O116>$W$1),P116="Y"),"Yes",IF(O116<>"","No","Pending"))) | S116: Brooke Minichino | T116: Local ENT | U116: Agenda & Video, Email & SMS, Public Records Request | X116: A | Y116: 58.5 | Z116: 0.625 | AA116: 0.601 | AB116: 1 | AC116: Growth engine | AD116: 1 | AE116: reported
A117: Minnesota Public Utilities Commission | B117: Minnesota | C117: MN | D117: State | E117: Joe Spair | F117: Brooke Minichino | G117: Brooke Minichino | H117: =IF(F117="(not in WIP)","New to Enterprise",IF(F117=G117,"No","Yes")) | I117: =IFERROR(INDEX(Lookups!$B$2:$B$14,MATCH(G117,Lookups!$A$2:$A$14,0)),"Not found") | J117: =IFERROR(INDEX(Lookups!$E$2:$E$14,MATCH(G117,Lookups!$A$2:$A$14,0)),"") | K117: CT | L117: =IF(J117="n/a","n/a",IFERROR(IF(ABS(INDEX(Lookups!$H$2:$H$5,MATCH(J117,Lookups!$G$2:$G$5,0))-INDEX(Lookups!$H$2:$H$5,MATCH(K117,Lookups!$G$2:$G$5,0)))<=1,"Yes","No"),"Check")) | M117: 51463.55 | N117: Yes | O117: 0 | Q117: =IF(N117<>"Yes","n/a",IF(OR(AND(O117<>"",O117>$W$1),P117="Y"),"Yes",IF(O117<>"","No","Pending"))) | S117: Alejandro Solano | T117: State | X117: A | Y117: 67.4 | Z117: 0.75 | AA117: 0.7044 | AB117: 2 | AC117: Expansion | AD117: 0.8 | AE117: imputed
A118: Minnesota Department of Children, Youth, and Families | B118: Minnesota | C118: MN | D118: State | E118: Joe Spair | F118: Brooke Minichino | G118: Brooke Minichino | H118: =IF(F118="(not in WIP)","New to Enterprise",IF(F118=G118,"No","Yes")) | I118: =IFERROR(INDEX(Lookups!$B$2:$B$14,MATCH(G118,Lookups!$A$2:$A$14,0)),"Not found") | J118: =IFERROR(INDEX(Lookups!$E$2:$E$14,MATCH(G118,Lookups!$A$2:$A$14,0)),"") | K118: CT | L118: =IF(J118="n/a","n/a",IFERROR(IF(ABS(INDEX(Lookups!$H$2:$H$5,MATCH(J118,Lookups!$G$2:$G$5,0))-INDEX(Lookups!$H$2:$H$5,MATCH(K118,Lookups!$G$2:$G$5,0)))<=1,"Yes","No"),"Check")) | M118: 37261.94 | N118: Yes | O118: 1 | Q118: =IF(N118<>"Yes","n/a",IF(OR(AND(O118<>"",O118>$W$1),P118="Y"),"Yes",IF(O118<>"","No","Pending"))) | S118: Steffany Amador | T118: State | U118: Public Records Request | X118: A | Y118: 67.4 | Z118: 0.875 | AA118: 0.7544 | AB118: 2 | AC118: Expansion | AD118: 0.8 | AE118: reported
A119: Minnesota Attorney General | B119: Minnesota | C119: MN | D119: State | E119: Joe Spair | F119: Brooke Minichino | G119: Brooke Minichino | H119: =IF(F119="(not in WIP)","New to Enterprise",IF(F119=G119,"No","Yes")) | I119: =IFERROR(INDEX(Lookups!$B$2:$B$14,MATCH(G119,Lookups!$A$2:$A$14,0)),"Not found") | J119: =IFERROR(INDEX(Lookups!$E$2:$E$14,MATCH(G119,Lookups!$A$2:$A$14,0)),"") | K119: CT | L119: =IF(J119="n/a","n/a",IFERROR(IF(ABS(INDEX(Lookups!$H$2:$H$5,MATCH(J119,Lookups!$G$2:$G$5,0))-INDEX(Lookups!$H$2:$H$5,MATCH(K119,Lookups!$G$2:$G$5,0)))<=1,"Yes","No"),"Check")) | M119: 25748.88 | N119: Yes | O119: 3 | Q119: =IF(N119<>"Yes","n/a",IF(OR(AND(O119<>"",O119>$W$1),P119="Y"),"Yes",IF(O119<>"","No","Pending"))) | S119: Natalia Sanchez | T119: State | U119: Email & SMS, Engagement & Sentiment, Recurring Services | X119: A | Y119: 67.4 | Z119: 0.625 | AA119: 0.6544 | AB119: 2 | AC119: Expansion | AD119: 0.8 | AE119: reported
A120: Minnesota State Auditor's Office | B120: Minnesota | C120: MN | D120: State | E120: Joe Spair | F120: Brooke Minichino | G120: Brooke Minichino | H120: =IF(F120="(not in WIP)","New to Enterprise",IF(F120=G120,"No","Yes")) | I120: =IFERROR(INDEX(Lookups!$B$2:$B$14,MATCH(G120,Lookups!$A$2:$A$14,0)),"Not found") | J120: =IFERROR(INDEX(Lookups!$E$2:$E$14,MATCH(G120,Lookups!$A$2:$A$14,0)),"") | K120: CT | L120: =IF(J120="n/a","n/a",IFERROR(IF(ABS(INDEX(Lookups!$H$2:$H$5,MATCH(J120,Lookups!$G$2:$G$5,0))-INDEX(Lookups!$H$2:$H$5,MATCH(K120,Lookups!$G$2:$G$5,0)))<=1,"Yes","No"),"Check")) | M120: 22471.75 | N120: Yes | O120: 3 | Q120: =IF(N120<>"Yes","n/a",IF(OR(AND(O120<>"",O120>$W$1),P120="Y"),"Yes",IF(O120<>"","No","Pending"))) | S120: Kerrian Dailey | T120: State | U120: Email & SMS, Engagement & Sentiment, Recurring Services | X120: A | Y120: 67.4 | Z120: 0.625 | AA120: 0.6544 | AB120: 2 | AC120: Expansion | AD120: 0.8 | AE120: reported
A121: Milwaukee County WI | B121: Milwaukee County WI | C121: WI | D121: Local ENT | E121: Tyler Carlson | F121: Brooke Minichino | G121: Brooke Minichino | H121: =IF(F121="(not in WIP)","New to Enterprise",IF(F121=G121,"No","Yes")) | I121: =IFERROR(INDEX(Lookups!$B$2:$B$14,MATCH(G121,Lookups!$A$2:$A$14,0)),"Not found") | J121: =IFERROR(INDEX(Lookups!$E$2:$E$14,MATCH(G121,Lookups!$A$2:$A$14,0)),"") | K121: CT | L121: =IF(J121="n/a","n/a",IFERROR(IF(ABS(INDEX(Lookups!$H$2:$H$5,MATCH(J121,Lookups!$G$2:$G$5,0))-INDEX(Lookups!$H$2:$H$5,MATCH(K121,Lookups!$G$2:$G$5,0)))<=1,"Yes","No"),"Check")) | M121: 183209.4 | N121: Yes | O121: 4 | Q121: =IF(N121<>"Yes","n/a",IF(OR(AND(O121<>"",O121>$W$1),P121="Y"),"Yes",IF(O121<>"","No","Pending"))) | S121: Carolina Cambronero | T121: Local ENT | U121: Agenda & Video, Customer Service, Engagement & Sentiment, Forms & Workflows | X121: C | Y121: 44.7 | Z121: 0.5 | AA121: 0.4682 | AB121: 3 | AC121: Defend | AD121: 0.5 | AE121: reported
A122: Milwaukee, WI | B122: Milwaukee, WI | C122: WI | D122: Local ENT | E122: Tyler Carlson | F122: Brooke Minichino | G122: Brooke Minichino | H122: =IF(F122="(not in WIP)","New to Enterprise",IF(F122=G122,"No","Yes")) | I122: =IFERROR(INDEX(Lookups!$B$2:$B$14,MATCH(G122,Lookups!$A$2:$A$14,0)),"Not found") | J122: =IFERROR(INDEX(Lookups!$E$2:$E$14,MATCH(G122,Lookups!$A$2:$A$14,0)),"") | K122: CT | L122: =IF(J122="n/a","n/a",IFERROR(IF(ABS(INDEX(Lookups!$H$2:$H$5,MATCH(J122,Lookups!$G$2:$G$5,0))-INDEX(Lookups!$H$2:$H$5,MATCH(K122,Lookups!$G$2:$G$5,0)))<=1,"Yes","No"),"Check")) | M122: 171842.49 | N122: Yes | O122: 5 | Q122: =IF(N122<>"Yes","n/a",IF(OR(AND(O122<>"",O122>$W$1),P122="Y"),"Yes",IF(O122<>"","No","Pending"))) | S122: Carolina Cambronero | T122: Local ENT | U122: Agenda & Video, Email & SMS, Public Records Request, Short-term Rentals, Experience Agents | X122: C | Y122: 44.7 | Z122: 0.375 | AA122: 0.4182 | AB122: 3 | AC122: Defend | AD122: 0.5 | AE122: reported
A123: Wisconsin Court System | B123: Wisconsin | C123: WI | D123: State | E123: Joe Spair | F123: Brooke Minichino | G123: Brooke Minichino | H123: =IF(F123="(not in WIP)","New to Enterprise",IF(F123=G123,"No","Yes")) | I123: =IFERROR(INDEX(Lookups!$B$2:$B$14,MATCH(G123,Lookups!$A$2:$A$14,0)),"Not found") | J123: =IFERROR(INDEX(Lookups!$E$2:$E$14,MATCH(G123,Lookups!$A$2:$A$14,0)),"") | K123: CT | L123: =IF(J123="n/a","n/a",IFERROR(IF(ABS(INDEX(Lookups!$H$2:$H$5,MATCH(J123,Lookups!$G$2:$G$5,0))-INDEX(Lookups!$H$2:$H$5,MATCH(K123,Lookups!$G$2:$G$5,0)))<=1,"Yes","No"),"Check")) | M123: 26810.58 | N123: Yes | O123: 3 | Q123: =IF(N123<>"Yes","n/a",IF(OR(AND(O123<>"",O123>$W$1),P123="Y"),"Yes",IF(O123<>"","No","Pending"))) | S123: Alejandro Solano | T123: State | U123: Email & SMS, Engagement & Sentiment, Recurring Services | X123: B | Y123: 57.8 | Z123: 0.625 | AA123: 0.5968 | AB123: 2 | AC123: Expansion | AD123: 0.8 | AE123: reported
A124: Wisconsin Department of Public Instruction | B124: Wisconsin | C124: WI | D124: State | E124: Joe Spair | F124: Brooke Minichino | G124: Brooke Minichino | H124: =IF(F124="(not in WIP)","New to Enterprise",IF(F124=G124,"No","Yes")) | I124: =IFERROR(INDEX(Lookups!$B$2:$B$14,MATCH(G124,Lookups!$A$2:$A$14,0)),"Not found") | J124: =IFERROR(INDEX(Lookups!$E$2:$E$14,MATCH(G124,Lookups!$A$2:$A$14,0)),"") | K124: CT | L124: =IF(J124="n/a","n/a",IFERROR(IF(ABS(INDEX(Lookups!$H$2:$H$5,MATCH(J124,Lookups!$G$2:$G$5,0))-INDEX(Lookups!$H$2:$H$5,MATCH(K124,Lookups!$G$2:$G$5,0)))<=1,"Yes","No"),"Check")) | M124: 26733.86 | N124: Yes | O124: 3 | Q124: =IF(N124<>"Yes","n/a",IF(OR(AND(O124<>"",O124>$W$1),P124="Y"),"Yes",IF(O124<>"","No","Pending"))) | S124: Alejandro Solano | T124: State | U124: Email & SMS, Engagement & Sentiment, Recurring Services | X124: B | Y124: 57.8 | Z124: 0.625 | AA124: 0.5968 | AB124: 2 | AC124: Expansion | AD124: 0.8 | AE124: reported
A125: San Antonio, TX | B125: San Antonio, TX | C125: TX | D125: Local ENT | E125: Cedric Simpkins | F125: Steffany Amador | G125: Steffany Amador | H125: =IF(F125="(not in WIP)","New to Enterprise",IF(F125=G125,"No","Yes")) | I125: =IFERROR(INDEX(Lookups!$B$2:$B$14,MATCH(G125,Lookups!$A$2:$A$14,0)),"Not found") | J125: =IFERROR(INDEX(Lookups!$E$2:$E$14,MATCH(G125,Lookups!$A$2:$A$14,0)),"") | K125: CT | L125: =IF(J125="n/a","n/a",IFERROR(IF(ABS(INDEX(Lookups!$H$2:$H$5,MATCH(J125,Lookups!$G$2:$G$5,0))-INDEX(Lookups!$H$2:$H$5,MATCH(K125,Lookups!$G$2:$G$5,0)))<=1,"Yes","No"),"Check")) | M125: 756412.27 | N125: Yes | O125: 6 | Q125: =IF(N125<>"Yes","n/a",IF(OR(AND(O125<>"",O125>$W$1),P125="Y"),"Yes",IF(O125<>"","No","Pending"))) | S125: Steffany Amador | T125: Local ENT | U125: Agenda & Video, Engagement & Sentiment, Forms & Workflows, Public Records Request, Service Request Management, Websites, Portals, & Intranets | X125: A | Y125: 63.1 | Z125: 0.25 | AA125: 0.4786 | AB125: 3 | AC125: Defend | AD125: 0.5 | AE125: reported
A126: Pedernales Electric Cooperative | B126: Pedernales Electric Cooperative | C126: TX | D126: Local ENT | E126: Cedric Simpkins | F126: (not in WIP) | G126: Steffany Amador | H126: =IF(F126="(not in WIP)","New to Enterprise",IF(F126=G126,"No","Yes")) | I126: =IFERROR(INDEX(Lookups!$B$2:$B$14,MATCH(G126,Lookups!$A$2:$A$14,0)),"Not found") | J126: =IFERROR(INDEX(Lookups!$E$2:$E$14,MATCH(G126,Lookups!$A$2:$A$14,0)),"") | K126: CT | L126: =IF(J126="n/a","n/a",IFERROR(IF(ABS(INDEX(Lookups!$H$2:$H$5,MATCH(J126,Lookups!$G$2:$G$5,0))-INDEX(Lookups!$H$2:$H$5,MATCH(K126,Lookups!$G$2:$G$5,0)))<=1,"Yes","No"),"Check")) | M126: 131088.1 | N126: Yes | O126: 2 | Q126: =IF(N126<>"Yes","n/a",IF(OR(AND(O126<>"",O126>$W$1),P126="Y"),"Yes",IF(O126<>"","No","Pending"))) | S126: Natalia Sanchez | T126: Local ENT | U126: Agenda & Video, Public Records Request | X126: A | Y126: 63.1 | Z126: 0.75 | AA126: 0.6786 | AB126: 1 | AC126: Growth engine | AD126: 1 | AE126: reported
A127: VIA Metropolitan Transit | B127: Bexar County TX | C127: TX | D127: Local ENT | E127: Cedric Simpkins | F127: (not in WIP) | G127: Steffany Amador | H127: =IF(F127="(not in WIP)","New to Enterprise",IF(F127=G127,"No","Yes")) | I127: =IFERROR(INDEX(Lookups!$B$2:$B$14,MATCH(G127,Lookups!$A$2:$A$14,0)),"Not found") | J127: =IFERROR(INDEX(Lookups!$E$2:$E$14,MATCH(G127,Lookups!$A$2:$A$14,0)),"") | K127: CT | L127: =IF(J127="n/a","n/a",IFERROR(IF(ABS(INDEX(Lookups!$H$2:$H$5,MATCH(J127,Lookups!$G$2:$G$5,0))-INDEX(Lookups!$H$2:$H$5,MATCH(K127,Lookups!$G$2:$G$5,0)))<=1,"Yes","No"),"Check")) | M127: 98314.78 | N127: Yes | O127: 1 | Q127: =IF(N127<>"Yes","n/a",IF(OR(AND(O127<>"",O127>$W$1),P127="Y"),"Yes",IF(O127<>"","No","Pending"))) | S127: Carlos Torres | T127: Local ENT | U127: Agenda & Video | X127: A | Y127: 63.1 | Z127: 0.875 | AA127: 0.7286 | AB127: 1 | AC127: Growth engine | AD127: 1 | AE127: reported
A128: Texas Department of Motor Vehicles | B128: Texas Department of Motor Vehicles | C128: TX | D128: State | E128: No State AE shown (TX) | F128: Taylor Roman | G128: Steffany Amador | H128: =IF(F128="(not in WIP)","New to Enterprise",IF(F128=G128,"No","Yes")) | I128: =IFERROR(INDEX(Lookups!$B$2:$B$14,MATCH(G128,Lookups!$A$2:$A$14,0)),"Not found") | J128: =IFERROR(INDEX(Lookups!$E$2:$E$14,MATCH(G128,Lookups!$A$2:$A$14,0)),"") | K128: CT | L128: =IF(J128="n/a","n/a",IFERROR(IF(ABS(INDEX(Lookups!$H$2:$H$5,MATCH(J128,Lookups!$G$2:$G$5,0))-INDEX(Lookups!$H$2:$H$5,MATCH(K128,Lookups!$G$2:$G$5,0)))<=1,"Yes","No"),"Check")) | M128: 330981.51 | N128: Yes | O128: 2 | Q128: =IF(N128<>"Yes","n/a",IF(OR(AND(O128<>"",O128>$W$1),P128="Y"),"Yes",IF(O128<>"","No","Pending"))) | S128: Taylor Roman | T128: State | U128: Email & SMS, Public Records Request | X128: A | Y128: 82.4 | Z128: 0.75 | AA128: 0.7944 | AB128: 1 | AC128: Growth engine | AD128: 1 | AE128: reported
A129: Texas Department of Transportation (TXDOT) | B129: Texas | C129: TX | D129: State | E129: No State AE shown (TX) | F129: Taylor Roman | G129: Steffany Amador | H129: =IF(F129="(not in WIP)","New to Enterprise",IF(F129=G129,"No","Yes")) | I129: =IFERROR(INDEX(Lookups!$B$2:$B$14,MATCH(G129,Lookups!$A$2:$A$14,0)),"Not found") | J129: =IFERROR(INDEX(Lookups!$E$2:$E$14,MATCH(G129,Lookups!$A$2:$A$14,0)),"") | K129: CT | L129: =IF(J129="n/a","n/a",IFERROR(IF(ABS(INDEX(Lookups!$H$2:$H$5,MATCH(J129,Lookups!$G$2:$G$5,0))-INDEX(Lookups!$H$2:$H$5,MATCH(K129,Lookups!$G$2:$G$5,0)))<=1,"Yes","No"),"Check")) | M129: 321374.86 | N129: Yes | O129: 3 | Q129: =IF(N129<>"Yes","n/a",IF(OR(AND(O129<>"",O129>$W$1),P129="Y"),"Yes",IF(O129<>"","No","Pending"))) | S129: Taylor Roman | T129: State | U129: Agenda & Video, Email & SMS, Public Records Request | X129: A | Y129: 82.4 | Z129: 0.625 | AA129: 0.7444 | AB129: 1 | AC129: Growth engine | AD129: 1 | AE129: reported
... A138: Texas Ethics Commission | B138: Texas | C138: TX | D138: State | E138: No State AE shown (TX) | F138: Taylor Roman | G138: Steffany Amador | H138: =IF(F138="(not in WIP)","New to Enterprise",IF(F138=G138,"No","Yes")) | I138: =IFERROR(INDEX(Lookups!$B$2:$B$14,MATCH(G138,Lookups!$A$2:$A$14,0)),"Not found") | J138: =IFERROR(INDEX(Lookups!$E$2:$E$14,MATCH(G138,Lookups!$A$2:$A$14,0)),"") | K138: CT | L138: =IF(J138="n/a","n/a",IFERROR(IF(ABS(INDEX(Lookups!$H$2:$H$5,MATCH(J138,Lookups!$G$2:$G$5,0))-INDEX(Lookups!$H$2:$H$5,MATCH(K138,Lookups!$G$2:$G$5,0)))<=1,"Yes","No"),"Check")) | M138: 29497.5 | N138: Yes | O138: 1 | Q138: =IF(N138<>"Yes","n/a",IF(OR(AND(O138<>"",O138>$W$1),P138="Y"),"Yes",IF(O138<>"","No","Pending"))) | S138: Natalia Sanchez | T138: State | U138: Public Records Request | X138: A | Y138: 82.4 | Z138: 0.875 | AA138: 0.8444 | AB138: 2 | AC138: Expansion | AD138: 0.8 | AE138: reported
A139: Texas Lottery Commission | B139: Texas | C139: TX | D139: State | E139: No State AE shown (TX) | F139: Taylor Roman | G139: Steffany Amador | H139: =IF(F139="(not in WIP)","New to Enterprise",IF(F139=G139,"No","Yes")) | I139: =IFERROR(INDEX(Lookups!$B$2:$B$14,MATCH(G139,Lookups!$A$2:$A$14,0)),"Not found") | J139: =IFERROR(INDEX(Lookups!$E$2:$E$14,MATCH(G139,Lookups!$A$2:$A$14,0)),"") | K139: CT | L139: =IF(J139="n/a","n/a",IFERROR(IF(ABS(INDEX(Lookups!$H$2:$H$5,MATCH(J139,Lookups!$G$2:$G$5,0))-INDEX(Lookups!$H$2:$H$5,MATCH(K139,Lookups!$G$2:$G$5,0)))<=1,"Yes","No"),"Check")) | M139: 28897.72 | N139: Yes | O139: 0 | Q139: =IF(N139<>"Yes","n/a",IF(OR(AND(O139<>"",O139>$W$1),P139="Y"),"Yes",IF(O139<>"","No","Pending"))) | S139: Savannah Lane | T139: State | X139: A | Y139: 82.4 | Z139: 0.75 | AA139: 0.7944 | AB139: 2 | AC139: Expansion | AD139: 0.8 | AE139: imputed
A140: Texas Board of Nursing | B140: Texas | C140: TX | D140: State | E140: No State AE shown (TX) | F140: Taylor Roman | G140: Steffany Amador | H140: =IF(F140="(not in WIP)","New to Enterprise",IF(F140=G140,"No","Yes")) | I140: =IFERROR(INDEX(Lookups!$B$2:$B$14,MATCH(G140,Lookups!$A$2:$A$14,0)),"Not found") | J140: =IFERROR(INDEX(Lookups!$E$2:$E$14,MATCH(G140,Lookups!$A$2:$A$14,0)),"") | K140: CT | L140: =IF(J140="n/a","n/a",IFERROR(IF(ABS(INDEX(Lookups!$H$2:$H$5,MATCH(J140,Lookups!$G$2:$G$5,0))-INDEX(Lookups!$H$2:$H$5,MATCH(K140,Lookups!$G$2:$G$5,0)))<=1,"Yes","No"),"Check")) | M140: 25883.03 | N140: Yes | O140: 5 | Q140: =IF(N140<>"Yes","n/a",IF(OR(AND(O140<>"",O140>$W$1),P140="Y"),"Yes",IF(O140<>"","No","Pending"))) | S140: Kerrian Dailey | T140: State | U140: Email & SMS, Engagement & Sentiment, Forms & Workflows, Recurring Services, Websites, Portals, & Intranets | X140: A | Y140: 82.4 | Z140: 0.375 | AA140: 0.6444 | AB140: 2 | AC140: Expansion | AD140: 0.8 | AE140: reported
A141: Texas Charitable Bingo | B141: Texas | C141: TX | D141: State | E141: No State AE shown (TX) | F141: Taylor Roman | G141: Steffany Amador | H141: =IF(F141="(not in WIP)","New to Enterprise",IF(F141=G141,"No","Yes")) | I141: =IFERROR(INDEX(Lookups!$B$2:$B$14,MATCH(G141,Lookups!$A$2:$A$14,0)),"Not found") | J141: =IFERROR(INDEX(Lookups!$E$2:$E$14,MATCH(G141,Lookups!$A$2:$A$14,0)),"") | K141: CT | L141: =IF(J141="n/a","n/a",IFERROR(IF(ABS(INDEX(Lookups!$H$2:$H$5,MATCH(J141,Lookups!$G$2:$G$5,0))-INDEX(Lookups!$H$2:$H$5,MATCH(K141,Lookups!$G$2:$G$5,0)))<=1,"Yes","No"),"Check")) | M141: 0 | N141: No (Allocated) | O141: 0 | Q141: =IF(N141<>"Yes","n/a",IF(OR(AND(O141<>"",O141>$W$1),P141="Y"),"Yes",IF(O141<>"","No","Pending"))) | S141: Savannah Lane | T141: State | X141: A | Y141: 82.4 | Z141: 0.75 | AA141: 0.7944 | AB141: 2 | AC141: Expansion | AD141: 0 | AE141: imputed
A142: Connecticut Department of Administrative Services | B142: Connecticut | C142: CT | D142: State | E142: Stephanie DelSignore | F142: Halena Martin | G142: Halena Martin | H142: =IF(F142="(not in WIP)","New to Enterprise",IF(F142=G142,"No","Yes")) | I142: =IFERROR(INDEX(Lookups!$B$2:$B$14,MATCH(G142,Lookups!$A$2:$A$14,0)),"Not found") | J142: =IFERROR(INDEX(Lookups!$E$2:$E$14,MATCH(G142,Lookups!$A$2:$A$14,0)),"") | K142: ET | L142: =IF(J142="n/a","n/a",IFERROR(IF(ABS(INDEX(Lookups!$H$2:$H$5,MATCH(J142,Lookups!$G$2:$G$5,0))-INDEX(Lookups!$H$2:$H$5,MATCH(K142,Lookups!$G$2:$G$5,0)))<=1,"Yes","No"),"Check")) | M142: 605766.08 | N142: Yes | O142: 1 | Q142: =IF(N142<>"Yes","n/a",IF(OR(AND(O142<>"",O142>$W$1),P142="Y"),"Yes",IF(O142<>"","No","Pending"))) | S142: Carolina Prieto | T142: State | U142: Public Records Request | X142: C | Y142: 40.5 | Z142: 0.875 | AA142: 0.593 | AB142: 1 | AC142: Growth engine | AD142: 1 | AE142: reported
A143: Connecticut Workers' Compensation Commission | B143: Connecticut | C143: CT | D143: State | E143: Stephanie DelSignore | F143: Halena Martin | G143: Halena Martin | H143: =IF(F143="(not in WIP)","New to Enterprise",IF(F143=G143,"No","Yes")) | I143: =IFERROR(INDEX(Lookups!$B$2:$B$14,MATCH(G143,Lookups!$A$2:$A$14,0)),"Not found") | J143: =IFERROR(INDEX(Lookups!$E$2:$E$14,MATCH(G143,Lookups!$A$2:$A$14,0)),"") | K143: ET | L143: =IF(J143="n/a","n/a",IFERROR(IF(ABS(INDEX(Lookups!$H$2:$H$5,MATCH(J143,Lookups!$G$2:$G$5,0))-INDEX(Lookups!$H$2:$H$5,MATCH(K143,Lookups!$G$2:$G$5,0)))<=1,"Yes","No"),"Check")) | M143: 69192.83 | N143: Yes | O143: 2 | Q143: =IF(N143<>"Yes","n/a",IF(OR(AND(O143<>"",O143>$W$1),P143="Y"),"Yes",IF(O143<>"","No","Pending"))) | S143: Carolina Prieto | T143: State | U143: Other, Public Records Request | X143: C | Y143: 40.5 | Z143: 0.75 | AA143: 0.543 | AB143: 4 | AC143: Maintain | AD143: 0.3 | AE143: reported
A144: Connecticut Public Utilities Regulatory Authority [PURA], | B144: Connecticut Public Utilities Regulatory Authority [PURA], | C144: CT | D144: State | E144: Stephanie DelSignore | F144: Halena Martin | G144: Halena Martin | H144: =IF(F144="(not in WIP)","New to Enterprise",IF(F144=G144,"No","Yes")) | I144: =IFERROR(INDEX(Lookups!$B$2:$B$14,MATCH(G144,Lookups!$A$2:$A$14,0)),"Not found") | J144: =IFERROR(INDEX(Lookups!$E$2:$E$14,MATCH(G144,Lookups!$A$2:$A$14,0)),"") | K144: ET | L144: =IF(J144="n/a","n/a",IFERROR(IF(ABS(INDEX(Lookups!$H$2:$H$5,MATCH(J144,Lookups!$G$2:$G$5,0))-INDEX(Lookups!$H$2:$H$5,MATCH(K144,Lookups!$G$2:$G$5,0)))<=1,"Yes","No"),"Check")) | M144: 40636.87 | N144: Yes | O144: 1 | Q144: =IF(N144<>"Yes","n/a",IF(OR(AND(O144<>"",O144>$W$1),P144="Y"),"Yes",IF(O144<>"","No","Pending"))) | S144: Ashley Hill | T144: State | U144: Public Records Request | X144: C | Y144: 40.5 | Z144: 0.875 | AA144: 0.593 | AB144: 2 | AC144: Expansion | AD144: 0.8 | AE144: reported
A145: Connecticut Department of Emergency Services and Public Protection | B145: Connecticut | C145: CT | D145: State | E145: Stephanie DelSignore | F145: Halena Martin | G145: Halena Martin | H145: =IF(F145="(not in WIP)","New to Enterprise",IF(F145=G145,"No","Yes")) | I145: =IFERROR(INDEX(Lookups!$B$2:$B$14,MATCH(G145,Lookups!$A$2:$A$14,0)),"Not found") | J145: =IFERROR(INDEX(Lookups!$E$2:$E$14,MATCH(G145,Lookups!$A$2:$A$14,0)),"") | K145: ET | L145: =IF(J145="n/a","n/a",IFERROR(IF(ABS(INDEX(Lookups!$H$2:$H$5,MATCH(J145,Lookups!$G$2:$G$5,0))-INDEX(Lookups!$H$2:$H$5,MATCH(K145,Lookups!$G$2:$G$5,0)))<=1,"Yes","No"),"Check")) | M145: 29568.49 | N145: Yes | O145: 1 | Q145: =IF(N145<>"Yes","n/a",IF(OR(AND(O145<>"",O145>$W$1),P145="Y"),"Yes",IF(O145<>"","No","Pending"))) | S145: Carolina Prieto | T145: State | U145: Public Records Request | X145: C | Y145: 40.5 | Z145: 0.875 | AA145: 0.593 | AB145: 2 | AC145: Expansion | AD145: 0.8 | AE145: reported
A146: Connecticut Office of the Healthcare Advocate | B146: Connecticut | C146: CT | D146: State | E146: Stephanie DelSignore | F146: Halena Martin | G146: Halena Martin | H146: =IF(F146="(not in WIP)","New to Enterprise",IF(F146=G146,"No","Yes")) | I146: =IFERROR(INDEX(Lookups!$B$2:$B$14,MATCH(G146,Lookups!$A$2:$A$14,0)),"Not found") | J146: =IFERROR(INDEX(Lookups!$E$2:$E$14,MATCH(G146,Lookups!$A$2:$A$14,0)),"") | K146: ET | L146: =IF(J146="n/a","n/a",IFERROR(IF(ABS(INDEX(Lookups!$H$2:$H$5,MATCH(J146,Lookups!$G$2:$G$5,0))-INDEX(Lookups!$H$2:$H$5,MATCH(K146,Lookups!$G$2:$G$5,0)))<=1,"Yes","No"),"Check")) | M146: 0 | N146: No (Allocated) | O146: 0 | Q146: =IF(N146<>"Yes","n/a",IF(OR(AND(O146<>"",O146>$W$1),P146="Y"),"Yes",IF(O146<>"","No","Pending"))) | S146: Carolina Prieto | T146: State | X146: C | Y146: 40.5 | Z146: 0.75 | AA146: 0.543 | AB146: 4 | AC146: Maintain | AD146: 0 | AE146: imputed
A147: Connecticut Office of the Chief Medical Examiner | B147: Connecticut | C147: CT | D147: State | E147: Stephanie DelSignore | F147: Halena Martin | G147: Halena Martin | H147: =IF(F147="(not in WIP)","New to Enterprise",IF(F147=G147,"No","Yes")) | I147: =IFERROR(INDEX(Lookups!$B$2:$B$14,MATCH(G147,Lookups!$A$2:$A$14,0)),"Not found") | J147: =IFERROR(INDEX(Lookups!$E$2:$E$14,MATCH(G147,Lookups!$A$2:$A$14,0)),"") | K147: ET | L147: =IF(J147="n/a","n/a",IFERROR(IF(ABS(INDEX(Lookups!$H$2:$H$5,MATCH(J147,Lookups!$G$2:$G$5,0))-INDEX(Lookups!$H$2:$H$5,MATCH(K147,Lookups!$G$2:$G$5,0)))<=1,"Yes","No"),"Check")) | M147: 0 | N147: No (Allocated) | O147: 0 | Q147: =IF(N147<>"Yes","n/a",IF(OR(AND(O147<>"",O147>$W$1),P147="Y"),"Yes",IF(O147<>"","No","Pending"))) | S147: Carolina Prieto | T147: State | X147: C | Y147: 40.5 | Z147: 0.75 | AA147: 0.543 | AB147: 4 | AC147: Maintain | AD147: 0 | AE147: imputed
A148: Connecticut Office of the Governor | B148: Connecticut | C148: CT | D148: State | E148: Stephanie DelSignore | F148: Halena Martin | G148: Halena Martin | H148: =IF(F148="(not in WIP)","New to Enterprise",IF(F148=G148,"No","Yes")) | I148: =IFERROR(INDEX(Lookups!$B$2:$B$14,MATCH(G148,Lookups!$A$2:$A$14,0)),"Not found") | J148: =IFERROR(INDEX(Lookups!$E$2:$E$14,MATCH(G148,Lookups!$A$2:$A$14,0)),"") | K148: ET | L148: =IF(J148="n/a","n/a",IFERROR(IF(ABS(INDEX(Lookups!$H$2:$H$5,MATCH(J148,Lookups!$G$2:$G$5,0))-INDEX(Lookups!$H$2:$H$5,MATCH(K148,Lookups!$G$2:$G$5,0)))<=1,"Yes","No"),"Check")) | M148: 0 | N148: No (Allocated) | O148: 0 | Q148: =IF(N148<>"Yes","n/a",IF(OR(AND(O148<>"",O148>$W$1),P148="Y"),"Yes",IF(O148<>"","No","Pending"))) | S148: Carolina Prieto | T148: State | X148: C | Y148: 40.5 | Z148: 0.75 | AA148: 0.543 | AB148: 4 | AC148: Maintain | AD148: 0 | AE148: imputed
A149: Connecticut Office of Lieutenant Governor | B149: Connecticut | C149: CT | D149: State | E149: Stephanie DelSignore | F149: Halena Martin | G149: Halena Martin | H149: =IF(F149="(not in WIP)","New to Enterprise",IF(F149=G149,"No","Yes")) | I149: =IFERROR(INDEX(Lookups!$B$2:$B$14,MATCH(G149,Lookups!$A$2:$A$14,0)),"Not found") | J149: =IFERROR(INDEX(Lookups!$E$2:$E$14,MATCH(G149,Lookups!$A$2:$A$14,0)),"") | K149: ET | L149: =IF(J149="n/a","n/a",IFERROR(IF(ABS(INDEX(Lookups!$H$2:$H$5,MATCH(J149,Lookups!$G$2:$G$5,0))-INDEX(Lookups!$H$2:$H$5,MATCH(K149,Lookups!$G$2:$G$5,0)))<=1,"Yes","No"),"Check")) | M149: 0 | N149: No (Allocated) | O149: 0 | Q149: =IF(N149<>"Yes","n/a",IF(OR(AND(O149<>"",O149>$W$1),P149="Y"),"Yes",IF(O149<>"","No","Pending"))) | S149: Carolina Prieto | T149: State | X149: C | Y149: 40.5 | Z149: 0.75 | AA149: 0.543 | AB149: 4 | AC149: Maintain | AD149: 0 | AE149: imputed
A150: Connecticut Office of the Attorney General | B150: Connecticut | C150: CT | D150: State | E150: Stephanie DelSignore | F150: Halena Martin | G150: Halena Martin | H150: =IF(F150="(not in WIP)","New to Enterprise",IF(F150=G150,"No","Yes")) | I150: =IFERROR(INDEX(Lookups!$B$2:$B$14,MATCH(G150,Lookups!$A$2:$A$14,0)),"Not found") | J150: =IFERROR(INDEX(Lookups!$E$2:$E$14,MATCH(G150,Lookups!$A$2:$A$14,0)),"") | K150: ET | L150: =IF(J150="n/a","n/a",IFERROR(IF(ABS(INDEX(Lookups!$H$2:$H$5,MATCH(J150,Lookups!$G$2:$G$5,0))-INDEX(Lookups!$H$2:$H$5,MATCH(K150,Lookups!$G$2:$G$5,0)))<=1,"Yes","No"),"Check")) | M150: 0 | N150: No (Allocated) | O150: 0 | Q150: =IF(N150<>"Yes","n/a",IF(OR(AND(O150<>"",O150>$W$1),P150="Y"),"Yes",IF(O150<>"","No","Pending"))) | S150: Carolina Prieto | T150: State | X150: C | Y150: 40.5 | Z150: 0.75 | AA150: 0.543 | AB150: 4 | AC150: Maintain | AD150: 0 | AE150: imputed
A151: Connecticut Criminal Justice Division | B151: Connecticut | C151: CT | D151: State | E151: Stephanie DelSignore | F151: Halena Martin | G151: Halena Martin | H151: =IF(F151="(not in WIP)","New to Enterprise",IF(F151=G151,"No","Yes")) | I151: =IFERROR(INDEX(Lookups!$B$2:$B$14,MATCH(G151,Lookups!$A$2:$A$14,0)),"Not found") | J151: =IFERROR(INDEX(Lookups!$E$2:$E$14,MATCH(G151,Lookups!$A$2:$A$14,0)),"") | K151: ET | L151: =IF(J151="n/a","n/a",IFERROR(IF(ABS(INDEX(Lookups!$H$2:$H$5,MATCH(J151,Lookups!$G$2:$G$5,0))-INDEX(Lookups!$H$2:$H$5,MATCH(K151,Lookups!$G$2:$G$5,0)))<=1,"Yes","No"),"Check")) | M151: 0 | N151: No (Allocated) | O151: 0 | Q151: =IF(N151<>"Yes","n/a",IF(OR(AND(O151<>"",O151>$W$1),P151="Y"),"Yes",IF(O151<>"","No","Pending"))) | S151: Carolina Prieto | T151: State | X151: C | Y151: 40.5 | Z151: 0.75 | AA151: 0.543 | AB151: 4 | AC151: Maintain | AD151: 0 | AE151: imputed
A152: Connecticut Contracting Standards Board | B152: Connecticut | C152: CT | D152: State | E152: Stephanie DelSignore | F152: Halena Martin | G152: Halena Martin | H152: =IF(F152="(not in WIP)","New to Enterprise",IF(F152=G152,"No","Yes")) | I152: =IFERROR(INDEX(Lookups!$B$2:$B$14,MATCH(G152,Lookups!$A$2:$A$14,0)),"Not found") | J152: =IFERROR(INDEX(Lookups!$E$2:$E$14,MATCH(G152,Lookups!$A$2:$A$14,0)),"") | K152: ET | L152: =IF(J152="n/a","n/a",IFERROR(IF(ABS(INDEX(Lookups!$H$2:$H$5,MATCH(J152,Lookups!$G$2:$G$5,0))-INDEX(Lookups!$H$2:$H$5,MATCH(K152,Lookups!$G$2:$G$5,0)))<=1,"Yes","No"),"Check")) | M152: 0 | N152: No (Allocated) | O152: 0 | Q152: =IF(N152<>"Yes","n/a",IF(OR(AND(O152<>"",O152>$W$1),P152="Y"),"Yes",IF(O152<>"","No","Pending"))) | S152: Carolina Prieto | T152: State | X152: C | Y152: 40.5 | Z152: 0.75 | AA152: 0.543 | AB152: 4 | AC152: Maintain | AD152: 0 | AE152: imputed
A153: Connecticut Connecticut Technical Education and Career System | B153: Connecticut | C153: CT | D153: State | E153: Stephanie DelSignore | F153: Halena Martin | G153: Halena Martin | H153: =IF(F153="(not in WIP)","New to Enterprise",IF(F153=G153,"No","Yes")) | I153: =IFERROR(INDEX(Lookups!$B$2:$B$14,MATCH(G153,Lookups!$A$2:$A$14,0)),"Not found") | J153: =IFERROR(INDEX(Lookups!$E$2:$E$14,MATCH(G153,Lookups!$A$2:$A$14,0)),"") | K153: ET | L153: =IF(J153="n/a","n/a",IFERROR(IF(ABS(INDEX(Lookups!$H$2:$H$5,MATCH(J153,Lookups!$G$2:$G$5,0))-INDEX(Lookups!$H$2:$H$5,MATCH(K153,Lookups!$G$2:$G$5,0)))<=1,"Yes","No"),"Check")) | M153: 0 | N153: No (Allocated) | O153: 0 | Q153: =IF(N153<>"Yes","n/a",IF(OR(AND(O153<>"",O153>$W$1),P153="Y"),"Yes",IF(O153<>"","No","Pending"))) | S153: Carolina Prieto | T153: State | X153: C | Y153: 40.5 | Z153: 0.75 | AA153: 0.543 | AB153: 4 | AC153: Maintain | AD153: 0 | AE153: imputed
A154: Connecticut Department of Aging and Disability Services | B154: Connecticut | C154: CT | D154: State | E154: Stephanie DelSignore | F154: Halena Martin | G154: Halena Martin | H154: =IF(F154="(not in WIP)","New to Enterprise",IF(F154=G154,"No","Yes")) | I154: =IFERROR(INDEX(Lookups!$B$2:$B$14,MATCH(G154,Lookups!$A$2:$A$14,0)),"Not found") | J154: =IFERROR(INDEX(Lookups!$E$2:$E$14,MATCH(G154,Lookups!$A$2:$A$14,0)),"") | K154: ET | L154: =IF(J154="n/a","n/a",IFERROR(IF(ABS(INDEX(Lookups!$H$2:$H$5,MATCH(J154,Lookups!$G$2:$G$5,0))-INDEX(Lookups!$H$2:$H$5,MATCH(K154,Lookups!$G$2:$G$5,0)))<=1,"Yes","No"),"Check")) | M154: 0 | N154: No (Allocated) | O154: 0 | Q154: =IF(N154<>"Yes","n/a",IF(OR(AND(O154<>"",O154>$W$1),P154="Y"),"Yes",IF(O154<>"","No","Pending"))) | S154: Carolina Prieto | T154: State | X154: C | Y154: 40.5 | Z154: 0.75 | AA154: 0.543 | AB154: 4 | AC154: Maintain | AD154: 0 | AE154: imputed
A155: Connecticut Connecticut State Colleges and Universities | B155: Connecticut | C155: CT | D155: State | E155: Stephanie DelSignore | F155: Halena Martin | G155: Halena Martin | H155: =IF(F155="(not in WIP)","New to Enterprise",IF(F155=G155,"No","Yes")) | I155: =IFERROR(INDEX(Lookups!$B$2:$B$14,MATCH(G155,Lookups!$A$2:$A$14,0)),"Not found") | J155: =IFERROR(INDEX(Lookups!$E$2:$E$14,MATCH(G155,Lookups!$A$2:$A$14,0)),"") | K155: ET | L155: =IF(J155="n/a","n/a",IFERROR(IF(ABS(INDEX(Lookups!$H$2:$H$5,MATCH(J155,Lookups!$G$2:$G$5,0))-INDEX(Lookups!$H$2:$H$5,MATCH(K155,Lookups!$G$2:$G$5,0)))<=1,"Yes","No"),"Check")) | M155: 0 | N155: No (Allocated) | O155: 0 | Q155: =IF(N155<>"Yes","n/a",IF(OR(AND(O155<>"",O155>$W$1),P155="Y"),"Yes",IF(O155<>"","No","Pending"))) | S155: Carolina Prieto | T155: State | X155: C | Y155: 40.5 | Z155: 0.75 | AA155: 0.543 | AB155: 4 | AC155: Maintain | AD155: 0 | AE155: imputed
A156: Connecticut Department of Consumer Protection | B156: Connecticut | C156: CT | D156: State | E156: Stephanie DelSignore | F156: Halena Martin | G156: Halena Martin | H156: =IF(F156="(not in WIP)","New to Enterprise",IF(F156=G156,"No","Yes")) | I156: =IFERROR(INDEX(Lookups!$B$2:$B$14,MATCH(G156,Lookups!$A$2:$A$14,0)),"Not found") | J156: =IFERROR(INDEX(Lookups!$E$2:$E$14,MATCH(G156,Lookups!$A$2:$A$14,0)),"") | K156: ET | L156: =IF(J156="n/a","n/a",IFERROR(IF(ABS(INDEX(Lookups!$H$2:$H$5,MATCH(J156,Lookups!$G$2:$G$5,0))-INDEX(Lookups!$H$2:$H$5,MATCH(K156,Lookups!$G$2:$G$5,0)))<=1,"Yes","No"),"Check")) | M156: 0 | N156: No (Allocated) | O156: 0 | Q156: =IF(N156<>"Yes","n/a",IF(OR(AND(O156<>"",O156>$W$1),P156="Y"),"Yes",IF(O156<>"","No","Pending"))) | S156: Carolina Prieto | T156: State | X156: C | Y156: 40.5 | Z156: 0.75 | AA156: 0.543 | AB156: 4 | AC156: Maintain | AD156: 0 | AE156: imputed
A157: Connecticut Department of Banking | B157: Connecticut | C157: CT | D157: State | E157: Stephanie DelSignore | F157: Halena Martin | G157: Halena Martin | H157: =IF(F157="(not in WIP)","New to Enterprise",IF(F157=G157,"No","Yes")) | I157: =IFERROR(INDEX(Lookups!$B$2:$B$14,MATCH(G157,Lookups!$A$2:$A$14,0)),"Not found") | J157: =IFERROR(INDEX(Lookups!$E$2:$E$14,MATCH(G157,Lookups!$A$2:$A$14,0)),"") | K157: ET | L157: =IF(J157="n/a","n/a",IFERROR(IF(ABS(INDEX(Lookups!$H$2:$H$5,MATCH(J157,Lookups!$G$2:$G$5,0))-INDEX(Lookups!$H$2:$H$5,MATCH(K157,Lookups!$G$2:$G$5,0)))<=1,"Yes","No"),"Check")) | M157: 0 | N157: No (Allocated) | O157: 0 | Q157: =IF(N157<>"Yes","n/a",IF(OR(AND(O157<>"",O157>$W$1),P157="Y"),"Yes",IF(O157<>"","No","Pending"))) | S157: Carolina Prieto | T157: State | X157: C | Y157: 40.5 | Z157: 0.75 | AA157: 0.543 | AB157: 4 | AC157: Maintain | AD157: 0 | AE157: imputed
... A179: Connecticut Department of Transportation | B179: Connecticut | C179: CT | D179: State | E179: Stephanie DelSignore | F179: Halena Martin | G179: Halena Martin | H179: =IF(F179="(not in WIP)","New to Enterprise",IF(F179=G179,"No","Yes")) | I179: =IFERROR(INDEX(Lookups!$B$2:$B$14,MATCH(G179,Lookups!$A$2:$A$14,0)),"Not found") | J179: =IFERROR(INDEX(Lookups!$E$2:$E$14,MATCH(G179,Lookups!$A$2:$A$14,0)),"") | K179: ET | L179: =IF(J179="n/a","n/a",IFERROR(IF(ABS(INDEX(Lookups!$H$2:$H$5,MATCH(J179,Lookups!$G$2:$G$5,0))-INDEX(Lookups!$H$2:$H$5,MATCH(K179,Lookups!$G$2:$G$5,0)))<=1,"Yes","No"),"Check")) | M179: 0 | N179: No (Allocated) | O179: 0 | Q179: =IF(N179<>"Yes","n/a",IF(OR(AND(O179<>"",O179>$W$1),P179="Y"),"Yes",IF(O179<>"","No","Pending"))) | S179: Carolina Prieto | T179: State | X179: C | Y179: 40.5 | Z179: 0.75 | AA179: 0.543 | AB179: 4 | AC179: Maintain | AD179: 0 | AE179: imputed
A180: Massachusetts Department of Transportation | B180: Massachusetts | C180: MA | D180: State | E180: Stephanie DelSignore | F180: Halena Martin | G180: Halena Martin | H180: =IF(F180="(not in WIP)","New to Enterprise",IF(F180=G180,"No","Yes")) | I180: =IFERROR(INDEX(Lookups!$B$2:$B$14,MATCH(G180,Lookups!$A$2:$A$14,0)),"Not found") | J180: =IFERROR(INDEX(Lookups!$E$2:$E$14,MATCH(G180,Lookups!$A$2:$A$14,0)),"") | K180: ET | L180: =IF(J180="n/a","n/a",IFERROR(IF(ABS(INDEX(Lookups!$H$2:$H$5,MATCH(J180,Lookups!$G$2:$G$5,0))-INDEX(Lookups!$H$2:$H$5,MATCH(K180,Lookups!$G$2:$G$5,0)))<=1,"Yes","No"),"Check")) | M180: 214643.91 | N180: Yes | O180: 2 | Q180: =IF(N180<>"Yes","n/a",IF(OR(AND(O180<>"",O180>$W$1),P180="Y"),"Yes",IF(O180<>"","No","Pending"))) | S180: Taylor Roman | T180: State | U180: Email & SMS, Public Records Request | X180: A | Y180: 61.8 | Z180: 0.75 | AA180: 0.6708 | AB180: 1 | AC180: Growth engine | AD180: 1 | AE180: reported
A181: Maine | B181: Maine | C181: ME | D181: State | E181: No State AE shown (ME) | F181: Halena Martin | G181: Halena Martin | H181: =IF(F181="(not in WIP)","New to Enterprise",IF(F181=G181,"No","Yes")) | I181: =IFERROR(INDEX(Lookups!$B$2:$B$14,MATCH(G181,Lookups!$A$2:$A$14,0)),"Not found") | J181: =IFERROR(INDEX(Lookups!$E$2:$E$14,MATCH(G181,Lookups!$A$2:$A$14,0)),"") | K181: ET | L181: =IF(J181="n/a","n/a",IFERROR(IF(ABS(INDEX(Lookups!$H$2:$H$5,MATCH(J181,Lookups!$G$2:$G$5,0))-INDEX(Lookups!$H$2:$H$5,MATCH(K181,Lookups!$G$2:$G$5,0)))<=1,"Yes","No"),"Check")) | M181: 289386.97 | N181: Yes | O181: 3 | Q181: =IF(N181<>"Yes","n/a",IF(OR(AND(O181<>"",O181>$W$1),P181="Y"),"Yes",IF(O181<>"","No","Pending"))) | S181: Carolina Prieto | T181: State | U181: Email & SMS, Engagement & Sentiment, Recurring Services | X181: D | Y181: 26.9 | Z181: 0.625 | AA181: 0.4114 | AB181: 3 | AC181: Defend | AD181: 0.5 | AE181: reported
A182: Maine Department of Health & Human Services | B182: Maine | C182: ME | D182: State | E182: No State AE shown (ME) | F182: Halena Martin | G182: Halena Martin | H182: =IF(F182="(not in WIP)","New to Enterprise",IF(F182=G182,"No","Yes")) | I182: =IFERROR(INDEX(Lookups!$B$2:$B$14,MATCH(G182,Lookups!$A$2:$A$14,0)),"Not found") | J182: =IFERROR(INDEX(Lookups!$E$2:$E$14,MATCH(G182,Lookups!$A$2:$A$14,0)),"") | K182: ET | L182: =IF(J182="n/a","n/a",IFERROR(IF(ABS(INDEX(Lookups!$H$2:$H$5,MATCH(J182,Lookups!$G$2:$G$5,0))-INDEX(Lookups!$H$2:$H$5,MATCH(K182,Lookups!$G$2:$G$5,0)))<=1,"Yes","No"),"Check")) | M182: 67000 | N182: Yes | O182: 1 | Q182: =IF(N182<>"Yes","n/a",IF(OR(AND(O182<>"",O182>$W$1),P182="Y"),"Yes",IF(O182<>"","No","Pending"))) | S182: Carolina Prieto | T182: State | U182: Email & SMS | X182: D | Y182: 26.9 | Z182: 0.875 | AA182: 0.5114 | AB182: 4 | AC182: Maintain | AD182: 0.3 | AE182: reported
A183: Maine Department of Environmental Protection | B183: Maine | C183: ME | D183: State | E183: No State AE shown (ME) | F183: Halena Martin | G183: Halena Martin | H183: =IF(F183="(not in WIP)","New to Enterprise",IF(F183=G183,"No","Yes")) | I183: =IFERROR(INDEX(Lookups!$B$2:$B$14,MATCH(G183,Lookups!$A$2:$A$14,0)),"Not found") | J183: =IFERROR(INDEX(Lookups!$E$2:$E$14,MATCH(G183,Lookups!$A$2:$A$14,0)),"") | K183: ET | L183: =IF(J183="n/a","n/a",IFERROR(IF(ABS(INDEX(Lookups!$H$2:$H$5,MATCH(J183,Lookups!$G$2:$G$5,0))-INDEX(Lookups!$H$2:$H$5,MATCH(K183,Lookups!$G$2:$G$5,0)))<=1,"Yes","No"),"Check")) | M183: 0 | N183: No (Allocated) | O183: 0 | Q183: =IF(N183<>"Yes","n/a",IF(OR(AND(O183<>"",O183>$W$1),P183="Y"),"Yes",IF(O183<>"","No","Pending"))) | S183: Carolina Prieto | T183: State | X183: D | Y183: 26.9 | Z183: 0.75 | AA183: 0.4614 | AB183: 4 | AC183: Maintain | AD183: 0 | AE183: imputed
A184: Maine Department of Economic & Community Development | B184: Maine | C184: ME | D184: State | E184: No State AE shown (ME) | F184: Halena Martin | G184: Halena Martin | H184: =IF(F184="(not in WIP)","New to Enterprise",IF(F184=G184,"No","Yes")) | I184: =IFERROR(INDEX(Lookups!$B$2:$B$14,MATCH(G184,Lookups!$A$2:$A$14,0)),"Not found") | J184: =IFERROR(INDEX(Lookups!$E$2:$E$14,MATCH(G184,Lookups!$A$2:$A$14,0)),"") | K184: ET | L184: =IF(J184="n/a","n/a",IFERROR(IF(ABS(INDEX(Lookups!$H$2:$H$5,MATCH(J184,Lookups!$G$2:$G$5,0))-INDEX(Lookups!$H$2:$H$5,MATCH(K184,Lookups!$G$2:$G$5,0)))<=1,"Yes","No"),"Check")) | M184: 0 | N184: No (Allocated) | O184: 0 | Q184: =IF(N184<>"Yes","n/a",IF(OR(AND(O184<>"",O184>$W$1),P184="Y"),"Yes",IF(O184<>"","No","Pending"))) | S184: Carolina Prieto | T184: State | X184: D | Y184: 26.9 | Z184: 0.75 | AA184: 0.4614 | AB184: 4 | AC184: Maintain | AD184: 0 | AE184: imputed
A185: Maine Bureau of Insurance | B185: Maine | C185: ME | D185: State | E185: No State AE shown (ME) | F185: Halena Martin | G185: Halena Martin | H185: =IF(F185="(not in WIP)","New to Enterprise",IF(F185=G185,"No","Yes")) | I185: =IFERROR(INDEX(Lookups!$B$2:$B$14,MATCH(G185,Lookups!$A$2:$A$14,0)),"Not found") | J185: =IFERROR(INDEX(Lookups!$E$2:$E$14,MATCH(G185,Lookups!$A$2:$A$14,0)),"") | K185: ET | L185: =IF(J185="n/a","n/a",IFERROR(IF(ABS(INDEX(Lookups!$H$2:$H$5,MATCH(J185,Lookups!$G$2:$G$5,0))-INDEX(Lookups!$H$2:$H$5,MATCH(K185,Lookups!$G$2:$G$5,0)))<=1,"Yes","No"),"Check")) | M185: 0 | N185: No (Allocated) | O185: 0 | Q185: =IF(N185<>"Yes","n/a",IF(OR(AND(O185<>"",O185>$W$1),P185="Y"),"Yes",IF(O185<>"","No","Pending"))) | S185: Carolina Prieto | T185: State | X185: D | Y185: 26.9 | Z185: 0.75 | AA185: 0.4614 | AB185: 4 | AC185: Maintain | AD185: 0 | AE185: imputed
A186: Maine Attorney General | B186: Maine | C186: ME | D186: State | E186: No State AE shown (ME) | F186: Halena Martin | G186: Halena Martin | H186: =IF(F186="(not in WIP)","New to Enterprise",IF(F186=G186,"No","Yes")) | I186: =IFERROR(INDEX(Lookups!$B$2:$B$14,MATCH(G186,Lookups!$A$2:$A$14,0)),"Not found") | J186: =IFERROR(INDEX(Lookups!$E$2:$E$14,MATCH(G186,Lookups!$A$2:$A$14,0)),"") | K186: ET | L186: =IF(J186="n/a","n/a",IFERROR(IF(ABS(INDEX(Lookups!$H$2:$H$5,MATCH(J186,Lookups!$G$2:$G$5,0))-INDEX(Lookups!$H$2:$H$5,MATCH(K186,Lookups!$G$2:$G$5,0)))<=1,"Yes","No"),"Check")) | M186: 0 | N186: No (Allocated) | O186: 0 | Q186: =IF(N186<>"Yes","n/a",IF(OR(AND(O186<>"",O186>$W$1),P186="Y"),"Yes",IF(O186<>"","No","Pending"))) | S186: Carolina Prieto | T186: State | X186: D | Y186: 26.9 | Z186: 0.75 | AA186: 0.4614 | AB186: 4 | AC186: Maintain | AD186: 0 | AE186: imputed
A187: Maine Department of Agriculture, Conservation and Forestry | B187: Maine | C187: ME | D187: State | E187: No State AE shown (ME) | F187: Halena Martin | G187: Halena Martin | H187: =IF(F187="(not in WIP)","New to Enterprise",IF(F187=G187,"No","Yes")) | I187: =IFERROR(INDEX(Lookups!$B$2:$B$14,MATCH(G187,Lookups!$A$2:$A$14,0)),"Not found") | J187: =IFERROR(INDEX(Lookups!$E$2:$E$14,MATCH(G187,Lookups!$A$2:$A$14,0)),"") | K187: ET | L187: =IF(J187="n/a","n/a",IFERROR(IF(ABS(INDEX(Lookups!$H$2:$H$5,MATCH(J187,Lookups!$G$2:$G$5,0))-INDEX(Lookups!$H$2:$H$5,MATCH(K187,Lookups!$G$2:$G$5,0)))<=1,"Yes","No"),"Check")) | M187: 0 | N187: No (Allocated) | O187: 0 | Q187: =IF(N187<>"Yes","n/a",IF(OR(AND(O187<>"",O187>$W$1),P187="Y"),"Yes",IF(O187<>"","No","Pending"))) | S187: Carolina Prieto | T187: State | X187: D | Y187: 26.9 | Z187: 0.75 | AA187: 0.4614 | AB187: 4 | AC187: Maintain | AD187: 0 | AE187: imputed
A188: Maine Department of Transportation | B188: Maine | C188: ME | D188: State | E188: No State AE shown (ME) | F188: Halena Martin | G188: Halena Martin | H188: =IF(F188="(not in WIP)","New to Enterprise",IF(F188=G188,"No","Yes")) | I188: =IFERROR(INDEX(Lookups!$B$2:$B$14,MATCH(G188,Lookups!$A$2:$A$14,0)),"Not found") | J188: =IFERROR(INDEX(Lookups!$E$2:$E$14,MATCH(G188,Lookups!$A$2:$A$14,0)),"") | K188: ET | L188: =IF(J188="n/a","n/a",IFERROR(IF(ABS(INDEX(Lookups!$H$2:$H$5,MATCH(J188,Lookups!$G$2:$G$5,0))-INDEX(Lookups!$H$2:$H$5,MATCH(K188,Lookups!$G$2:$G$5,0)))<=1,"Yes","No"),"Check")) | M188: 0 | N188: No (Allocated) | O188: 0 | Q188: =IF(N188<>"Yes","n/a",IF(OR(AND(O188<>"",O188>$W$1),P188="Y"),"Yes",IF(O188<>"","No","Pending"))) | S188: Carolina Prieto | T188: State | X188: D | Y188: 26.9 | Z188: 0.75 | AA188: 0.4614 | AB188: 4 | AC188: Maintain | AD188: 0 | AE188: imputed
A189: Maine Department of Inland Fisheries & Wildlife | B189: Maine | C189: ME | D189: State | E189: No State AE shown (ME) | F189: Halena Martin | G189: Halena Martin | H189: =IF(F189="(not in WIP)","New to Enterprise",IF(F189=G189,"No","Yes")) | I189: =IFERROR(INDEX(Lookups!$B$2:$B$14,MATCH(G189,Lookups!$A$2:$A$14,0)),"Not found") | J189: =IFERROR(INDEX(Lookups!$E$2:$E$14,MATCH(G189,Lookups!$A$2:$A$14,0)),"") | K189: ET | L189: =IF(J189="n/a","n/a",IFERROR(IF(ABS(INDEX(Lookups!$H$2:$H$5,MATCH(J189,Lookups!$G$2:$G$5,0))-INDEX(Lookups!$H$2:$H$5,MATCH(K189,Lookups!$G$2:$G$5,0)))<=1,"Yes","No"),"Check")) | M189: 0 | N189: No (Allocated) | O189: 0 | Q189: =IF(N189<>"Yes","n/a",IF(OR(AND(O189<>"",O189>$W$1),P189="Y"),"Yes",IF(O189<>"","No","Pending"))) | S189: Carolina Prieto | T189: State | X189: D | Y189: 26.9 | Z189: 0.75 | AA189: 0.4614 | AB189: 4 | AC189: Maintain | AD189: 0 | AE189: imputed
A190: Maine Department of Marine Resources | B190: Maine | C190: ME | D190: State | E190: No State AE shown (ME) | F190: Halena Martin | G190: Halena Martin | H190: =IF(F190="(not in WIP)","New to Enterprise",IF(F190=G190,"No","Yes")) | I190: =IFERROR(INDEX(Lookups!$B$2:$B$14,MATCH(G190,Lookups!$A$2:$A$14,0)),"Not found") | J190: =IFERROR(INDEX(Lookups!$E$2:$E$14,MATCH(G190,Lookups!$A$2:$A$14,0)),"") | K190: ET | L190: =IF(J190="n/a","n/a",IFERROR(IF(ABS(INDEX(Lookups!$H$2:$H$5,MATCH(J190,Lookups!$G$2:$G$5,0))-INDEX(Lookups!$H$2:$H$5,MATCH(K190,Lookups!$G$2:$G$5,0)))<=1,"Yes","No"),"Check")) | M190: 0 | N190: No (Allocated) | O190: 0 | Q190: =IF(N190<>"Yes","n/a",IF(OR(AND(O190<>"",O190>$W$1),P190="Y"),"Yes",IF(O190<>"","No","Pending"))) | S190: Carolina Prieto | T190: State | X190: D | Y190: 26.9 | Z190: 0.75 | AA190: 0.4614 | AB190: 4 | AC190: Maintain | AD190: 0 | AE190: imputed
A191: Maine Department of General Services | B191: Maine | C191: ME | D191: State | E191: No State AE shown (ME) | F191: Halena Martin | G191: Halena Martin | H191: =IF(F191="(not in WIP)","New to Enterprise",IF(F191=G191,"No","Yes")) | I191: =IFERROR(INDEX(Lookups!$B$2:$B$14,MATCH(G191,Lookups!$A$2:$A$14,0)),"Not found") | J191: =IFERROR(INDEX(Lookups!$E$2:$E$14,MATCH(G191,Lookups!$A$2:$A$14,0)),"") | K191: ET | L191: =IF(J191="n/a","n/a",IFERROR(IF(ABS(INDEX(Lookups!$H$2:$H$5,MATCH(J191,Lookups!$G$2:$G$5,0))-INDEX(Lookups!$H$2:$H$5,MATCH(K191,Lookups!$G$2:$G$5,0)))<=1,"Yes","No"),"Check")) | M191: 0 | N191: No (Allocated) | O191: 0 | Q191: =IF(N191<>"Yes","n/a",IF(OR(AND(O191<>"",O191>$W$1),P191="Y"),"Yes",IF(O191<>"","No","Pending"))) | S191: Carolina Prieto | T191: State | X191: D | Y191: 26.9 | Z191: 0.75 | AA191: 0.4614 | AB191: 4 | AC191: Maintain | AD191: 0 | AE191: imputed
A192: Maine Treasurers Office | B192: Maine | C192: ME | D192: State | E192: No State AE shown (ME) | F192: Halena Martin | G192: Halena Martin | H192: =IF(F192="(not in WIP)","New to Enterprise",IF(F192=G192,"No","Yes")) | I192: =IFERROR(INDEX(Lookups!$B$2:$B$14,MATCH(G192,Lookups!$A$2:$A$14,0)),"Not found") | J192: =IFERROR(INDEX(Lookups!$E$2:$E$14,MATCH(G192,Lookups!$A$2:$A$14,0)),"") | K192: ET | L192: =IF(J192="n/a","n/a",IFERROR(IF(ABS(INDEX(Lookups!$H$2:$H$5,MATCH(J192,Lookups!$G$2:$G$5,0))-INDEX(Lookups!$H$2:$H$5,MATCH(K192,Lookups!$G$2:$G$5,0)))<=1,"Yes","No"),"Check")) | M192: 0 | N192: No (Allocated) | O192: 0 | Q192: =IF(N192<>"Yes","n/a",IF(OR(AND(O192<>"",O192>$W$1),P192="Y"),"Yes",IF(O192<>"","No","Pending"))) | S192: Carolina Prieto | T192: State | X192: D | Y192: 26.9 | Z192: 0.75 | AA192: 0.4614 | AB192: 4 | AC192: Maintain | AD192: 0 | AE192: imputed
A193: Maine Public Safety Department | B193: Maine | C193: ME | D193: State | E193: No State AE shown (ME) | F193: Halena Martin | G193: Halena Martin | H193: =IF(F193="(not in WIP)","New to Enterprise",IF(F193=G193,"No","Yes")) | I193: =IFERROR(INDEX(Lookups!$B$2:$B$14,MATCH(G193,Lookups!$A$2:$A$14,0)),"Not found") | J193: =IFERROR(INDEX(Lookups!$E$2:$E$14,MATCH(G193,Lookups!$A$2:$A$14,0)),"") | K193: ET | L193: =IF(J193="n/a","n/a",IFERROR(IF(ABS(INDEX(Lookups!$H$2:$H$5,MATCH(J193,Lookups!$G$2:$G$5,0))-INDEX(Lookups!$H$2:$H$5,MATCH(K193,Lookups!$G$2:$G$5,0)))<=1,"Yes","No"),"Check")) | M193: 0 | N193: No (Allocated) | O193: 0 | Q193: =IF(N193<>"Yes","n/a",IF(OR(AND(O193<>"",O193>$W$1),P193="Y"),"Yes",IF(O193<>"","No","Pending"))) | S193: Carolina Prieto | T193: State | X193: D | Y193: 26.9 | Z193: 0.75 | AA193: 0.4614 | AB193: 4 | AC193: Maintain | AD193: 0 | AE193: imputed
A194: The Independent Commission to Investigate the Facts of the Lewiston Tragedy | B194: Maine | C194: ME | D194: State | E194: No State AE shown (ME) | F194: Halena Martin | G194: Halena Martin | H194: =IF(F194="(not in WIP)","New to Enterprise",IF(F194=G194,"No","Yes")) | I194: =IFERROR(INDEX(Lookups!$B$2:$B$14,MATCH(G194,Lookups!$A$2:$A$14,0)),"Not found") | J194: =IFERROR(INDEX(Lookups!$E$2:$E$14,MATCH(G194,Lookups!$A$2:$A$14,0)),"") | K194: ET | L194: =IF(J194="n/a","n/a",IFERROR(IF(ABS(INDEX(Lookups!$H$2:$H$5,MATCH(J194,Lookups!$G$2:$G$5,0))-INDEX(Lookups!$H$2:$H$5,MATCH(K194,Lookups!$G$2:$G$5,0)))<=1,"Yes","No"),"Check")) | M194: 0 | N194: No (Allocated) | O194: 0 | Q194: =IF(N194<>"Yes","n/a",IF(OR(AND(O194<>"",O194>$W$1),P194="Y"),"Yes",IF(O194<>"","No","Pending"))) | S194: Carolina Prieto | T194: State | X194: D | Y194: 26.9 | Z194: 0.75 | AA194: 0.4614 | AB194: 4 | AC194: Maintain | AD194: 0 | AE194: imputed
... A200: Maine State Police | B200: Maine | C200: ME | D200: State | E200: No State AE shown (ME) | F200: Halena Martin | G200: Halena Martin | H200: =IF(F200="(not in WIP)","New to Enterprise",IF(F200=G200,"No","Yes")) | I200: =IFERROR(INDEX(Lookups!$B$2:$B$14,MATCH(G200,Lookups!$A$2:$A$14,0)),"Not found") | J200: =IFERROR(INDEX(Lookups!$E$2:$E$14,MATCH(G200,Lookups!$A$2:$A$14,0)),"") | K200: ET | L200: =IF(J200="n/a","n/a",IFERROR(IF(ABS(INDEX(Lookups!$H$2:$H$5,MATCH(J200,Lookups!$G$2:$G$5,0))-INDEX(Lookups!$H$2:$H$5,MATCH(K200,Lookups!$G$2:$G$5,0)))<=1,"Yes","No"),"Check")) | M200: 0 | N200: No (Allocated) | O200: 0 | Q200: =IF(N200<>"Yes","n/a",IF(OR(AND(O200<>"",O200>$W$1),P200="Y"),"Yes",IF(O200<>"","No","Pending"))) | S200: Carolina Prieto | T200: State | X200: D | Y200: 26.9 | Z200: 0.75 | AA200: 0.4614 | AB200: 4 | AC200: Maintain | AD200: 0 | AE200: imputed
A201: North Jersey Transportation Planning Authority | B201: Newark NJ | C201: NJ | D201: Local ENT | E201: Andrew Wyzkoski | F201: (not in WIP) | G201: Halena Martin | H201: =IF(F201="(not in WIP)","New to Enterprise",IF(F201=G201,"No","Yes")) | I201: =IFERROR(INDEX(Lookups!$B$2:$B$14,MATCH(G201,Lookups!$A$2:$A$14,0)),"Not found") | J201: =IFERROR(INDEX(Lookups!$E$2:$E$14,MATCH(G201,Lookups!$A$2:$A$14,0)),"") | K201: ET | L201: =IF(J201="n/a","n/a",IFERROR(IF(ABS(INDEX(Lookups!$H$2:$H$5,MATCH(J201,Lookups!$G$2:$G$5,0))-INDEX(Lookups!$H$2:$H$5,MATCH(K201,Lookups!$G$2:$G$5,0)))<=1,"Yes","No"),"Check")) | M201: 23334.06 | N201: Yes | O201: 3 | Q201: =IF(N201<>"Yes","n/a",IF(OR(AND(O201<>"",O201>$W$1),P201="Y"),"Yes",IF(O201<>"","No","Pending"))) | S201: Marcy Castro | T201: Local ENT | U201: Email & SMS, Engagement & Sentiment, Recurring Services | X201: B | Y201: 54 | Z201: 0.625 | AA201: 0.574 | AB201: 4 | AC201: Maintain | AD201: 0.3 | AE201: reported
...
